Workbook

Sheet Portada
C4: Proyecto: Modelo Financiero y Valoración
C5: VOLCAN COMPAÑÍA MINERA S.A.C
C7: Equipo de análisis:
C8: - Nombre de estudiante 1 | D8: Asencios Huaman, Roberth William
C9: - Nombre de estudiante 2 | D9: Romani Rojas, Renzo Nicolas
C10: - Nombre de estudiante 3 | D10: Rodriguez Alcalde, Jeremias Martin
C12: Leyenda de colores
C13: Azul | D13: Input externos o datos históricos
C14: Negro | D14: Fómula o cálculo
C15: Verde | D15: Fórmula vinculada a otra(s) hoja(s)

Sheet Buildup
C1: Check balance | E1: =ROUND(E53-E85,0) -> 0 | F1: =ROUND(F53-F85,0) -> 0 | G1: =ROUND(G53-G85,0) -> 0 | H1: =ROUND(H53-H85,0) -> 0 | I1: =ROUND(I53-I85,0) -> 0 | J1: =ROUND(J53-J85,0) -> 0 | K1: =ROUND(K53-K85,0) -> 0 | L1: =ROUND(L53-L85,0) -> 0 | ... O1: =ROUND(O53-O85,0) -> 0
B2: VOLCAN COMPAÑÍA MINERA S.A.C | Q2: Análisis vertical histórico | W2: Análisis horizontal histórico
B3: Buildup | E3: 2019 | F3: 2020 | G3: 2021 | H3: 2022 | I3: 2023 | J3: 2024 | K3: 2025 | L3: 2026 | M3: 2027 | N3: 2028 | O3: 2029 | Q3: 2020 | R3: 2021 | S3: 2022 | T3: 2023 | U3: 2024 | W3: '20 vs '19 | X3: '21 vs '20 | Y3: '22 vs '21 | Z3: '23 vs '22 | AA3: '24 vs '23 | AD3: CAGR '19-'24 | AE3: CAGR '24-'29
C4: Unidad | E4: Histórico | F4: Histórico | G4: Histórico | H4: Histórico | I4: Histórico | J4: Histórico | K4: Proyección | L4: Proyección | M4: Proyección | N4: Proyección | O4: Proyección | Q4: % | R4: % | S4: % | T4: % | U4: % | W4: % | X4: % | Y4: % | Z4: % | AA4: % | AD4: % | AE4: %
A5: x | B5: Estados de resultados
B6: Ventas | C6: USD mm | E6: =743578/1000 -> 743.578 | F6: =535469/1000 -> 535.469 | G6: =937399/1000 -> 937.399 | H6: =951266/1000 -> 951.266 | I6: =883086/1000 -> 883.086 | J6: =(960521/1000) -> 960.521 | K6: ='Supuestos '!L14 -> 922.27501 | L6: ='Supuestos '!M14 -> 1065.6195 | M6: ='Supuestos '!N14 -> 1182.8316 | N6: ='Supuestos '!O14 -> 1182.8316 | O6: ='Supuestos '!P14 -> 1221.3316 | Q6: =+F6/$F$6 -> 1 | R6: =+G6/$G$6 -> 1 | S6: =H6/$H$6 -> 1 | T6: =+I6/$I$6 -> 1 | U6: =+J6/$J$6 -> 1 | W6: =+(F6-E6)/E6 -> -0.27987514 | X6: =+(G6-F6)/F6 -> 0.75061301 | Y6: =(H6-G6)/G6 -> 0.01479306 | Z6: =(I6-H6)/H6 -> -0.071672907 | AA6: =(J6-I6)/I6 -> 0.087686816 | AD6: =IFERROR((J6/E6)^(1/(J$3-E$3))-1,"") -> 0.052533837 | AE6: =IFERROR((O6/J6)^(1/(O$3-J$3))-1,"") -> 0.049217067
B7: Costo de ventas | C7: USD mm | E7: =-619985/1000 -> -619.985 | F7: =-513266/1000 -> -513.266 | G7: =-656031/1000 -> -656.031 | H7: =-762743/1000 -> -762.743 | I7: =-(725507/1000) -> -725.507 | J7: =-(699588/1000) -> -699.588 | K7: =-'Supuestos '!L77 -> -571.77992 | L7: =-'Supuestos '!M77 -> -652.31607 | M7: =-'Supuestos '!N77 -> -724.60449 | N7: =-'Supuestos '!O77 -> -727.05096 | O7: =-'Supuestos '!P77 -> -750.15562 | Q7: =+F7/$F$6 -> -0.95853541 | R7: =+G7/$G$6 -> -0.6998418 | S7: =H7/$H$6 -> -0.80181884 | T7: =+I7/$I$6 -> -0.82155872 | U7: =+J7/$J$6 -> -0.72834222 | W7: =+(F7-E7)/E7 -> -0.17213158 | X7: =+(G7-F7)/F7 -> 0.27815012 | Y7: =(H7-G7)/G7 -> 0.16266304 | Z7: =(I7-H7)/H7 -> -0.04881854 | AA7: =(J7-I7)/I7 -> -0.035725362 | AD7: =IFERROR((J7/E7)^(1/(J$3-E$3))-1,"") -> 0.024453461 | AE7: =IFERROR((O7/J7)^(1/(O$3-J$3))-1,"") -> 0.014055681
B8: Utilidad bruta | C8: USD mm | E8: =E6+E7 -> 123.593 | F8: =F6+F7 -> 22.203 | G8: =G6+G7 -> 281.368 | H8: =H6+H7 -> 188.523 | I8: =I6+I7 -> 157.579 | J8: =J6+J7 -> 260.933 | K8: =K6+K7 -> 350.49509 | L8: =L6+L7 -> 413.30342 | ... O8: =O6+O7 -> 471.17599 | AD8: =IFERROR((J8/E8)^(1/(J$3-E$3))-1,"") -> 0.1612 | AE8: =IFERROR((O8/J8)^(1/(O$3-J$3))-1,"") -> 0.12546198
B9: Mg. bruto | C9: % | E9: =IFERROR(E8/E$6,"") -> 0.1662139 | F9: =IFERROR(F8/F$6,"") -> 0.041464585 | G9: =IFERROR(G8/G$6,"") -> 0.3001582 | H9: =IFERROR(H8/H$6,"") -> 0.19818116 | I9: =IFERROR(I8/I$6,"") -> 0.17844128 | J9: =IFERROR(J8/J$6,"") -> 0.27165778 | K9: =IFERROR(K8/K$6,"") -> 0.38003316 | L9: =IFERROR(L8/L$6,"") -> 0.38785272 | ... O9: =IFERROR(O8/O$6,"") -> 0.38578875
AD10: =IFERROR((J10/E10)^(1/(J$3-E$3))-1,"") | AE10: =IFERROR((O10/J10)^(1/(O$3-J$3))-1,"")
B11: Gasto de ventas | C11: USD mm | E11: =-23199/1000 -> -23.199 | F11: =-15435/1000 -> -15.435 | G11: =-21125/1000 -> -21.125 | H11: =-24852/1000 -> -24.852 | I11: =-(30563/1000) -> -30.563 | J11: =-(29081/1000) -> -29.081 | K11: =-'Supuestos '!L87 -> -27.912349 | L11: =-'Supuestos '!M87 -> -33.757614 | M11: =-'Supuestos '!N87 -> -36.334439 | N11: =-'Supuestos '!O87 -> -36.53567 | O11: =-'Supuestos '!P87 -> -37.978573 | Q11: =+F11/$F$6 -> -0.028825198 | R11: =+G11/$G$6 -> -0.022535761 | S11: =H11/$H$6 -> -0.026125185 | T11: =+I11/$I$6 -> -0.034609313 | U11: =+J11/$J$6 -> -0.030276277 | W11: =+(F11-E11)/E11 -> -0.3346696 | X11: =+(G11-F11)/F11 -> 0.3686427 | Y11: =(H11-G11)/G11 -> 0.17642604 | Z11: =(I11-H11)/H11 -> 0.22980042 | AA11: =(J11-I11)/I11 -> -0.048490004 | AD11: =IFERROR((J11/E11)^(1/(J$3-E$3))-1,"") -> 0.046232036 | AE11: =IFERROR((O11/J11)^(1/(O$3-J$3))-1,"") -> 0.054838231
B12: Gasto de administración | C12: USD mm | E12: =-58275/1000 -> -58.275 | F12: =-40752/1000 -> -40.752 | G12: =-57680/1000 -> -57.68 | H12: =-69646/1000 -> -69.646 | I12: =-(55157/1000) -> -55.157 | J12: =-(62875/1000) -> -62.875 | K12: =-'Supuestos '!L96 -> -25.903736 | L12: =-'Supuestos '!M96 -> -30.331794 | M12: =-'Supuestos '!N96 -> -33.465727 | N12: =-'Supuestos '!O96 -> -33.313603 | O12: =-'Supuestos '!P96 -> -32.360325 | Q12: =+F12/$F$6 -> -0.076105246 | R12: =+G12/$G$6 -> -0.061531962 | S12: =H12/$H$6 -> -0.073214012 | T12: =+I12/$I$6 -> -0.062459375 | U12: =+J12/$J$6 -> -0.065459266 | W12: =+(F12-E12)/E12 -> -0.30069498 | X12: =+(G12-F12)/F12 -> 0.41539066 | Y12: =+(H12-G12)/G12 -> 0.20745492 | Z12: =+(I12-H12)/H12 -> -0.20803779 | AA12: =+(J12-I12)/I12 -> 0.13992784 | AD12: =IFERROR((J12/E12)^(1/(J$3-E$3))-1,"") -> 0.015311121 | AE12: =IFERROR((O12/J12)^(1/(O$3-J$3))-1,"") -> -0.12439753
B13: Otros ingresos operativos | C13: USD mm | E13: =66840/1000 -> 66.84 | F13: =46907/1000 -> 46.907 | G13: =42505/1000 -> 42.505 | H13: =60068/1000 -> 60.068 | I13: =63429/1000 -> 63.429 | J13: =145115/1000 -> 145.115 | K13: ='Supuestos '!L102 -> 87.939327 | L13: ='Supuestos '!M102 -> 101.60729 | M13: ='Supuestos '!N102 -> 112.78351 | N13: ='Supuestos '!O102 -> 112.78351 | O13: ='Supuestos '!P102 -> 116.4545 | Q13: =+F13/$F$6 -> 0.087599842 | R13: =+G13/$G$6 -> 0.045343552 | S13: =H13/$H$6 -> 0.063145324 | T13: =+I13/$I$6 -> 0.071826527 | U13: =+J13/$J$6 -> 0.15107947 | W13: =+(F13-E13)/E13 -> -0.29821963 | X13: =+(G13-F13)/F13 -> -0.093845268 | Y13: =+(H13-G13)/G13 -> 0.41319845 | Z13: =+(I13-H13)/H13 -> 0.055953253 | AA13: =+(J13-I13)/I13 -> 1.2878336 | AD13: =IFERROR((J13/E13)^(1/(J$3-E$3))-1,"") -> 0.16771047 | AE13: =IFERROR((O13/J13)^(1/(O$3-J$3))-1,"") -> -0.04305099
B14: Otros gastos operativos | C14: USD mm | E14: =-96341/1000 -> -96.341 | F14: =-97347/1000 -> -97.347 | G14: =-79472/1000 -> -79.472 | H14: =-87465/1000 -> -87.465 | I14: =-(78507/1000) -> -78.507 | J14: =-(115282/1000) -> -115.282 | K14: =-'Supuestos '!L112 -> -89.707902 | L14: =-'Supuestos '!M112 -> -103.60858 | M14: =-'Supuestos '!N112 -> -114.98159 | N14: =-'Supuestos '!O112 -> -115.00624 | O14: =-'Supuestos '!P112 -> -119.21441 | Q14: =+F14/$F$6 -> -0.18179764 | R14: =+G14/$G$6 -> -0.084779267 | S14: =H14/$H$6 -> -0.091945891 | T14: =+I14/$I$6 -> -0.088900741 | U14: =+J14/$J$6 -> -0.12002028 | W14: =+(F14-E14)/E14 -> 0.010442076 | X14: =+(G14-F14)/F14 -> -0.18362148 | Y14: =+(H14-G14)/G14 -> 0.1005763 | Z14: =+(I14-H14)/H14 -> -0.10241811 | AA14: =+(J14-I14)/I14 -> 0.46842957 | AD14: =IFERROR((J14/E14)^(1/(J$3-E$3))-1,"") -> 0.036549557 | AE14: =IFERROR((O14/J14)^(1/(O$3-J$3))-1,"") -> 0.0067310142
B15: Ingreso por reversión de deterioro de activos de larga duración | C15: USD mm | E15: =35600/1000 -> 35.6 | F15: 0 | G15: 0 | H15: 0 | I15: 0 | J15: 0 | K15: 0 | L15: 0 | M15: 0 | N15: 0 | O15: 0 | W15: =+(F15-E15)/E15 -> -1 | AE15: =IFERROR((O15/J15)^(1/(O$3-J$3))-1,"")
B16: Pérdida por deterioro de activos de larga duración | C16: USD mm | E16: =-19613/1000 -> -19.613 | F16: =-10659/1000 -> -10.659 | G16: =-13397/1000 -> -13.397 | H16: =-126069/1000 -> -126.069 | I16: =-(36200/1000) -> -36.2 | J16: =(91700/1000) -> 91.7 | K16: 0 | L16: 0 | M16: 0 | N16: 0 | O16: 0 | Q16: =+F16/$F$6 -> -0.019905914 | R16: =+G16/$G$6 -> -0.014291673 | S16: =H16/$H$6 -> -0.1325276 | T16: =+I16/$I$6 -> -0.04099261 | U16: =+J16/$J$6 -> 0.095469022 | W16: =+(F16-E16)/E16 -> -0.45653393 | X16: =+(G16-F16)/F16 -> 0.25687213 | Y16: =+(H16-G16)/G16 -> 8.4102411 | Z16: =+(I16-H16)/H16 -> -0.71285566 | AA16: =+(J16-I16)/I16 -> -3.5331492 | AD16: =IFERROR((J16/E16)^(1/(J$3-E$3))-1,"") -> -2.3613352 | AE16: =IFERROR((O16/J16)^(1/(O$3-J$3))-1,"") -> -1
B17: Utilidad operativa | C17: USD mm | E17: =SUM(E8,E11:E16) -> 28.605 | F17: =SUM(F8,F11:F16) -> -95.083 | G17: =SUM(G8,G11:G16) -> 152.199 | H17: =SUM(H8,H11:H16) -> -59.441 | I17: =SUM(I8,I11:I16) -> 20.581 | J17: =SUM(J8,J11:J16) -> 290.51 | K17: =SUM(K8,K11:K16) -> 294.91043 | L17: =SUM(L8,L11:L16) -> 347.21272 | ... O17: =SUM(O8,O11:O16) -> 398.07719 | Q17: =+F17/$F$6 -> -0.17756957 | R17: =+G17/$G$6 -> 0.16236309 | S17: =H17/$H$6 -> -0.062486203 | T17: =+I17/$I$6 -> 0.023305771 | U17: =+J17/$J$6 -> 0.30245044 | W17: =+(F17-E17)/E17 -> -4.3239993 | X17: =+(G17-F17)/F17 -> -2.6006962 | Y17: =+(H17-G17)/G17 -> -1.3905479 | Z17: =+(I17-H17)/H17 -> -1.3462425 | AA17: =+(J17-I17)/I17 -> 13.115446 | AD17: =IFERROR((J17/E17)^(1/(J$3-E$3))-1,"") -> 0.58980488 | AE17: =IFERROR((O17/J17)^(1/(O$3-J$3))-1,"") -> 0.065028528
B18: Mg. operativo | C18: % | E18: =IFERROR(E17/E$6,"") -> 0.038469401 | F18: =IFERROR(F17/F$6,"") -> -0.17756957 | G18: =IFERROR(G17/G$6,"") -> 0.16236309 | H18: =IFERROR(H17/H$6,"") -> -0.062486203 | I18: =IFERROR(I17/I$6,"") -> 0.023305771 | J18: =IFERROR(J17/J$6,"") -> 0.30245044 | K18: =IFERROR(K17/K$6,"") -> 0.31976409 | L18: =IFERROR(L17/L$6,"") -> 0.3258318 | ... O18: =IFERROR(O17/O$6,"") -> 0.32593702 | AE18: =IFERROR((O18/J18)^(1/(O$3-J$3))-1,"") -> 0.015069772
AD19: =IFERROR((J19/E19)^(1/(J$3-E$3))-1,"") | AE19: =IFERROR((O19/J19)^(1/(O$3-J$3))-1,"")
B20: D&A | C20: USD mm | E20: =201340/1000 -> 201.34 | F20: =165496/1000 -> 165.496 | G20: =224794/1000 -> 224.794 | H20: =194238/1000 -> 194.238 | I20: =(207115/1000) -> 207.115 | J20: =(194964/1000) -> 194.964 | K20: ='Supuestos '!L119 -> 70.810647 | L20: ='Supuestos '!M119 -> 73.119451 | M20: ='Supuestos '!N119 -> 82.146703 | N20: ='Supuestos '!O119 -> 84.337603 | O20: ='Supuestos '!P119 -> 86.191289 | Q20: =+F20/$F$6 -> 0.30906738 | R20: =+G20/$G$6 -> 0.2398061 | S20: =H20/$H$6 -> 0.20418894 | T20: =+I20/$I$6 -> 0.23453548 | U20: =+J20/$J$6 -> 0.20297734 | W20: =+(F20-E20)/E20 -> -0.17802722 | X20: =+(G20-F20)/F20 -> 0.35830473 | Y20: =+(H20-G20)/G20 -> -0.13592889 | Z20: =+(I20-H20)/H20 -> 0.066294958 | AA20: =+(J20-I20)/I20 -> -0.05866789 | AD20: =IFERROR((J20/E20)^(1/(J$3-E$3))-1,"") -> -0.0064153522 | AE20: =IFERROR((O20/J20)^(1/(O$3-J$3))-1,"") -> -0.15062047
B21: EBITDA | C21: USD mm | E21: =E17+E20 -> 229.945 | F21: =F17+F20 -> 70.413 | G21: =G17+G20 -> 376.993 | H21: =H17+H20 -> 134.797 | I21: =I17+I20 -> 227.696 | J21: =J17+J20 -> 485.474 | K21: =K17+K20 -> 365.72108 | L21: =L17+L20 -> 420.33217 | ... O21: =O17+O20 -> 484.26848 | Q21: =+F21/$F$6 -> 0.13149781 | R21: =+G21/$G$6 -> 0.40216919 | S21: =H21/$H$6 -> 0.14170274 | T21: =+I21/$I$6 -> 0.25784125 | U21: =+J21/$J$6 -> 0.50542778 | W21: =+(F21-E21)/E21 -> -0.6937833 | X21: =+(G21-F21)/F21 -> 4.3540255 | Y21: =+(H21-G21)/G21 -> -0.64244164 | Z21: =+(I21-H21)/H21 -> 0.68917706 | AA21: =+(J21-I21)/I21 -> 1.1321147 | AD21: =IFERROR((J21/E21)^(1/(J$3-E$3))-1,"") -> 0.16120367 | AE21: =IFERROR((O21/J21)^(1/(O$3-J$3))-1,"") -> -0.00049713134
B22: Mg. EBITDA | C22: % | E22: =IFERROR(E21/E$6,"") -> 0.30924126 | F22: =IFERROR(F21/F$6,"") -> 0.13149781 | G22: =IFERROR(G21/G$6,"") -> 0.40216919 | H22: =IFERROR(H21/H$6,"") -> 0.14170274 | I22: =IFERROR(I21/I$6,"") -> 0.25784125 | J22: =IFERROR(J21/J$6,"") -> 0.50542778 | K22: =IFERROR(K21/K$6,"") -> 0.39654232 | L22: =IFERROR(L21/L$6,"") -> 0.39444865 | ... O22: =IFERROR(O21/O$6,"") -> 0.39650859
AD23: =IFERROR((J23/E23)^(1/(J$3-E$3))-1,"") | AE23: =IFERROR((O23/J23)^(1/(O$3-J$3))-1,"")
B24: Ingresos financieros | C24: USD mm | E24: =1842/1000 -> 1.842 | F24: =1820/1000 -> 1.82 | G24: =3179/1000 -> 3.179 | H24: =14751/1000 -> 14.751 | I24: =(5793/1000) -> 5.793 | J24: =(4888/1000) -> 4.888 | K24: ='Supuestos '!L165 -> 155.834 | L24: ='Supuestos '!M165 -> 149.62901 | M24: ='Supuestos '!N165 -> 172.88508 | N24: ='Supuestos '!O165 -> 191.90146 | O24: ='Supuestos '!P165 -> 191.90146 | Q24: =+F24/$F$6 -> 0.0033988896 | R24: =+G24/$G$6 -> 0.0033912987 | S24: =H24/$H$6 -> 0.015506704 | T24: =+I24/$I$6 -> 0.00655995 | U24: =+J24/$J$6 -> 0.0050889049 | W24: =+(F24-E24)/E24 -> -0.01194354 | X24: =+(G24-F24)/F24 -> 0.7467033 | Y24: =+(H24-G24)/G24 -> 3.6401384 | Z24: =+(I24-H24)/H24 -> -0.60728086 | AA24: =+(J24-I24)/I24 -> -0.15622303 | AD24: =IFERROR((J24/E24)^(1/(J$3-E$3))-1,"") -> 0.21553737 | AE24: =IFERROR((O24/J24)^(1/(O$3-J$3))-1,"") -> 1.0834804
B25: Gastos financieros | C25: USD mm | E25: =-48386/1000 -> -48.386 | F25: =-56473/1000 -> -56.473 | G25: =-61591/1000 -> -61.591 | H25: =-57124/1000 -> -57.124 | I25: =-(70526/1000) -> -70.526 | J25: =-(79206/1000) -> -79.206 | K25: =-'Supuestos '!L169 -> -39.662357 | L25: =-'Supuestos '!M169 -> -28.929886 | M25: =-'Supuestos '!N169 -> -19.4558 | N25: =-'Supuestos '!O169 -> -11.504982 | O25: =-'Supuestos '!P169 -> -5.3778645 | Q25: =+F25/$F$6 -> -0.10546456 | R25: =+G25/$G$6 -> -0.065704145 | S25: =H25/$H$6 -> -0.060050501 | T25: =+I25/$I$6 -> -0.079863116 | U25: =+J25/$J$6 -> -0.082461497 | W25: =+(F25-E25)/E25 -> 0.16713512 | X25: =+(G25-F25)/F25 -> 0.090627379 | Y25: =+(H25-G25)/G25 -> -0.07252683 | Z25: =+(I25-H25)/H25 -> 0.23461242 | AA25: =+(J25-I25)/I25 -> 0.12307518 | AD25: =IFERROR((J25/E25)^(1/(J$3-E$3))-1,"") -> 0.10358979 | AE25: =IFERROR((O25/J25)^(1/(O$3-J$3))-1,"") -> -0.41605714
B26: Utilidad antes de impuestos | C26: USD mm | E26: =SUM(E17,E24:E25) -> -17.939 | F26: =SUM(F17,F24:F25) -> -149.736 | G26: =SUM(G17,G24:G25) -> 93.787 | H26: =SUM(H17,H24:H25) -> -101.814 | I26: =SUM(I17,I24:I25) -> -44.152 | J26: =SUM(J17,J24:J25) -> 216.192 | K26: =SUM(K17,K24:K25) -> 411.08207 | L26: =SUM(L17,L24:L25) -> 467.91184 | ... O26: =SUM(O17,O24:O25) -> 584.60078 | Q26: =+F26/$F$6 -> -0.27963524 | R26: =+G26/$G$6 -> 0.10005025 | S26: =H26/$H$6 -> -0.10703 | T26: =+I26/$I$6 -> -0.049997395 | U26: =+J26/$J$6 -> 0.22507785 | W26: =+(F26-E26)/E26 -> 7.3469536 | X26: =+(G26-F26)/F26 -> -1.626349 | Y26: =+(H26-G26)/G26 -> -2.0855876 | Z26: =+(I26-H26)/H26 -> -0.56634647 | AA26: =+(J26-I26)/I26 -> -5.8965392 | AD26: =IFERROR((J26/E26)^(1/(J$3-E$3))-1,"") -> -2.6451605 | AE26: =IFERROR((O26/J26)^(1/(O$3-J$3))-1,"") -> 0.22012396
AD27: =IFERROR((J27/E27)^(1/(J$3-E$3))-1,"") | AE27: =IFERROR((O27/J27)^(1/(O$3-J$3))-1,"")
B28: Impuestos | C28: USD mm | E28: =-52389/1000 -> -52.389 | F28: =-706/1000 -> -0.706 | G28: =-53913/1000 -> -53.913 | H28: =20132/1000 -> 20.132 | I28: =34169/1000 -> 34.169 | J28: =-(79059/1000) -> -79.059 | K28: ='Supuestos '!L178 -> -121.26921 | L28: ='Supuestos '!M178 -> -138.03399 | M28: ='Supuestos '!N178 -> -159.19916 | N28: ='Supuestos '!O178 -> -166.41101 | O28: ='Supuestos '!P178 -> -172.45723 | Q28: =+F28/$F$6 -> -0.0013184704 | R28: =+G28/$G$6 -> -0.057513396 | S28: =H28/$H$6 -> 0.021163376 | T28: =+I28/$I$6 -> 0.038692721 | U28: =+J28/$J$6 -> -0.082308456 | W28: =+(F28-E28)/E28 -> -0.98652389 | X28: =+(G28-F28)/F28 -> 75.364023 | Y28: =+(H28-G28)/G28 -> -1.3734164 | Z28: =+(I28-H28)/H28 -> 0.69724816 | AA28: =+(J28-I28)/I28 -> -3.3137639 | AD28: =IFERROR((J28/E28)^(1/(J$3-E$3))-1,"") -> 0.08578101 | AE28: =IFERROR((O28/J28)^(1/(O$3-J$3))-1,"") -> 0.16881565
B29: Utilidad neta | C29: USD mm | E29: =E26+E28 -> -70.328 | F29: =F26+F28 -> -150.442 | G29: =G26+G28 -> 39.874 | H29: =H26+H28 -> -81.682 | I29: =I26+I28 -> -9.983 | J29: =J26+J28 -> 137.133 | K29: =K26+K28 -> 289.81286 | L29: =L26+L28 -> 329.87785 | ... O29: =O26+O28 -> 412.14355 | Q29: =+F29/$F$6 -> -0.28095371 | R29: =+G29/$G$6 -> 0.042536849 | S29: =H29/$H$6 -> -0.085866624 | T29: =+I29/$I$6 -> -0.011304675 | U29: =+J29/$J$6 -> 0.14276939 | W29: =+(F29-E29)/E29 -> 1.139148 | X29: =+(G29-F29)/F29 -> -1.2650457 | Y29: =+(H29-G29)/G29 -> -3.0485028 | Z29: =+(I29-H29)/H29 -> -0.87778213 | AA29: =+(J29-I29)/I29 -> -14.736652 | AD29: =IFERROR((J29/E29)^(1/(J$3-E$3))-1,"") -> -2.1428856 | AE29: =IFERROR((O29/J29)^(1/(O$3-J$3))-1,"") -> 0.24618152
B30: Mg. neto | C30: % | E30: =IFERROR(E29/E$6,"") -> -0.094580528 | F30: =IFERROR(F29/F$6,"") -> -0.28095371 | G30: =IFERROR(G29/G$6,"") -> 0.042536849 | H30: =IFERROR(H29/H$6,"") -> -0.085866624 | I30: =IFERROR(I29/I$6,"") -> -0.011304675 | J30: =IFERROR(J29/J$6,"") -> 0.14276939 | K30: =IFERROR(K29/K$6,"") -> 0.31423692 | L30: =IFERROR(L29/L$6,"") -> 0.30956439 | ... O30: =IFERROR(O29/O$6,"") -> 0.33745426 | AD30: =IFERROR((J30/E30)^(1/(J$3-E$3))-1,"") -> -2.0858421 | AE30: =IFERROR((O30/J30)^(1/(O$3-J$3))-1,"") -> 0.18772517
AD31: =IFERROR((J31/E31)^(1/(J$3-E$3))-1,"") | AE31: =IFERROR((O31/J31)^(1/(O$3-J$3))-1,"")
A32: x | B32: Balance general | AD32: =IFERROR((J32/E32)^(1/(J$3-E$3))-1,"") | AE32: =IFERROR((O32/J32)^(1/(O$3-J$3))-1,"")
B33: Activos | AD33: =IFERROR((J33/E33)^(1/(J$3-E$3))-1,"") | AE33: =IFERROR((O33/J33)^(1/(O$3-J$3))-1,"")
B34: Activos corrientes | AD34: =IFERROR((J34/E34)^(1/(J$3-E$3))-1,"") | AE34: =IFERROR((O34/J34)^(1/(O$3-J$3))-1,"")
B35: Excedentes | C35: USD mm | E35: 0 | F35: 0 | G35: 0 | H35: 0 | I35: 0 | J35: 0 | K35: =K141 -> 83.921489 | L35: =L141 -> 175.11669 | M35: =M141 -> 288.94676 | N35: =N141 -> 653.61591 | O35: =O141 -> 568.88822 | AD35: =IFERROR((J35/E35)^(1/(J$3-E$3))-1,"") | AE35: =IFERROR((O35/J35)^(1/(O$3-J$3))-1,"")
B36: Efectivo y equivalente de efectivo | C36: USD mm | E36: =33828/1000 -> 33.828 | F36: =114646/1000 -> 114.646 | G36: =231187/1000 -> 231.187 | H36: =73600/1000 -> 73.6 | I36: =61642/1000 -> 61.642 | J36: =(155834/1000) -> 155.834 | K36: ='Supuestos '!L185 -> 149.62901 | L36: ='Supuestos '!M185 -> 172.88508 | M36: ='Supuestos '!N185 -> 191.90146 | N36: ='Supuestos '!O185 -> 191.90146 | O36: ='Supuestos '!P185 -> 198.14766 | Q36: =+F36/$F$53 -> 0.055305937 | R36: =+G36/$G$53 -> 0.10674868 | S36: =H36/$H$53 -> 0.037249075 | T36: =I36/$I$53 -> 0.032872665 | U36: =J36/$J$53 -> 0.084654389 | W36: =+(F36-E36)/E36 -> 2.389086 | X36: =+(G36-F36)/F36 -> 1.0165291 | Y36: =+(H36-G36)/G36 -> -0.681643 | Z36: =+(I36-H36)/H36 -> -0.16247283 | AA36: =+(J36-I36)/I36 -> 1.5280491 | AD36: =IFERROR((J36/E36)^(1/(J$3-E$3))-1,"") -> 0.35730416 | AE36: =IFERROR((O36/J36)^(1/(O$3-J$3))-1,"") -> 0.049217067
A37: Op | B37: Cuentas por cobrar comerciales, neto | C37: USD mm | E37: =36159/1000 -> 36.159 | F37: =28781/1000 -> 28.781 | G37: =43806/1000 -> 43.806 | H37: =28586/1000 -> 28.586 | I37: =(20316/1000) -> 20.316 | J37: =(33477/1000) -> 33.477 | K37: ='Supuestos '!L194 -> 27.025464 | L37: ='Supuestos '!M194 -> 31.225893 | M37: ='Supuestos '!N194 -> 34.660565 | N37: ='Supuestos '!O194 -> 34.660565 | O37: ='Supuestos '!P194 -> 35.788732 | Q37: =+F37/$F$53 -> 0.013884132 | R37: =+G37/$G$53 -> 0.020227057 | S37: =H37/$H$53 -> 0.014467419 | T37: =I37/$I$53 -> 0.010834189 | U37: =J37/$J$53 -> 0.018185858 | W37: =+(F37-E37)/E37 -> -0.20404325 | X37: =+(G37-F37)/F37 -> 0.52204579 | Y37: =+(H37-G37)/G37 -> -0.34744099 | Z37: =+(I37-H37)/H37 -> -0.28930246 | AA37: =+(J37-I37)/I37 -> 0.64781453 | AD37: =IFERROR((J37/E37)^(1/(J$3-E$3))-1,"") -> -0.01529527 | AE37: =IFERROR((O37/J37)^(1/(O$3-J$3))-1,"") -> 0.013444465
A38: Op | B38: Otras cuentas por cobrar, neto | C38: USD mm | E38: =65344/1000 -> 65.344 | F38: =89530/1000 -> 89.53 | G38: =55971/1000 -> 55.971 | H38: =65389/1000 -> 65.389 | I38: =77038/1000 -> 77.038 | J38: =67424/1000 -> 67.424 | K38: ='Supuestos '!L195 -> 0.17736798 | L38: ='Supuestos '!M195 -> 0.20493538 | M38: ='Supuestos '!N195 -> 0.22747711 | N38: ='Supuestos '!O195 -> 0.22747711 | O38: ='Supuestos '!P195 -> 0.23488127 | Q38: =+F38/$F$53 -> 0.043189824 | R38: =+G38/$G$53 -> 0.025844145 | S38: =H38/$H$53 -> 0.033093475 | T38: =I38/$I$53 -> 0.041083099 | U38: =J38/$J$53 -> 0.036627036 | W38: =+(F38-E38)/E38 -> 0.37013345 | X38: =+(G38-F38)/F38 -> -0.37483525 | Y38: =+(H38-G38)/G38 -> 0.16826571 | Z38: =+(I38-H38)/H38 -> 0.17814923 | AA38: =+(J38-I38)/I38 -> -0.12479556 | AD38: =IFERROR((J38/E38)^(1/(J$3-E$3))-1,"") -> 0.0062867623 | AE38: =IFERROR((O38/J38)^(1/(O$3-J$3))-1,"") -> -0.67759128
A39: Op | B39: Otros activos financieros | C39: USD mm | E39: =5416/1000 -> 5.416 | F39: =223/1000 -> 0.223 | G39: 0 | H39: 0 | I39: =655/1000 -> 0.655 | J39: =948/1000 -> 0.948 | K39: ='Supuestos '!L196 -> 0.0021839996 | L39: ='Supuestos '!M196 -> 0.0025234475 | M39: ='Supuestos '!N196 -> 0.0028010125 | N39: ='Supuestos '!O196 -> 0.0028010125 | O39: ='Supuestos '!P196 -> 0.0028921826 | Q39: =+F39/$F$53 -> 0.00010757657 | R39: =+G39/$G$53 -> 0 | S39: =H39/$H$53 -> 0 | T39: =I39/$I$53 -> 0.00034930073 | U39: =J39/$J$53 -> 0.00051498621 | W39: =+(F39-E39)/E39 -> -0.9588257 | X39: =+(G39-F39)/F39 -> -1 | Y39: 0 | Z39: 0 | AA39: =+(J39-I39)/I39 -> 0.44732824 | AD39: =IFERROR((J39/E39)^(1/(J$3-E$3))-1,"") -> -0.29429054 | AE39: =IFERROR((O39/J39)^(1/(O$3-J$3))-1,"") -> -0.68603338
A40: Op | B40: Inventarios, neto | C40: USD mm | E40: =36709/1000 -> 36.709 | F40: =60961/1000 -> 60.961 | G40: =59824/1000 -> 59.824 | H40: =57093/1000 -> 57.093 | I40: =48305/1000 -> 48.305 | J40: =38070/1000 -> 38.07 | K40: ='Supuestos '!L197 -> 47.451933 | L40: ='Supuestos '!M197 -> 54.827144 | M40: ='Supuestos '!N197 -> 60.857819 | N40: ='Supuestos '!O197 -> 60.857819 | O40: ='Supuestos '!P197 -> 62.838681 | Q40: =+F40/$F$53 -> 0.029407962 | R40: =+G40/$G$53 -> 0.027623235 | S40: =H40/$H$53 -> 0.028894856 | T40: =I40/$I$53 -> 0.025760262 | U40: =J40/$J$53 -> 0.020680933 | W40: =+(F40-E40)/E40 -> 0.66065543 | X40: =+(G40-F40)/F40 -> -0.018651269 | Y40: =+(H40-G40)/G40 -> -0.045650575 | Z40: =+(I40-H40)/H40 -> -0.1539243 | AA40: =+(J40-I40)/I40 -> -0.21188283 | AD40: =IFERROR((J40/E40)^(1/(J$3-E$3))-1,"") -> 0.0073074931 | AE40: =IFERROR((O40/J40)^(1/(O$3-J$3))-1,"") -> 0.10542387
A41: Op | B41: Activos clasificados como mantenidos para la venta | C41: USD mm | E41: =301986/1000 -> 301.986 | F41: =0/1000 -> 0 | G41: 0 | H41: 0 | I41: =0/1000 -> 0 | J41: =0/1000 -> 0 | K41: ='Supuestos '!L198 -> 0 | L41: ='Supuestos '!M198 -> 0 | M41: ='Supuestos '!N198 -> 0 | N41: ='Supuestos '!O198 -> 0 | O41: ='Supuestos '!P198 -> 0 | Q41: =+F41/$F$53 -> 0 | R41: =+G41/$G$53 -> 0 | S41: =H41/$H$53 -> 0 | T41: =I41/$I$53 -> 0 | U41: =J41/$J$53 -> 0 | W41: =+(F41-E41)/E41 -> -1 | X41: =IFERROR((G41-F41)/F41,"-") -> - | Y41: =IFERROR((H41-G41)/G41,"-") -> - | Z41: =IFERROR((I41-H41)/H41,"-") -> - | AA41: =IFERROR((J41-I41)/I41,"-") -> - | AD41: =IFERROR((J41/E41)^(1/(J$3-E$3))-1,"") -> -1 | AE41: =IFERROR((O41/J41)^(1/(O$3-J$3))-1,"")
B42: Total activos corrientes | C42: USD mm | E42: =SUM(E35:E41) -> 479.442 | F42: =SUM(F35:F41) -> 294.141 | G42: =SUM(G35:G41) -> 390.788 | H42: =SUM(H35:H41) -> 224.668 | I42: =SUM(I35:I41) -> 207.956 | J42: =SUM(J35:J41) -> 295.753 | K42: =SUM(K35:K41) -> 308.20745 | L42: =SUM(L35:L41) -> 434.26226 | ... O42: =SUM(O35:O41) -> 865.90107 | Q42: =+F42/$F$53 -> 0.14189543 | R42: =+G42/$G$53 -> 0.18044311 | S42: =H42/$H$53 -> 0.11370483 | T42: =I42/$I$53 -> 0.11089952 | U42: =J42/$J$53 -> 0.1606632 | W42: =+(F42-E42)/E42 -> -0.38649305 | X42: =+(G42-F42)/F42 -> 0.32857371 | Y42: =+(H42-G42)/G42 -> -0.42508982 | Z42: =+(I42-H42)/H42 -> -0.074385315 | AA42: =+(J42-I42)/I42 -> 0.42219027 | AD42: =IFERROR((J42/E42)^(1/(J$3-E$3))-1,"") -> -0.092098745 | AE42: =IFERROR((O42/J42)^(1/(O$3-J$3))-1,"") -> 0.23967494
AD43: =IFERROR((J43/E43)^(1/(J$3-E$3))-1,"") | AE43: =IFERROR((O43/J43)^(1/(O$3-J$3))-1,"")
B44: Activos no corrientes | AD44: =IFERROR((J44/E44)^(1/(J$3-E$3))-1,"") | AE44: =IFERROR((O44/J44)^(1/(O$3-J$3))-1,"")
A45: Inv | B45: Inversiones financieras y en asociada | C45: USD mm | E45: =193794/1000 -> 193.794 | F45: =195346/1000 -> 195.346 | G45: =187751/1000 -> 187.751 | H45: =(147801+38704)/1000 -> 186.505 | I45: =((148118+37158)/1000) -> 185.276 | J45: =153047/1000 -> 153.047 | K45: =J45 -> 153.047 | L45: =K45 -> 153.047 | M45: =L45 -> 153.047 | N45: =M45 -> 153.047 | O45: =N45 -> 153.047 | Q45: =+F45/$F$53 -> 0.094236115 | R45: =+G45/$G$53 -> 0.086692466 | S45: =H45/$H$53 -> 0.094390472 | T45: =I45/$I$53 -> 0.098804645 | U45: =J45/$J$53 -> 0.083140395 | W45: =+(F45-E45)/E45 -> 0.0080085039 | X45: =+(G45-F45)/F45 -> -0.038879731 | Y45: =+(H45-G45)/G45 -> -0.0066364493 | Z45: =+(I45-H45)/H45 -> -0.0065896357 | AA45: =+(J45-I45)/I45 -> -0.17395129 | AD45: =IFERROR((J45/E45)^(1/(J$3-E$3))-1,"") -> -0.046113069 | AE45: =IFERROR((O45/J45)^(1/(O$3-J$3))-1,"") -> 0
A46: Op | B46: Inventarios(neto) | E46: 0 | F46: =7077/1000 -> 7.077 | G46: =6642/1000 -> 6.642 | H46: =6218/1000 -> 6.218 | I46: =5619/1000 -> 5.619 | J46: =5180/1000 -> 5.18 | K46: =J46 -> 5.18 | L46: =K46 -> 5.18 | M46: =L46 -> 5.18 | N46: =M46 -> 5.18 | O46: =N46 -> 5.18 | Q46: =+F46/$F$53 -> 0.0034139884 | R46: =+G46/$G$53 -> 0.0030668884 | S46: =H46/$H$53 -> 0.0031469395 | T46: =I46/$I$53 -> 0.0029965203 | U46: =J46/$J$53 -> 0.0028139542 | W46: =IFERROR((F46-E46)/E46,"0%") -> 0% | X46: =+(G46-F46)/F46 -> -0.061466723 | Y46: =+(H46-G46)/G46 -> -0.063836194 | Z46: =+(I46-H46)/H46 -> -0.096333226 | AA46: =+(J46-I46)/I46 -> -0.078127781 | AD46: =IFERROR((J46/E46)^(1/(J$3-E$3))-1,"") | AE46: =IFERROR((O46/J46)^(1/(O$3-J$3))-1,"") -> 0
A47: Op | B47: Otras cuentas por cobrar a largo plazo, neto | C47: USD mm | E47: =7990/1000 -> 7.99 | F47: =9477/1000 -> 9.477 | G47: =17445/1000 -> 17.445 | H47: =34262/1000 -> 34.262 | I47: =35970/1000 -> 35.97 | J47: =31834/1000 -> 31.834 | K47: =J47 -> 31.834 | L47: =K47 -> 31.834 | M47: =L47 -> 31.834 | N47: =M47 -> 31.834 | O47: =N47 -> 31.834 | Q47: =+F47/$F$53 -> 0.0045717632 | R47: =+G47/$G$53 -> 0.0080550839 | S47: =H47/$H$53 -> 0.017340052 | T47: =I47/$I$53 -> 0.01918221 | U47: =J47/$J$53 -> 0.017293324 | W47: =+(F47-E47)/E47 -> 0.18610763 | X47: =+(G47-F47)/F47 -> 0.8407724 | Y47: =+(H47-G47)/G47 -> 0.96400115 | Z47: =+(I47-H47)/H47 -> 0.049851147 | AA47: =+(J47-I47)/I47 -> -0.11498471 | AD47: =IFERROR((J47/E47)^(1/(J$3-E$3))-1,"") -> 0.31846585 | AE47: =IFERROR((O47/J47)^(1/(O$3-J$3))-1,"") -> 0
A48: Inv | B48: Inmuebles, maquinaria y equipo, neto | C48: USD mm | E48: =676790/1000 -> 676.79 | F48: =772063/1000 -> 772.063 | G48: =756719/1000 -> 756.719 | H48: =812912/1000 -> 812.912 | I48: =771778/1000 -> 771.778 | J48: =683121/1000 -> 683.121 | K48: ='Supuestos '!L231 -> 773.06565 | L48: ='Supuestos '!M231 -> 875.52842 | M48: ='Supuestos '!N231 -> 988.57793 | N48: ='Supuestos '!O231 -> 1100.6902 | O48: ='Supuestos '!P231 -> 1215.6214 | Q48: =+F48/$F$53 -> 0.37244795 | R48: =+G48/$G$53 -> 0.34940872 | S48: =H48/$H$53 -> 0.41141603 | T48: =I48/$I$53 -> 0.41157652 | U48: =J48/$J$53 -> 0.37109482 | W48: =+(F48-E48)/E48 -> 0.14077188 | X48: =+(G48-F48)/F48 -> -0.019874026 | Y48: =+(H48-G48)/G48 -> 0.074258741 | Z48: =+(I48-H48)/H48 -> -0.050600803 | AA48: =+(J48-I48)/I48 -> -0.11487371 | AD48: =IFERROR((J48/E48)^(1/(J$3-E$3))-1,"") -> 0.0018639291 | AE48: =IFERROR((O48/J48)^(1/(O$3-J$3))-1,"") -> 0.12217384
A49: Op | B49: Derecho de uso, neto | C49: USD mm | E49: =22463/1000 -> 22.463 | F49: =4285/1000 -> 4.285 | G49: =4385/1000 -> 4.385 | H49: =11385/1000 -> 11.385 | I49: =17926/1000 -> 17.926 | J49: =15663/1000 -> 15.663 | K49: ='Supuestos '!L232 -> 16.971542 | L49: ='Supuestos '!M232 -> 16.586652 | M49: ='Supuestos '!N232 -> 21.034327 | N49: ='Supuestos '!O232 -> 21.905322 | O49: ='Supuestos '!P232 -> 19.192708 | Q49: =+F49/$F$53 -> 0.0020671104 | R49: =+G49/$G$53 -> 0.0020247373 | S49: =H49/$H$53 -> 0.0057619663 | T49: =I49/$I$53 -> 0.0095596411 | U49: =J49/$J$53 -> 0.0085086803 | W49: =+(F49-E49)/E49 -> -0.80924186 | X49: =+(G49-F49)/F49 -> 0.023337223 | Y49: =+(H49-G49)/G49 -> 1.5963512 | Z49: =+(I49-H49)/H49 -> 0.57452789 | AA49: =+(J49-I49)/I49 -> -0.12624121 | AD49: =IFERROR((J49/E49)^(1/(J$3-E$3))-1,"") -> -0.069574856 | AE49: =IFERROR((O49/J49)^(1/(O$3-J$3))-1,"") -> 0.041483186
A50: Inv | B50: Concesiones mineras, costos de exploración y desarrollo y otros intangibles,neto | C50: USD mm | E50: =780122/1000 -> 780.122 | F50: =790553/1000 -> 790.553 | G50: =801983/1000 -> 801.983 | H50: =699938/1000 -> 699.938 | I50: =650650/1000 -> 650.65 | J50: =656228/1000 -> 656.228 | K50: ='Supuestos '!L233 -> 666.12658 | L50: ='Supuestos '!M233 -> 685.82414 | M50: ='Supuestos '!N233 -> 712.26227 | N50: ='Supuestos '!O233 -> 733.87003 | O50: ='Supuestos '!P233 -> 754.29085 | Q50: =+F50/$F$53 -> 0.38136764 | R50: =+G50/$G$53 -> 0.37030899 | S50: =H50/$H$53 -> 0.35423971 | T50: =I50/$I$53 -> 0.34698095 | U50: =J50/$J$53 -> 0.35648562 | W50: =+(F50-E50)/E50 -> 0.013370986 | X50: =+(G50-F50)/F50 -> 0.014458234 | Y50: =+(H50-G50)/G50 -> -0.12724085 | Z50: =+(I50-H50)/H50 -> -0.070417666 | AA50: =+(J50-I50)/I50 -> 0.0085729655 | AD50: =IFERROR((J50/E50)^(1/(J$3-E$3))-1,"") -> -0.033997064 | AE50: =IFERROR((O50/J50)^(1/(O$3-J$3))-1,"") -> 0.028245496
B51: Total activos no corrientes | C51: USD mm | E51: =SUM(E45:E50) -> 1681.159 | F51: =SUM(F45:F50) -> 1778.801 | G51: =SUM(G45:G50) -> 1774.925 | H51: =SUM(H45:H50) -> 1751.22 | I51: =SUM(I45:I50) -> 1667.219 | J51: =SUM(J45:J50) -> 1545.073 | K51: =SUM(K45:K50) -> 1646.2248 | L51: =SUM(L45:L50) -> 1768.0002 | ... O51: =SUM(O45:O50) -> 2179.1659 | Q51: =+F51/$F$53 -> 0.85810457 | R51: =+G51/$G$53 -> 0.81955689 | S51: =H51/$H$53 -> 0.88629517 | T51: =I51/$I$53 -> 0.88910048 | U51: =J51/$J$53 -> 0.8393368 | W51: =+(F51-E51)/E51 -> 0.05808017 | X51: =+(G51-F51)/F51 -> -0.0021789959 | Y51: =+(H51-G51)/G51 -> -0.013355494 | Z51: =+(I51-H51)/H51 -> -0.047967131 | AA51: =+(J51-I51)/I51 -> -0.073263321 | AD51: =IFERROR((J51/E51)^(1/(J$3-E$3))-1,"") -> -0.016740746 | AE51: =IFERROR((O51/J51)^(1/(O$3-J$3))-1,"") -> 0.071194317
AD52: =IFERROR((J52/E52)^(1/(J$3-E$3))-1,"") | AE52: =IFERROR((O52/J52)^(1/(O$3-J$3))-1,"")
B53: Total Activos | C53: USD mm | E53: =E42+E51 -> 2160.601 | F53: =F42+F51 -> 2072.942 | G53: =G42+G51 -> 2165.713 | H53: =H42+H51 -> 1975.888 | I53: =I42+I51 -> 1875.175 | J53: =J42+J51 -> 1840.826 | K53: =K42+K51 -> 1954.4322 | L53: =L42+L51 -> 2202.2625 | ... O53: =O42+O51 -> 3045.067 | Q53: =+F53/$F$53 -> 1 | R53: =+G53/$G$53 -> 1 | S53: =H53/$H$53 -> 1 | T53: =I53/$I$53 -> 1 | U53: =J53/$J$53 -> 1 | W53: =+(F53-E53)/E53 -> -0.040571582 | X53: =+(G53-F53)/F53 -> 0.044753302 | Y53: =+(H53-G53)/G53 -> -0.087650118 | Z53: =+(I53-H53)/H53 -> -0.050971006 | AA53: =+(J53-I53)/I53 -> -0.018317757 | AD53: =IFERROR((J53/E53)^(1/(J$3-E$3))-1,"") -> -0.031526742 | AE53: =IFERROR((O53/J53)^(1/(O$3-J$3))-1,"") -> 0.10590246
AD54: =IFERROR((J54/E54)^(1/(J$3-E$3))-1,"") | AE54: =IFERROR((O54/J54)^(1/(O$3-J$3))-1,"")
B55: Pasivos | AD55: =IFERROR((J55/E55)^(1/(J$3-E$3))-1,"") | AE55: =IFERROR((O55/J55)^(1/(O$3-J$3))-1,"")
B56: Pasivos corrientes | AD56: =IFERROR((J56/E56)^(1/(J$3-E$3))-1,"") | AE56: =IFERROR((O56/J56)^(1/(O$3-J$3))-1,"")
A57: Fin | B57: Obligaciones financieras | C57: USD mm | E57: =224476/1000 -> 224.476 | F57: =37179/1000 -> 37.179 | G57: =451144/1000 -> 451.144 | H57: =34697/1000 -> 34.697 | I57: =136326/1000 -> 136.326 | J57: =40701/1000 -> 40.701 | K57: ='Supuestos '!L251 -> 115.21508 | L57: ='Supuestos '!M251 -> 121.30996 | M57: ='Supuestos '!N251 -> 127.72726 | N57: ='Supuestos '!O251 -> 134.48403 | O57: ='Supuestos '!P251 | Q57: =+F57/$F$53 -> 0.017935379 | R57: =+G57/$G$53 -> 0.208312 | S57: =+H57/$H$53 -> 0.017560206 | T57: =+I57/$I$53 -> 0.072700415 | U57: =+J57/$J$53 -> 0.022110183 | W57: =+(F57-E57)/E57 -> -0.83437428 | X57: =+(G57-F57)/F57 -> 11.134377 | Y57: =+(H57-G57)/G57 -> -0.92309108 | Z57: =+(I57-H57)/H57 -> 2.9290429 | AA57: =+(J57-I57)/I57 -> -0.7014436 | AD57: =IFERROR((J57/E57)^(1/(J$3-E$3))-1,"") -> -0.28929883 | AE57: =IFERROR((O57/J57)^(1/(O$3-J$3))-1,"") -> -1
A58: Op | B58: Sobregiros bancarios | C58: USD mm | E58: =8448/1000 -> 8.448 | F58: =10070/1000 -> 10.07 | G58: =1168/1000 -> 1.168 | H58: =198/1000 -> 0.198 | I58: =1046/1000 -> 1.046 | J58: 0 | K58: ='Supuestos '!L202 -> 0.00063824022 | L58: ='Supuestos '!M202 -> 0.00073743863 | M58: ='Supuestos '!N202 -> 0.0008185527 | N58: ='Supuestos '!O202 -> 0.0015043309 | O58: ='Supuestos '!P202 -> 0.00084519578 | Q58: =+F58/$F$53 -> 0.0048578301 | R58: =+G58/$G$53 -> 0.0005393143 | S58: =+H58/$H$53 -> 0.00010020811 | T58: =+I58/$I$53 -> 0.0005578146 | U58: =+J58/$J$53 -> 0 | W58: =+(F58-E58)/E58 -> 0.19199811 | X58: =+(G58-F58)/F58 -> -0.88401192 | Y58: =+(H58-G58)/G58 -> -0.83047945 | Z58: =+(I58-H58)/H58 -> 4.2828283 | AA58: =+(J58-I58)/I58 -> -1 | AD58: =IFERROR((J58/E58)^(1/(J$3-E$3))-1,"") -> -1
A59: Op | B59: Cuentas por pagar comerciales | C59: USD mm | E59: =178175/1000 -> 178.175 | F59: =222640/1000 -> 222.64 | G59: =229693/1000 -> 229.693 | H59: =251239/1000 -> 251.239 | I59: =242213/1000 -> 242.213 | J59: =189711/1000 -> 189.711 | K59: ='Supuestos '!L203 -> 213.2878 | L59: ='Supuestos '!M203 -> 246.43803 | M59: ='Supuestos '!N203 -> 273.54481 | N59: ='Supuestos '!O203 -> 502.71891 | O59: ='Supuestos '!P203 -> 282.44843 | Q59: =+F59/$F$53 -> 0.10740291 | R59: =+G59/$G$53 -> 0.10605884 | S59: =+H59/$H$53 -> 0.12715245 | T59: =+I59/$I$53 -> 0.12916821 | U59: =+J59/$J$53 -> 0.10305754 | W59: =+(F59-E59)/E59 -> 0.24955802 | X59: =+(G59-F59)/F59 -> 0.031678944 | Y59: =+(H59-G59)/G59 -> 0.093803468 | Z59: =+(I59-H59)/H59 -> -0.035925951 | AA59: =+(J59-I59)/I59 -> -0.21675963 | AD59: =IFERROR((J59/E59)^(1/(J$3-E$3))-1,"") -> 0.012626175 | AE59: =IFERROR((O59/J59)^(1/(O$3-J$3))-1,"") -> 0.082852564
A60: Op | B60: Otros pasivos financieros | C60: USD mm | E60: =53407/1000 -> 53.407 | F60: =15107/1000 -> 15.107 | G60: =2241/1000 -> 2.241 | H60: 0 | I60: 0 | J60: 0 | K60: ='Supuestos '!L204 -> 0 | L60: ='Supuestos '!M204 -> 0 | M60: ='Supuestos '!N204 -> 0 | N60: ='Supuestos '!O204 -> 0 | O60: ='Supuestos '!P204 -> 0 | Q60: =+F60/$F$53 -> 0.0072877099 | R60: =+G60/$G$53 -> 0.0010347631 | S60: =+H60/$H$53 -> 0 | T60: =+I60/$I$53 -> 0 | U60: =+J60/$J$53 -> 0 | W60: =+(F60-E60)/E60 -> -0.71713446 | X60: =+(G60-F60)/F60 -> -0.85165817 | Y60: =+(H60-G60)/G60 -> -1 | Z60: =IFERROR((I60-H60)/H60,"-") -> - | AA60: =IFERROR((J60-I60)/I60,"-") -> - | AD60: =IFERROR((J60/E60)^(1/(J$3-E$3))-1,"") -> -1 | AE60: =IFERROR((O60/J60)^(1/(O$3-J$3))-1,"")
A61: Op | B61: Otras cuentas por pagar | C61: USD mm | E61: =55482/1000 -> 55.482 | F61: =65883/1000 -> 65.883 | G61: =70688/1000 -> 70.688 | H61: =74869/1000 -> 74.869 | I61: =60495/1000 -> 60.495 | J61: =89891/1000 -> 89.891 | K61: ='Supuestos '!L205 -> 0.11035598 | L61: ='Supuestos '!M205 -> 0.12750804 | M61: ='Supuestos '!N205 -> 0.14153321 | N61: ='Supuestos '!O205 -> 0.26010882 | O61: ='Supuestos '!P205 -> 0.14613997 | Q61: =+F61/$F$53 -> 0.031782365 | R61: =+G61/$G$53 -> 0.032639597 | S61: =+H61/$H$53 -> 0.037891318 | T61: =+I61/$I$53 -> 0.032260989 | U61: =+J61/$J$53 -> 0.048831883 | W61: =+(F61-E61)/E61 -> 0.18746621 | X61: =+(G61-F61)/F61 -> 0.072932319 | Y61: =+(H61-G61)/G61 -> 0.059147239 | Z61: =IFERROR(+(I61-H61)/H61,"-") -> -0.19198867 | AA61: =+(J61-I61)/I61 -> 0.48592446 | AD61: =IFERROR((J61/E61)^(1/(J$3-E$3))-1,"") -> 0.10131821 | AE61: =IFERROR((O61/J61)^(1/(O$3-J$3))-1,"") -> -0.72317165
A62: Op | B62: Pasivos asociados directamente con activos clasificados como mantenidos para la venta | C62: USD mm | E62: =171484/1000 -> 171.484 | F62: =0/1000 -> 0 | G62: 0 | H62: 0 | I62: 0 | J62: 0 | K62: ='Supuestos '!L206 -> 0 | L62: ='Supuestos '!M206 -> 0 | M62: ='Supuestos '!N206 -> 0 | N62: ='Supuestos '!O206 -> 0 | O62: ='Supuestos '!P206 -> 0 | Q62: =+F62/$F$53 -> 0 | R62: =+G62/$G$53 -> 0 | S62: =+H62/$H$53 -> 0 | T62: =+I62/$I$53 -> 0 | U62: =+J62/$J$53 -> 0 | W62: =+(F62-E62)/E62 -> -1 | X62: =IFERROR((G62-F62)/F62,"-") -> - | Y62: =IFERROR((H62-G62)/G62,"-") -> - | Z62: =IFERROR((I62-H62)/H62,"-") -> - | AA62: =IFERROR((J62-I62)/I62,"-") -> - | AD62: =IFERROR((J62/E62)^(1/(J$3-E$3))-1,"") -> -1 | AE62: =IFERROR((O62/J62)^(1/(O$3-J$3))-1,"")
B63: Ingresos diferidos | C63: USD mm | E63: 0 | F63: 0 | G63: 0 | H63: 0 | I63: =21/1000 -> 0.021 | J63: =21/1000 -> 0.021 | K63: =+J63 -> 0.021 | L63: =+K63 -> 0.021 | M63: =+L63 -> 0.021 | N63: =+M63 -> 0.021 | O63: =+N63 -> 0.021 | AD63: =IFERROR((J63/E63)^(1/(J$3-E$3))-1,"") | AE63: =IFERROR((O63/J63)^(1/(O$3-J$3))-1,"") -> 0
B64: Total pasivos corrientes | C64: USD mm | E64: =SUM(E57:E63) -> 691.472 | F64: =SUM(F57:F63) -> 350.879 | G64: =SUM(G57:G63) -> 754.934 | H64: =SUM(H57:H63) -> 361.003 | I64: =SUM(I57:I63) -> 440.101 | J64: =SUM(J57:J63) -> 320.324 | K64: =SUM(K57:K63) -> 328.63487 | L64: =SUM(L57:L63) -> 367.89723 | ... O64: =SUM(O57:O63) -> 282.61641 | Q64: =+F64/$F$53 -> 0.16926619 | R64: =+G64/$G$53 -> 0.34858451 | S64: =+H64/$H$53 -> 0.18270418 | T64: =+I64/$H$53 -> 0.2227358 | U64: =+J64/$J$53 -> 0.17401101 | W64: =+(F64-E64)/E64 -> -0.49256224 | X64: =+(G64-F64)/F64 -> 1.1515508 | Y64: =+(H64-G64)/G64 -> -0.52180853 | Z64: =+(I64-H64)/H64 -> 0.21910621 | AA64: =+(J64-I64)/I64 -> -0.27215798 | AD64: =IFERROR((J64/E64)^(1/(J$3-E$3))-1,"") -> -0.14264048 | AE64: =IFERROR((O64/J64)^(1/(O$3-J$3))-1,"") -> -0.024737378
R65: =+G65/$G$53 -> 0 | S65: =+H65/$H$53 -> 0 | T65: =+I65/$I$53 -> 0 | U65: =+J65/$J$53 -> 0 | AD65: =IFERROR((J65/E65)^(1/(J$3-E$3))-1,"") | AE65: =IFERROR((O65/J65)^(1/(O$3-J$3))-1,"")
B66: Pasivos no corrientes | AD66: =IFERROR((J66/E66)^(1/(J$3-E$3))-1,"") | AE66: =IFERROR((O66/J66)^(1/(O$3-J$3))-1,"")
A67: Fin | B67: Obligaciones financieras a largo plazo | C67: USD mm | E67: =576322/1000 -> 576.322 | F67: =888615/1000 -> 888.615 | G67: =485311/1000 -> 485.311 | H67: =776771/1000 -> 776.771 | I67: =667543/1000 -> 667.543 | J67: =709060/1000 -> 709.06 | K67: ='Supuestos '!L252 -> 525.11949 | L67: ='Supuestos '!M252 -> 403.80953 | M67: ='Supuestos '!N252 -> 276.08227 | N67: ='Supuestos '!O252 -> 141.59824 | O67: ='Supuestos '!P252 -> 141.59824 | Q67: =+F67/$F$53 -> 0.42867335 | R67: =+G67/$G$53 -> 0.22408833 | S67: =+H67/$H$53 -> 0.39312502 | T67: =+I67/$I$53 -> 0.35598971 | U67: =+J67/$J$53 -> 0.38518578 | W67: =+(F67-E67)/E67 -> 0.54187243 | X67: =+(G67-F67)/F67 -> -0.45385684 | Y67: =+(H67-G67)/G67 -> 0.60056335 | Z67: =+(I67-H67)/H67 -> -0.14061802 | AA67: =+(J67-I67)/I67 -> 0.062193746 | AD67: =IFERROR((J67/E67)^(1/(J$3-E$3))-1,"") -> 0.042325968 | AE67: =IFERROR((O67/J67)^(1/(O$3-J$3))-1,"") -> -0.27543897
A68: Op | B68: Otras cuentas por pagar | C68: USD mm | E68: 0 | F68: 0 | G68: =6400/1000 -> 6.4 | H68: =3200/1000 -> 3.2 | I68: 0 | J68: 0 | K68: =J68 -> 0 | L68: =K68 -> 0 | M68: =L68 -> 0 | N68: =M68 -> 0 | O68: =N68 -> 0 | Q68: =+F68/$F$53 -> 0 | R68: =+G68/$G$53 -> 0.0029551469 | S68: =+H68/$H$53 -> 0.001619525 | T68: =+I68/$I$53 -> 0 | U68: =+J68/$J$53 -> 0 | W68: =IFERROR((F68-E68)/E68,"-") -> - | X68: =IFERROR((G68-F68)/F68,"-") -> - | Y68: =IFERROR((H68-G68)/G68,"-") -> -0.5 | Z68: =IFERROR((I68-H68)/H68,"-") -> -1 | AA68: =IFERROR((J68-I68)/I68,"-") -> - | AD68: =IFERROR((J68/E68)^(1/(J$3-E$3))-1,"") | AE68: =IFERROR((O68/J68)^(1/(O$3-J$3))-1,"")
A69: Op | B69: Provisiones | C69: USD mm | E69: =179089/1000 -> 179.089 | F69: =229250/1000 -> 229.25 | G69: =262370/1000 -> 262.37 | H69: =323384/1000 -> 323.384 | I69: =323474/1000 -> 323.474 | J69: =237658/1000 -> 237.658 | K69: =J69 -> 237.658 | L69: =K69 -> 237.658 | M69: =L69 -> 237.658 | N69: =M69 -> 237.658 | O69: =N69 -> 237.658 | Q69: =+F69/$F$53 -> 0.11059161 | R69: =+G69/$G$53 -> 0.12114717 | S69: =+H69/$H$53 -> 0.16366515 | T69: =+I69/$I$53 -> 0.17250337 | U69: =+J69/$J$53 -> 0.129104 | W69: =+(F69-E69)/E69 -> 0.28008979 | X69: =+(G69-F69)/F69 -> 0.1444711 | Y69: =+(H69-G69)/G69 -> 0.23254945 | Z69: =+(I69-H69)/H69 -> 0.0002783069 | AA69: =+(J69-I69)/I69 -> -0.26529489 | AD69: =IFERROR((J69/E69)^(1/(J$3-E$3))-1,"") -> 0.058221803 | AE69: =IFERROR((O69/J69)^(1/(O$3-J$3))-1,"") -> 0
A70: Op | B70: Pasivo por impuesto a las ganancias diferido | C70: USD mm | E70: =142989/1000 -> 142.989 | F70: =187277/1000 -> 187.277 | G70: =199831/1000 -> 199.831 | H70: =136277/1000 -> 136.277 | I70: =78857/1000 -> 78.857 | J70: =123509/1000 -> 123.509 | K70: =J70 -> 123.509 | L70: =K70 -> 123.509 | M70: =L70 -> 123.509 | N70: =M70 -> 123.509 | O70: =N70 -> 123.509 | Q70: =+F70/$F$53 -> 0.090343579 | R70: =+G70/$G$53 -> 0.092270305 | S70: =+H70/$H$53 -> 0.068970002 | T70: =+I70/$I$53 -> 0.042053142 | U70: =+J70/$J$53 -> 0.067094337 | W70: =+(F70-E70)/E70 -> 0.30973012 | X70: =+(G70-F70)/F70 -> 0.067034393 | Y70: =+(H70-G70)/G70 -> -0.31803874 | Z70: =+(I70-H70)/H70 -> -0.4213477 | AA70: =+(J70-I70)/I70 -> 0.56624016 | AD70: =IFERROR((J70/E70)^(1/(J$3-E$3))-1,"") -> -0.02886592 | AE70: =IFERROR((O70/J70)^(1/(O$3-J$3))-1,"") -> 0
B71: Ingresos Diferidos | C71: USD mm | E71: 0 | F71: 0 | G71: 0 | H71: 0 | I71: =(577/1000) -> 0.577 | J71: =602/1000 -> 0.602 | K71: 0 | L71: 0 | M71: 0 | N71: 0 | O71: 0 | Q71: =+F71/$F$53 -> 0 | R71: =+G71/$G$53 -> 0 | S71: =+H71/$H$53 -> 0 | T71: =+I71/$I$53 -> 0.00030770461 | U71: =+J71/$J$53 -> 0.00032702711 | AD71: =IFERROR((J71/E71)^(1/(J$3-E$3))-1,"") | AE71: =IFERROR((O71/J71)^(1/(O$3-J$3))-1,"") -> -1
B72: Total pasivos no corrientes | C72: USD mm | E72: =SUM(E67:E71) -> 898.4 | F72: =SUM(F67:F71) -> 1305.142 | G72: =SUM(G67:G71) -> 953.912 | H72: =SUM(H67:H71) -> 1239.632 | I72: =SUM(I67:I71) -> 1070.451 | J72: =SUM(J67:J71) -> 1070.829 | K72: =SUM(K67:K71) -> 886.28649 | L72: =SUM(L67:L71) -> 764.97653 | ... O72: =SUM(O67:O71) -> 502.76524 | Q72: =+F72/$F$53 -> 0.62960855 | R72: =+G72/$G$53 -> 0.44046095 | S72: =+H72/$H$53 -> 0.62737969 | T72: =+I72/$I$53 -> 0.57085392 | U72: =+J72/$J$53 -> 0.58171114 | W72: =+(F72-E72)/E72 -> 0.45274043 | X72: =+(G72-F72)/F72 -> -0.26911248 | Y72: =+(H72-G72)/G72 -> 0.29952448 | Z72: =+(I72-H72)/H72 -> -0.13647679 | AA72: =+(J72-I72)/I72 -> 0.00035312219 | AD72: =IFERROR((J72/E72)^(1/(J$3-E$3))-1,"") -> 0.035738396 | AE72: =IFERROR((O72/J72)^(1/(O$3-J$3))-1,"") -> -0.14033544
AD73: =IFERROR((J73/E73)^(1/(J$3-E$3))-1,"") | AE73: =IFERROR((O73/J73)^(1/(O$3-J$3))-1,"")
B74: Total Pasivos | C74: USD mm | E74: =E64+E72 -> 1589.872 | F74: =F64+F72 -> 1656.021 | G74: =G64+G72 -> 1708.846 | H74: =H64+H72 -> 1600.635 | I74: =I64+I72 -> 1510.552 | J74: =J64+J72 -> 1391.153 | K74: =K64+K72 -> 1214.9214 | L74: =L64+L72 -> 1132.8738 | ... O74: =O64+O72 -> 785.38165 | Q74: =+F74/$F$53 -> 0.79887474 | R74: =+G74/$G$53 -> 0.78904546 | S74: =+H74/$H$53 -> 0.81008387 | T74: =+I74/$I$53 -> 0.80555255 | U74: =+J74/$J$53 -> 0.75572216 | W74: =+(F74-E74)/E74 -> 0.041606494 | X74: =+(G74-F74)/F74 -> 0.03189875 | Y74: =+(H74-G74)/G74 -> -0.063324021 | Z74: =+(I74-H74)/H74 -> -0.056279539 | AA74: =+(J74-I74)/I74 -> -0.07904329 | AD74: =IFERROR((J74/E74)^(1/(J$3-E$3))-1,"") -> -0.02635072 | AE74: =IFERROR((O74/J74)^(1/(O$3-J$3))-1,"") -> -0.10804864
AD75: =IFERROR((J75/E75)^(1/(J$3-E$3))-1,"") | AE75: =IFERROR((O75/J75)^(1/(O$3-J$3))-1,"")
B76: Patrimonio neto | AD76: =IFERROR((J76/E76)^(1/(J$3-E$3))-1,"") | AE76: =IFERROR((O76/J76)^(1/(O$3-J$3))-1,"")
A77: Fi | B77: Capital social | C77: USD mm | E77: =1134300/1000 -> 1134.3 | F77: =1134300/1000 -> 1134.3 | G77: =1134300/1000 -> 1134.3 | H77: =1134300/1000 -> 1134.3 | I77: =906680/1000 -> 906.68 | J77: =774294/1000 -> 774.294 | K77: =J77 -> 774.294 | L77: =K77 -> 774.294 | M77: =L77 -> 774.294 | N77: =M77 -> 774.294 | O77: =N77 -> 774.294 | Q77: =+F77/$F$53 -> 0.54719331 | R77: =+G77/$G$53 -> 0.52375361 | S77: =+H77/$H$53 -> 0.574071 | T77: =+I77/$I$53 -> 0.48351754 | U77: =+J77/$J$53 -> 0.42062313 | W77: =+(F77-E77)/E77 -> 0 | X77: =+(G77-F77)/F77 -> 0 | Y77: =+(H77-G77)/G77 -> 0 | Z77: =+(I77-H77)/H77 -> -0.20067002 | AA77: =+(J77-I77)/I77 -> -0.14601182 | AD77: =IFERROR((J77/E77)^(1/(J$3-E$3))-1,"") -> -0.073520973 | AE77: =IFERROR((O77/J77)^(1/(O$3-J$3))-1,"") -> 0
A78: Fi | B78: Acciones en tesorería | C78: USD mm | E78: =-60926/1000 -> -60.926 | F78: =-60930/1000 -> -60.93 | G78: =-60934/1000 -> -60.934 | H78: =-60934/1000 -> -60.934 | I78: =-60934/1000 -> -60.934 | J78: =-41511/1000 -> -41.511 | K78: =J78 -> -41.511 | L78: =K78 -> -41.511 | M78: =L78 -> -41.511 | N78: =M78 -> -41.511 | O78: =N78 -> -41.511 | Q78: =+F78/$F$53 -> -0.029393008 | R78: =+G78/$G$53 -> -0.028135769 | S78: =+H78/$H$53 -> -0.030838792 | T78: =+I78/$I$53 -> -0.0324951 | U78: =+J78/$J$53 -> -0.022550203 | W78: =+(F78-E78)/E78 -> 6.5653416e-05 | X78: =+(G78-F78)/F78 -> 6.5649106e-05 | Y78: =+(H78-G78)/G78 -> 0 | Z78: =+(I78-H78)/H78 -> 0 | AA78: =+(J78-I78)/I78 -> -0.31875472 | AD78: =IFERROR((J78/E78)^(1/(J$3-E$3))-1,"") -> -0.073869673 | AE78: =IFERROR((O78/J78)^(1/(O$3-J$3))-1,"") -> 0
A79: Fi | B79: Reserva legal | C79: USD mm | E79: =11755/1000 -> 11.755 | F79: =11755/1000 -> 11.755 | G79: =10695/1000 -> 10.695 | H79: =10695/1000 -> 10.695 | I79: =10416/1000 -> 10.416 | J79: =10492/1000 -> 10.492 | K79: =J79 -> 10.492 | L79: =K79 -> 10.492 | M79: =L79 -> 10.492 | N79: =M79 -> 10.492 | O79: =N79 -> 10.492 | Q79: =+F79/$F$53 -> 0.0056706845 | R79: =+G79/$G$53 -> 0.0049383275 | S79: =+H79/$H$53 -> 0.0054127562 | T79: =+I79/$I$53 -> 0.0055546816 | U79: =+J79/$J$53 -> 0.0056996153 | W79: =+(F79-E79)/E79 -> 0 | X79: =+(G79-F79)/F79 -> -0.090174394 | Y79: =+(H79-G79)/G79 -> 0 | Z79: =+(I79-H79)/H79 -> -0.026086957 | AA79: =+(J79-I79)/I79 -> 0.007296467 | AD79: =IFERROR((J79/E79)^(1/(J$3-E$3))-1,"") -> -0.022476674 | AE79: =IFERROR((O79/J79)^(1/(O$3-J$3))-1,"") -> 0
A80: Fi | B80: Mayor valor en adquisición de acciones de tesorería | C80: USD mm | E80: =-173217/1000 -> -173.217 | F80: =-173231/1000 -> -173.231 | G80: =-173234/1000 -> -173.234 | H80: =-173234/1000 -> -173.234 | I80: =-173234/1000 -> -173.234 | J80: =-162285/1000 -> -162.285 | K80: =J80 -> -162.285 | L80: =K80 -> -162.285 | M80: =L80 -> -162.285 | N80: =M80 -> -162.285 | O80: =N80 -> -162.285 | Q80: =+F80/$F$53 -> -0.083567702 | R80: =+G80/$G$53 -> -0.079989361 | S80: =+H80/$H$53 -> -0.087673998 | T80: =+I80/$I$53 -> -0.092382844 | U80: =+J80/$J$53 -> -0.088158794 | W80: =+(F80-E80)/E80 -> 8.0823476e-05 | X80: =+(G80-F80)/F80 -> 1.7317917e-05 | Y80: =+(H80-G80)/G80 -> 0 | Z80: =+(I80-H80)/H80 -> 0 | AA80: =+(J80-I80)/I80 -> -0.063203528 | AD80: =IFERROR((J80/E80)^(1/(J$3-E$3))-1,"") -> -0.01295359 | AE80: =IFERROR((O80/J80)^(1/(O$3-J$3))-1,"") -> 0
A81: Fi | B81: Resultado no realizados | C81: USD mm | E81: =-5918/1000 -> -5.918 | F81: =-9265/1000 -> -9.265 | G81: =-9504/1000 -> -9.504 | H81: =-9436/1000 -> -9.436 | I81: =-10208/1000 -> -10.208 | J81: =49406/1000 -> 49.406 | K81: =J81 -> 49.406 | L81: =K81 -> 49.406 | M81: =L81 -> 49.406 | N81: =M81 -> 49.406 | O81: =N81 -> 49.406 | Q81: =+F81/$F$53 -> -0.0044694931 | R81: =+G81/$G$53 -> -0.0043883931 | S81: =+H81/$H$53 -> -0.0047755743 | T81: =+I81/$I$53 -> -0.0054437586 | U81: =+J81/$J$53 -> 0.026839039 | W81: =+(F81-E81)/E81 -> 0.56556269 | X81: =+(G81-F81)/F81 -> 0.025796006 | Y81: =+(H81-G81)/G81 -> -0.0071548822 | Z81: =+(I81-H81)/H81 -> 0.081814328 | AA81: =+(J81-I81)/I81 -> -5.8399295 | AD81: =IFERROR((J81/E81)^(1/(J$3-E$3))-1,"") -> -2.5286954 | AE81: =IFERROR((O81/J81)^(1/(O$3-J$3))-1,"") -> 0
A82: Fi | B82: Resultados acumulados | C82: USD mm | E82: =-335265/1000 -> -335.265 | F82: =-485708/1000 -> -485.708 | G82: =-444656/1000 -> -444.656 | H82: =-526038/1000 -> -526.038 | I82: =-308122/1000 -> -308.122 | J82: =-180698/1000 -> -180.698 | K82: ='Supuestos '!L264 -> 109.11486 | L82: ='Supuestos '!M264 -> 438.99271 | M82: ='Supuestos '!N264 -> 819.45171 | N82: ='Supuestos '!O264 -> 1217.1458 | O82: ='Supuestos '!P264 -> 1629.2894 | Q82: =+F82/$F$53 -> -0.23430853 | R82: =+G82/$G$53 -> -0.20531622 | S82: =+H82/$H$53 -> -0.26622865 | T82: =+I82/$I$53 -> -0.1643164 | U82: =+J82/$J$53 -> -0.098161369 | W82: =+(F82-E82)/E82 -> 0.44872862 | X82: =+(G82-F82)/F82 -> -0.084519917 | Y82: =+(H82-G82)/G82 -> 0.18302238 | Z82: =+(I82-H82)/H82 -> -0.41425905 | AA82: =+(J82-I82)/I82 -> -0.41355048 | AD82: =IFERROR((J82/E82)^(1/(J$3-E$3))-1,"") -> -0.11628337 | AE82: =IFERROR((O82/J82)^(1/(O$3-J$3))-1,"") -> -2.5524191
B83: Total Patrimonio neto | C83: USD mm | E83: =SUM(E77:E82) -> 570.729 | F83: =SUM(F77:F82) -> 416.921 | G83: =SUM(G77:G82) -> 456.667 | H83: =SUM(H77:H82) -> 375.353 | I83: =SUM(I77:I82) -> 364.598 | J83: =SUM(J77:J82) -> 449.698 | K83: =SUM(K77:K82) -> 739.51086 | L83: =SUM(L77:L82) -> 1069.3887 | ... O83: =SUM(O77:O82) -> 2259.6854 | Q83: =+F83/$F$53 -> 0.20112526 | R83: =+G83/$G$53 -> 0.2108622 | S83: =+H83/$H$53 -> 0.18996674 | T83: =+I83/$I$53 -> 0.19443412 | U83: =+J83/$J$53 -> 0.24429142 | W83: =+(F83-E83)/E83 -> -0.26949393 | X83: =+(G83-F83)/F83 -> 0.095332209 | Y83: =+(H83-G83)/G83 -> -0.17805972 | Z83: =+(I83-H83)/H83 -> -0.028653028 | AA83: =+(J83-I83)/I83 -> 0.23340775 | AD83: =IFERROR((J83/E83)^(1/(J$3-E$3))-1,"") -> -0.046549385 | AE83: =IFERROR((O83/J83)^(1/(O$3-J$3))-1,"") -> 0.38110088
AD84: =IFERROR((J84/E84)^(1/(J$3-E$3))-1,"") | AE84: =IFERROR((O84/J84)^(1/(O$3-J$3))-1,"")
B85: Total Pasivos y Patrimonio | C85: USD mm | E85: =E74+E83 -> 2160.601 | F85: =F74+F83 -> 2072.942 | G85: =G74+G83 -> 2165.513 | H85: =H74+H83 -> 1975.988 | I85: =I74+I83 -> 1875.15 | J85: =J74+J83 -> 1840.851 | K85: =K74+K83 -> 1954.4322 | L85: =L74+L83 -> 2202.2625 | ... O85: =O74+O83 -> 3045.067 | Q85: =+F85/$F$53 -> 1 | R85: =+G85/$G$53 -> 0.99990765 | S85: =+H85/$H$53 -> 1.0000506 | T85: =+I85/$I$53 -> 0.99998667 | U85: =+J85/$J$53 -> 1.0000136 | W85: =+(F85-E85)/E85 -> -0.040571582 | X85: =+(G85-F85)/F85 -> 0.044656821 | Y85: =+(H85-G85)/G85 -> -0.087519678 | Z85: =+(I85-H85)/H85 -> -0.051031686 | AA85: =+(J85-I85)/I85 -> -0.018291337 | AD85: =IFERROR((J85/E85)^(1/(J$3-E$3))-1,"") -> -0.031524111 | AE85: =IFERROR((O85/J85)^(1/(O$3-J$3))-1,"") -> 0.10589945
A87: x | B87: Estado de flujo de efectivo (método indirecto)
B89: Utilidad neta | C89: USD mm | E89: =E29 -> -70.328 | F89: =F29 -> -150.442 | G89: =G29 -> 39.874 | H89: =H29 -> -81.682 | I89: =I29 -> -9.983 | J89: =J29 -> 137.133 | K89: =K29 -> 289.81286 | L89: =L29 -> 329.87785 | ... O89: =O29 -> 412.14355
B90: D&A | C90: USD mm | E90: =E20 -> 201.34 | F90: =F20 -> 165.496 | G90: =G20 -> 224.794 | H90: =H20 -> 194.238 | I90: =I20 -> 207.115 | J90: =J20 -> 194.964 | K90: =K20 -> 70.810647 | L90: =L20 -> 73.119451 | ... O90: =O20 -> 86.191289
B91: Utilidad neta ajustada | C91: USD mm | E91: =SUM(E89:E90) -> 131.012 | F91: =SUM(F89:F90) -> 15.054 | G91: =SUM(G89:G90) -> 264.668 | H91: =SUM(H89:H90) -> 112.556 | I91: =SUM(I89:I90) -> 197.132 | J91: =SUM(J89:J90) -> 332.097 | K91: =SUM(K89:K90) -> 360.62351 | L91: =SUM(L89:L90) -> 402.9973 | ... O91: =SUM(O89:O90) -> 498.33484
B93: Variación de capital de trabajo | C93: USD mm | E93: =SUM(E94:E96) -> 105.307 | F93: =SUM(F94:F96) -> 27.591 | G93: =SUM(G94:G96) -> -6.835 | H93: =SUM(H94:H96) -> 39.497 | I93: =SUM(I94:I96) -> 8.032 | J93: =SUM(J94:J96) -> -55.428 | K93: =SUM(K94:K96) -> 20.646399 | L93: =SUM(L94:L96) -> 21.574589 | ... O93: =SUM(O94:O96) -> -223.37952
B94: =B37 -> Cuentas por cobrar comerciales, neto | C94: USD mm | E94: =-(E37-D37) -> -36.159 | F94: =-(F37-E37) -> 7.378 | G94: =-(G37-F37) -> -15.025 | H94: =-(H37-G37) -> 15.22 | I94: =-(I37-H37) -> 8.27 | J94: =-(J37-I37) -> -13.161 | K94: =-(K37-J37) -> 6.4515363 | L94: =-(L37-K37) -> -4.2004294 | ... O94: =-(O37-N37) -> -1.1281671
B95: =B40 -> Inventarios, neto | C95: USD mm | E95: =-(E40-D40) -> -36.709 | F95: =-(F40-E40) -> -24.252 | G95: =-(G40-F40) -> 1.137 | H95: =-(H40-G40) -> 2.731 | I95: =-(I40-H40) -> 8.788 | J95: =-(J40-I40) -> 10.235 | K95: =-(K40-J40) -> -9.3819331 | L95: =-(L40-K40) -> -7.375211 | ... O95: =-(O40-N40) -> -1.9808619
B96: =B59 -> Cuentas por pagar comerciales | C96: USD mm | E96: =(E59-D59) -> 178.175 | F96: =(F59-E59) -> 44.465 | G96: =(G59-F59) -> 7.053 | H96: =(H59-G59) -> 21.546 | I96: =(I59-H59) -> -9.026 | J96: =(J59-I59) -> -52.502 | K96: =(K59-J59) -> 23.576795 | L96: =(L59-K59) -> 33.15023 | ... O96: =(O59-N59) -> -220.27049
B98: Variación de otras cuentas del balance | C98: USD mm | E98: =SUM(E100:E102,E104:E106,E108:E112,E114:E116) -> 207.7 | F98: =SUM(F100:F102,F104:F106,F108:F112,F114:F116) -> 189.295 | G98: =SUM(G100:G102,G104:G106,G108:G112,G114:G116) -> 61.26 | H98: =SUM(H100:H102,H104:H106,H108:H112,H114:H116) -> -37.581 | I98: =SUM(I100:I102,I104:I106,I108:I112,I114:I117) -> -93.412 | J98: =SUM(J100:J102,J104:J106,J108:J112,J114:J117) -> 3.37 | K98: =SUM(K100:K102,K104:K106,K108:K112,K114:K117) -> -23.4981 | L98: =SUM(L100:L102,L104:L106,L108:L112,L114:L117) -> 0.37423461 | M98: =SUM(M100:M102,M104:M106,M108:M112,M114:M117) -> -4.4563879 | N98: =SUM(N100:N102,N104:N106,N108:N112,N114:N117) -> -0.75173373 | O98: =SUM(O100:O102,O104:O106,O108:O112,O114:O117) -> 2.5904906
B99: Activos corrientes
B100: =B38 -> Otras cuentas por cobrar, neto | C100: USD mm | E100: =-(E38-D38) -> -65.344 | F100: =-(F38-E38) -> -24.186 | G100: =-(G38-F38) -> 33.559 | H100: =-(H38-G38) -> -9.418 | I100: =-(I38-H38) -> -11.649 | J100: =-(J38-I38) -> 9.614 | K100: =-(K38-J38) -> 67.246632 | L100: =-(L38-K38) -> -0.027567397 | ... O100: =-(O38-N38) -> -0.0074041552
B101: =B39 -> Otros activos financieros | C101: USD mm | E101: =-(E39-D39) -> -5.416 | F101: =-(F39-E39) -> 5.193 | G101: =-(G39-F39) -> 0.223 | H101: =-(H39-G39) -> 0 | I101: =-(I39-H39) -> -0.655 | J101: =-(J39-I39) -> -0.293 | K101: =-(K39-J39) -> 0.945816 | L101: =-(L39-K39) -> -0.00033944788 | ... O101: =-(O39-N39) -> -9.1170188e-05
B102: =B41 -> Activos clasificados como mantenidos para la venta | C102: USD mm | E102: =-(E41-D41) -> -301.986 | F102: =-(F41-E41) -> 301.986 | G102: =-(G41-F41) -> 0 | H102: =-(H41-G41) -> 0 | I102: =-(I41-H41) -> 0 | J102: =-(J41-I41) -> 0 | K102: =-(K41-J41) -> 0 | L102: =-(L41-K41) -> 0 | ... O102: =-(O41-N41) -> 0
B103: Activos no corrientes
B104: =B46 -> Inventarios(neto) | C104: USD mm | E104: =-(E46-D46) -> 0 | F104: =-(F46-E46) -> -7.077 | G104: =-(G46-F46) -> 0.435 | H104: =-(H46-G46) -> 0.424 | I104: =-(I46-H46) -> 0.599 | J104: =-(J46-I46) -> 0.439 | K104: =-(K46-J46) -> 0 | L104: =-(L46-K46) -> 0 | ... O104: =-(O46-N46) -> 0
...

Sheet Análisis Financiero
B2: VOLCAN COMPAÑÍA MINERA S.A.C
B3: Análisis financiero
E4: 2019 | F4: 2020 | G4: 2021 | H4: 2022 | I4: 2023 | J4: 2024 | K4: 2025 | L4: 2026 | M4: 2027 | N4: 2028 | O4: 2029
C5: Unidad | E5: Histórico | F5: Histórico | G5: Histórico | H5: Histórico | I5: Histórico | J5: Histórico | K5: Proyección | L5: Proyección | M5: Proyección | N5: Proyección | O5: Proyección
A6: x | B6: Indicadores de rentabilidad
B7: Margen bruto | C7: % | E7: =Buildup!E9 -> 0.1662139 | F7: =Buildup!F9 -> 0.041464585 | G7: =Buildup!G9 -> 0.3001582 | H7: =Buildup!H9 -> 0.19818116 | I7: =Buildup!I9 -> 0.17844128 | J7: =Buildup!J9 -> 0.27165778 | K7: =Buildup!K9 -> 0.38003316 | L7: =Buildup!L9 -> 0.38785272 | ... O7: =Buildup!O9 -> 0.38578875
B8: Margen EBITDA | C8: % | E8: =Buildup!E22 -> 0.30924126 | F8: =Buildup!F22 -> 0.13149781 | G8: =Buildup!G22 -> 0.40216919 | H8: =Buildup!H22 -> 0.14170274 | I8: =Buildup!I22 -> 0.25784125 | J8: =Buildup!J22 -> 0.50542778 | K8: =Buildup!K22 -> 0.39654232 | L8: =Buildup!L20 -> 73.119451 | M8: =Buildup!M20 -> 82.146703 | N8: =Buildup!N20 -> 84.337603 | O8: =Buildup!O20 -> 86.191289
B9: Margen operativo | C9: % | K9: =Buildup!K18 -> 0.31976409 | L9: =Buildup!L18 -> 0.3258318 | M9: =Buildup!M18 -> 0.32652905 | N9: =Buildup!N18 -> 0.32439837 | O9: =Buildup!O18 -> 0.32593702
B10: Margen neto | C10: % | E10: =Buildup!E30 -> -0.094580528 | F10: =Buildup!F30 -> -0.28095371 | G10: =Buildup!G30 -> 0.042536849 | H10: =Buildup!H30 -> -0.085866624 | I10: =Buildup!I30 -> -0.011304675 | J10: =Buildup!J30 -> 0.14276939 | K10: =Buildup!K30 -> 0.31423692 | L10: =Buildup!L30 -> 0.30956439 | ... O10: =Buildup!O30 -> 0.33745426
B11: Flujo de caja operativo (FCO) / EBITDA | C11: % | E11: =Buildup!E118/Buildup!E21 -> 1.9309791 | F11: =Buildup!F118/Buildup!F21 -> 3.293994 | G11: =Buildup!G118/Buildup!G21 -> 0.84641625 | H11: =Buildup!H118/Buildup!H21 -> 0.84921771 | I11: =Buildup!I118/Buildup!I21 -> 0.49079474 | J11: =Buildup!J118/Buildup!J21 -> 0.57683625 | K11: =Buildup!K118/Buildup!K21 -> 0.97826412 | L11: =Buildup!L118/Buildup!L21 -> 1.0109769 | ... O11: =Buildup!O118/Buildup!O21 -> 0.57312385
B12: Flujo de caja operativo / Ingresos | C12: % | E12: =E27/Buildup!E6 -> 0.59713843 | F12: =F27/Buildup!F6 -> 0.43315299 | G12: =G27/Buildup!G6 -> 0.34040254 | H12: =H27/Buildup!H6 -> 0.12033648 | I12: =I27/Buildup!I6 -> 0.12654713 | J12: =J27/Buildup!J6 -> 0.29154907 | K12: =Buildup!K118/Buildup!K6 -> 0.38792313 | L12: =Buildup!L118/Buildup!L6 -> 0.39877848 | M12: =Buildup!M118/Buildup!M6 -> 0.40224725 | N12: =Buildup!N118/Buildup!N6 -> 0.60063839 | O12: =Buildup!O118/Buildup!O6 -> 0.22724853
B13: ROA | C13: % | F13: =Buildup!F17/AVERAGE(Buildup!E53:F53) -> -0.044918878 | G13: =Buildup!G17/AVERAGE(Buildup!F53:G53) -> 0.071814762 | H13: =Buildup!H17/AVERAGE(Buildup!G53:H53) -> -0.028704359 | I13: =Buildup!I17/AVERAGE(Buildup!H53:I53) -> 0.010688477 | J13: =Buildup!J17/AVERAGE(Buildup!I53:J53) -> 0.15635625 | K13: =Buildup!K17/AVERAGE(Buildup!J53:K53) -> 0.15540994 | L13: =Buildup!L17/AVERAGE(Buildup!K53:L53) -> 0.16706193 | M13: =Buildup!M17/AVERAGE(Buildup!L53:M53) -> 0.16467524 | ... O13: =Buildup!O17/AVERAGE(Buildup!N53:O53) -> 0.13196965
B14: ROE | C14: % | F14: =Buildup!F29/AVERAGE(Buildup!E83:F83) -> -0.30464638 | G14: =Buildup!G29/AVERAGE(Buildup!F83:G83) -> 0.091287884 | H14: =Buildup!H29/AVERAGE(Buildup!G83:H83) -> -0.19634624 | I14: =Buildup!I29/AVERAGE(Buildup!H83:I83) -> -0.026982868 | J14: =Buildup!J29/AVERAGE(Buildup!I83:J83) -> 0.33681364 | K14: =Buildup!K29/AVERAGE(Buildup!J83:K83) -> 0.48740448 | L14: =Buildup!L29/AVERAGE(Buildup!K83:L83) -> 0.36472766 | M14: =Buildup!M29/AVERAGE(Buildup!L83:M83) -> 0.30204311 | ... O14: =Buildup!O29/AVERAGE(Buildup!N83:O83) -> 0.20069187
A17: x | B17: Indicadores de liquidez
B18: Razon corriente (activos corrientes / pasivos corrientes) | C18: x | E18: =Buildup!E42/Buildup!E64 -> 0.6933643 | F18: =Buildup!F42/Buildup!F64 -> 0.83829753 | G18: =Buildup!G42/Buildup!G64 -> 0.51764525 | H18: =Buildup!H42/Buildup!H64 -> 0.62234386 | I18: =Buildup!I42/Buildup!I64 -> 0.47251881 | J18: =Buildup!J42/Buildup!J64 -> 0.92329329 | K18: =Buildup!K42/Buildup!K64 -> 0.93784157 | L18: =Buildup!L42/Buildup!L64 -> 1.1803901 | ... O18: =Buildup!O42/Buildup!O64 -> 3.063874
B19: Razon acida | C19: x | E19: =(Buildup!E42-Buildup!E40)/Buildup!E64 -> 0.64027611 | F19: =(Buildup!F42-Buildup!F40)/Buildup!F64 -> 0.66455958 | G19: =(Buildup!G42-Buildup!G40)/Buildup!G64 -> 0.43840124 | H19: =(Buildup!H42-Buildup!H40)/Buildup!H64 -> 0.46419282 | I19: =(Buildup!I42-Buildup!I40)/Buildup!I64 -> 0.36275991 | J19: =(Buildup!J42-Buildup!J40)/Buildup!J64 -> 0.80444487 | K19: =(Buildup!K42-Buildup!K40)/Buildup!K64 -> 0.79345052 | L19: =(Buildup!L42-Buildup!L40)/Buildup!L64 -> 1.0313617 | ... O19: =(Buildup!O42-Buildup!O40)/Buildup!O64 -> 2.8415278
B21: Capital de trabajo | C21: USD mm | D21: us | E21: =Buildup!E37+Buildup!E40-Buildup!E59 -> -105.307 | F21: =Buildup!F37+Buildup!F40-Buildup!F59 -> -132.898 | G21: =Buildup!G37+Buildup!G40-Buildup!G59 -> -126.063 | H21: =Buildup!H37+Buildup!H40-Buildup!H59 -> -165.56 | I21: =Buildup!I37+Buildup!I40-Buildup!I59 -> -173.592 | J21: =Buildup!J37+Buildup!J40-Buildup!J59 -> -118.164 | K21: =Buildup!K37+Buildup!K40-Buildup!K59 -> -138.8104 | L21: =Buildup!L37+Buildup!L40-Buildup!L59 -> -160.38499 | ... O21: =Buildup!O37+Buildup!O40-Buildup!O59 -> -183.82101
B22: Días de rotación de cuentas por cobrar | C22: días | E22: =(Buildup!E37/Buildup!E6)*365 -> 17.749362 | F22: =(Buildup!F37/Buildup!F6)*365 -> 19.618437 | G22: =(Buildup!G37/Buildup!G6)*365 -> 17.056974 | H22: =(Buildup!H37/Buildup!H6)*365 -> 10.968425 | I22: =(Buildup!I37/Buildup!I6)*365 -> 8.3970757 | J22: =(Buildup!J37/Buildup!J6)*365 -> 12.72133 | K22: =(Buildup!K37/Buildup!K6)*365 -> 10.69561 | L22: 10.7 | M22: =(Buildup!M37/Buildup!M6)*365 -> 10.69561 | N22: =(Buildup!N37/Buildup!N6)*365 -> 10.69561 | O22: =(Buildup!O37/Buildup!O6)*365 -> 10.69561
B23: Días de rotación de inventarios | C23: días | E23: =-Buildup!E40/Buildup!E7*365 -> 21.611466 | F23: =-Buildup!F40/Buildup!F7*365 -> 43.351332 | G23: =-Buildup!G40/Buildup!G7*365 -> 33.284647 | H23: =-Buildup!H40/Buildup!H7*365 -> 27.321057 | I23: =-Buildup!I40/Buildup!I7*365 -> 24.302074 | J23: =-Buildup!J40/Buildup!J7*365 -> 19.862476 | K23: =-Buildup!K40/Buildup!K7*365 -> 30.291297 | L23: =-Buildup!L40/Buildup!L7*365 -> 30.678238 | ... O23: =-Buildup!O40/Buildup!O7*365 -> 30.575148
B24: Días de rotación de cuentas por pagar | C24: días | E24: =-Buildup!E59/Buildup!E7*365 -> 104.89588 | F24: =-Buildup!F59/Buildup!F7*365 -> 158.32648 | G24: =-Buildup!G59/Buildup!G7*365 -> 127.79571 | H24: =-Buildup!H59/Buildup!H7*365 -> 120.22691 | I24: =-Buildup!I59/Buildup!I7*365 -> 121.8565 | J24: =-Buildup!J59/Buildup!J7*365 -> 98.978992 | K24: =-Buildup!K59/Buildup!K7*365 -> 136.15386 | L24: =-Buildup!L59/Buildup!L7*365 -> 137.89309 | ... O24: =-Buildup!O59/Buildup!O7*365 -> 137.42972
B25: Ciclo de conversión de efectivo | C25: días | E25: =(Buildup!E46+Buildup!F46)*365/(2*Buildup!F7)+(Buildup!E37+Buildup!F37)*365/(2*Buildup!F6)-(Buildup!E59+Buildup!F59)*365/(2*Buildup!F7) -> 162.13292 | F25: =(Buildup!F46+Buildup!G46)*365/(2*Buildup!G7)+(Buildup!F37+Buildup!G37)*365/(2*Buildup!G6)-(Buildup!F59+Buildup!G59)*365/(2*Buildup!G7) -> 136.14898 | G25: =(Buildup!G46+Buildup!H46)*365/(2*Buildup!H7)+(Buildup!G37+Buildup!H37)*365/(2*Buildup!H6)-(Buildup!G59+Buildup!H59)*365/(2*Buildup!H7) -> 125.88303 | H25: =(Buildup!H46+Buildup!I46)*365/(2*Buildup!I7)+(Buildup!H37+Buildup!I37)*365/(2*Buildup!I6)-(Buildup!H59+Buildup!I59)*365/(2*Buildup!I7) -> 131.25557 | I25: =(Buildup!I46+Buildup!J46)*365/(2*Buildup!J7)+(Buildup!I37+Buildup!J37)*365/(2*Buildup!J6)-(Buildup!I59+Buildup!J59)*365/(2*Buildup!J7) -> 120.07869 | K25: =(Buildup!K46+Buildup!L46)*365/(2*Buildup!L7)+(Buildup!K37+Buildup!L37)*365/(2*Buildup!L6)-(Buildup!K59+Buildup!L59)*365/(2*Buildup!L7) -> 135.69637 | L25: =(Buildup!L46+Buildup!M46)*365/(2*Buildup!M7)+(Buildup!L37+Buildup!M37)*365/(2*Buildup!M6)-(Buildup!L59+Buildup!M59)*365/(2*Buildup!M7) -> 138.52006 | M25: =(Buildup!M46+Buildup!N46)*365/(2*Buildup!N7)+(Buildup!M37+Buildup!N37)*365/(2*Buildup!N6)-(Buildup!M59+Buildup!N59)*365/(2*Buildup!N7) -> 202.9482 | N25: =(Buildup!N46+Buildup!O46)*365/(2*Buildup!O7)+(Buildup!N37+Buildup!O37)*365/(2*Buildup!O6)-(Buildup!N59+Buildup!O59)*365/(2*Buildup!O7) -> 199.02437
B27: Flujo de caja operativo (FCO) | C27: USD mm | E27: =Buildup!E118 -> 444.019 | F27: =Buildup!F118 -> 231.94 | G27: =Buildup!G118 -> 319.093 | H27: =Buildup!H118 -> 114.472 | I27: =Buildup!I118 -> 111.752 | J27: =Buildup!J118 -> 280.039 | K27: =Buildup!K118 -> 357.77181 | L27: =Buildup!L118 -> 424.94613 | ... O27: =Buildup!O118 -> 277.54582
A29: x | B29: Solvencia
B31: Estructura de capital y endeudamiento:
B32: Pasivos / Patrimonio | C32: x | F32: =Buildup!F74/Buildup!F83 -> 3.9720259 | G32: =Buildup!G74/Buildup!G83 -> 3.7419958 | H32: =Buildup!H74/Buildup!H83 -> 4.2643458 | I32: =Buildup!I74/Buildup!I83 -> 4.1430617 | J32: =Buildup!J74/Buildup!J83 -> 3.0935272 | K32: =Buildup!K74/Buildup!K83 -> 1.6428716 | L32: =Buildup!L74/Buildup!L83 -> 1.0593657 | M32: =Buildup!M74/Buildup!M83 -> 0.71640951 | ... O32: =Buildup!O74/Buildup!O83 -> 0.34756239
B33: Pasivos / Activos | C33: % | F33: =Buildup!F74/Buildup!F53 -> 0.79887474 | G33: =Buildup!G74/Buildup!G53 -> 0.78904546 | H33: =Buildup!H74/Buildup!H53 -> 0.81008387 | I33: =Buildup!I74/Buildup!I53 -> 0.80555255 | J33: =Buildup!J74/Buildup!J53 -> 0.75572216 | K33: =Buildup!K74/Buildup!K53 -> 0.62162369 | L33: =Buildup!L74/Buildup!L53 -> 0.5144136 | M33: =Buildup!M74/Buildup!M53 -> 0.41738845 | ... O33: =Buildup!O74/Buildup!O53 -> 0.25791933
B34: Deuda / EBITDA | C34: x | F34: =(Buildup!F57+Buildup!F67)/Buildup!F21 -> 13.148055 | G34: =(Buildup!G57+Buildup!G67)/Buildup!G21 -> 2.4840116 | H34: =(Buildup!H57+Buildup!H67)/Buildup!H21 -> 6.0199263 | I34: =(Buildup!I57+Buildup!I67)/Buildup!I21 -> 3.5304485 | J34: =(Buildup!J57+Buildup!J67)/Buildup!J21 -> 1.5443896 | K34: =(Buildup!K57+Buildup!K67)/Buildup!K21 -> 1.7508823 | L34: =(Buildup!L57+Buildup!L67)/Buildup!L21 -> 1.2492964 | M34: =(Buildup!M57+Buildup!M67)/Buildup!M21 -> 0.86214898 | ... O34: =(Buildup!O57+Buildup!O67)/Buildup!O21 -> 0.29239615
B36: Cobertura
B37: EBITDA / Gastos financiero | C37: x | F37: =-Buildup!F21/Buildup!F25 -> 1.2468436 | G37: =-Buildup!G21/Buildup!G25 -> 6.1209105 | H37: =-Buildup!H21/Buildup!H25 -> 2.3597262 | I37: =-Buildup!I21/Buildup!I25 -> 3.2285398 | J37: =-Buildup!J21/Buildup!J25 -> 6.1292579 | K37: =-Buildup!K21/Buildup!K25 -> 9.2208609 | L37: =-Buildup!L21/Buildup!L25 -> 14.529341 | M37: =-Buildup!M21/Buildup!M25 -> 24.073827 | ... O37: =-Buildup!O21/Buildup!O25 -> 90.048472
B38: EBITDA / Servicio de deuda | C38: x | F38: =Buildup!F21/(Buildup!F25+(Buildup!E57-Buildup!F53)) -> -0.036963388 | G38: =Buildup!G21/(Buildup!G25+(Buildup!F57-Buildup!G53)) -> -0.1721331 | H38: =Buildup!H21/(Buildup!H25+(Buildup!G57-Buildup!H53)) -> -0.085213811 | I38: =Buildup!I21/(Buildup!I25+(Buildup!H57-Buildup!I53)) -> -0.11914993 | J38: =Buildup!J21/(Buildup!J25+(Buildup!I57-Buildup!J53)) -> -0.27217154 | K38: =Buildup!K21/(Buildup!K25+(Buildup!J57-Buildup!K53)) -> -0.18722345 | L38: =Buildup!L21/(Buildup!L25+(Buildup!K57-Buildup!L53)) -> -0.19864683 | M38: =Buildup!M21/(Buildup!M25+(Buildup!L57-Buildup!M53)) -> -0.1962458 | ... O38: =Buildup!O21/(Buildup!O25+(Buildup!N57-Buildup!O53)) -> -0.1660751
A40: x | B40: Fin

Sheet Hoja2
D4: 000 dolares
D5: 2024 | E5: 2023 | F5: 2022 | G5: 2021 | H5: 2020 | I5: 2019
C6: COSTO DE VENTAS | E6: =+SUM(E7:E11)/1000 -> 199.51 | F6: =+SUM(F7:F11)/1000 -> 218.859 | G6: =+SUM(G7:G11)/1000 -> 187.514 | H6: =+SUM(H7:H11)/1000 -> 157.647 | I6: =+SUM(I7:I11)/1000 -> 194.488
B7: =+D7+D10 -> 108424 | C7: dep | D7: 102935 | E7: 103455 | F7: 106245 | G7: 88788 | H7: 74415 | I7: 105200
C8: dep uso | D8: 6700 | E8: 4568 | F8: 5952 | G8: 4058 | H8: 15350 | I8: 18302
C9: amo | D9: 68515 | E9: 88829 | F9: 104267 | G9: 90736 | H9: 42387 | I9: 66534
C10: dep planta paraliza | D10: 5489 | E10: 1785 | F10: 1619 | G10: 3237 | H10: 22774 | I10: 3032
C11: amor plant parali | D11: 4703 | E11: 873 | F11: 776 | G11: 695 | H11: 2721 | I11: 1420
C13: GASTOS ADM
C14: amor | D14: 2063 | E14: 2559 | F14: 409 | G14: 1123 | H14: 1225 | I14: 622
C15: dep uso | D15: 744 | E15: 870 | F15: 1134 | G15: 768 | H15: 868 | I15: 522
C16: dep | D16: 720 | E16: 1528 | F16: 229 | G16: 810 | H16: 860 | I16: 1193
C18: GASTOS DE VENTAS
C19: dep | D19: 66 | E19: 43 | F19: 96 | G19: 91 | H19: 80 | I19: 44
C22: OTROS GASTOS
C23: dep | D23: 2625 | E23: 2411 | F23: 3264 | G23: 3741 | H23: 4554 | I23: 3987
C24: amo | D24: 404 | E24: 194 | F24: 803 | G24: 191 | H24: 262 | I24: 484
D26: =+SUM(D7:D24) -> 194964 | E26: =+SUM(E7:E24) -> 207115 | F26: =+SUM(F7:F24) -> 224794 | G26: =+SUM(G7:G24) -> 194238 | H26: =+SUM(H7:H24) -> 165496 | I26: =+SUM(I7:I24) -> 201340
D27: =+D26/1000 -> 194.964 | E27: =+E26/1000 -> 207.115 | F27: =+F26/1000 -> 224.794 | G27: =+G26/1000 -> 194.238 | H27: =+H26/1000 -> 165.496 | I27: =+I26/1000 -> 201.34

Sheet Supuestos 
B2: Minera Volcan | F2: Históricos | L2: Proyecciones
B3: Supuestos y drivers | D3: Año | F3: 2019 | G3: 2020 | H3: 2021 | I3: 2022 | J3: 2023 | K3: 2024 | L3: =K3+1 -> 2025 | M3: =L3+1 -> 2026 | N3: =M3+1 -> 2027 | O3: =N3+1 -> 2028 | P3: =O3+1 -> 2029
D4: Mes | F4: 43830 | G4: 44196 | H4: 44561 | I4: 44926 | J4: 45291 | K4: 45657 | L4: 46022 | M4: 46387 | N4: 46752 | O4: 47118 | P4: 47483
A5: x | B5: Indicadores macroecónomicos
B7: Inflación promedia (AoP) - BCRP | F7: 0.024 | G7: 0.02 | H7: 0.064 | I7: 0.085 | J7: 0.032 | K7: 0.02 | L7: 0.017 | M7: 0.02 | N7: 0.02 | O7: 0.02 | P7: 0.02
B8: Variación del PBI minería Perú | D8: % | F8: - | G8: -0.134 | H8: 0.081 | I8: 0.005 | J8: 0.081 | K8: 0.022 | L8: 0.02 | M8: 0.048 | N8: 0.015 | O8: 0.013 | P8: 0.015
A10: x | B10: Estados de Resultados
A12: x | B12: A) Ventas
B14: Ventas | D14: Miles | F14: =+Buildup!E6 -> 743.578 | G14: =+Buildup!F6 -> 535.469 | H14: =+Buildup!G6 -> 937.399 | I14: =+Buildup!H6 -> 951.266 | J14: =+Buildup!I6 -> 883.086 | K14: =+Buildup!J6 -> 960.521 | L14: =+(L18+L31+L44+L57)/1000 -> 922.27501 | M14: =+(M18+M31+M44+M57)/1000 -> 1065.6195 | N14: =+(N18+N31+N44+N57)/1000 -> 1182.8316 | O14: =+(O18+O31+O44+O57)/1000 -> 1182.8316 | P14: =+(P18+P31+P44+P57)/1000 -> 1221.3316
B15: Variación anual | D15: % | F15: =IFERROR(F14/#REF!-1," ") | G15: =IFERROR(G14/F14-1," ") -> -0.27987514 | H15: =IFERROR(H14/G14-1," ") -> 0.75061301 | I15: =IFERROR(I14/H14-1," ") -> 0.01479306 | J15: =IFERROR(J14/I14-1," ") -> -0.071672907 | K15: =IFERROR(K14/J14-1," ") -> 0.087686816 | L15: =IFERROR(L14/K14-1," ") -> -0.039817962 | M15: =IFERROR(M14/L14-1," ") -> 0.15542488 | N15: =IFERROR(N14/M14-1," ") -> 0.10999434 | ... P15: =IFERROR(P14/O14-1," ") -> 0.032549012
B17: Zinc
B18: Ventas por zinc | F18: =+F20*F22 -> 612660.7 | G18: =+G20*G22 -> 379620 | H18: =+H20*H22 -> 661483.9 | I18: =+I20*I22 -> 771541.3 | J18: =+J20*J22 -> 645176.4 | K18: =+K20*K22 -> 653801.6 | L18: =+L20*L22 -> 708894.13 | M18: =+M20*M22 -> 777021.8 | ... P18: =+P20*P22 -> 859521.8
B19: Variación anual(%) | D19: % | G19: =+G18/F18-1 -> -0.38037481 | H19: =+H18/G18-1 -> 0.74248959 | I19: =+I18/H18-1 -> 0.16637956 | J19: =+J18/I18-1 -> -0.16378242 | K19: =+K18/J18-1 -> 0.013368747 | L19: =+L18/K18-1 -> 0.084264908 | M19: =+M18/L18-1 -> 0.096104152 | N19: =+N18/M18-1 -> 0.056626468 | ... P19: =+P18/O18-1 -> 0.046892786
B20: Precio | D20: US$/TM | F20: 2539 | G20: 2280 | H20: 2981 | I20: 3449 | J20: 2642 | K20: 2768 | L20: 2700 | M20: 2750 | N20: 2750 | O20: 2750 | P20: 2750
B21: Variación anual(%) | D21: % | G21: =+G20/F20-1 -> -0.10200866 | H21: =+H20/G20-1 -> 0.30745614 | I21: =+I20/H20-1 -> 0.1569943 | J21: =+J20/I20-1 -> -0.23398086 | K21: =+K20/J20-1 -> 0.047691143 | L21: =+L20/K20-1 -> -0.024566474 | M21: =+M20/L20-1 -> 0.018518519 | N21: =+N20/M20-1 -> 0 | ... P21: =+P20/O20-1 -> 0
B22: Volumen de venta | D22: Miles TMF | F22: 241.3 | G22: 166.5 | H22: 221.9 | I22: 223.7 | J22: 244.2 | K22: 236.2 | L22: =+L27+L29 -> 262.55338 | M22: =+M27+M28 -> 282.55338 | N22: =+N27+N28 -> 298.55338 | O22: =+O27+O28 -> 298.55338 | P22: =+P27+P28 -> 312.55338
B24: Reservas total de cobre | F24: 1565 | G24: 1274 | H24: 1091 | I24: 1162 | J24: 1162 | K24: 1924
B25: % de uso | F25: =+F22/AVERAGE(D24:F24) -> 0.1541853 | G25: =+G22/AVERAGE(F24:G24) -> 0.11729482 | H25: =+H22/AVERAGE(G24:H24) -> 0.18765328 | I25: =+I22/AVERAGE(H24:I24) -> 0.19857967 | J25: =+J22/AVERAGE(I24:J24) -> 0.21015491 | K25: =+K22/AVERAGE(J24:K24) -> 0.15307842
B27: Cantidad vendida por reservas existentes | C27: =+AVERAGE(F25:K25) -> 0.17015773 | L27: =+$C$27*AVERAGE($J$24:$K$24) -> 262.55338 | M27: =+$C$27*AVERAGE($J$24:$K$24) -> 262.55338 | N27: =+$C$27*AVERAGE($J$24:$K$24) -> 262.55338 | O27: =+$C$27*AVERAGE($J$24:$K$24) -> 262.55338 | P27: =+$C$27*AVERAGE($J$24:$K$24) -> 262.55338
B28: Producción por nuevas reservas | D28: Miles TMF | L28: 0 | M28: 20 | N28: 36 | O28: 36 | P28: 50
B30: Plomo
B31: Ventas por Plomo | F31: =+F33*F35 -> 128219.5 | G31: =+G33*G35 -> 83516.4 | H31: =+H33*H35 -> 102508.8 | I31: =+I33*I35 -> 122505.7 | J31: =+J33*J35 -> 129625.6 | K31: =+K33*K35 -> 114913.4 | L31: =+L33*L35 -> 166636.43 | M31: =+M33*M35 -> 188136.43 | ... P31: =+P33*P35 -> 209636.43
B32: Variación anual (%) | D32: % | G32: =+G31/F31-1 -> -0.3486451 | H32: =+H31/G31-1 -> 0.22740923 | I32: =+I31/H31-1 -> 0.19507496 | J32: =+J31/I31-1 -> 0.058118928 | K32: =+K31/J31-1 -> -0.11349764 | L32: =+L31/K31-1 -> 0.45010446 | M32: =+M31/L31-1 -> 0.1290234 | N32: =+N31/M31-1 -> 0.11427877 | ... P32: =+P31/O31-1 -> 0
B33: Precio | D33: US$/TM | F33: 2539 | G33: 1998 | H33: 1824 | I33: 2153 | J33: 2132 | K33: 2078 | L33: 2150 | M33: 2150 | N33: 2150 | O33: 2150 | P33: 2150
B34: Variación anual (%) | D34: % | G34: =+G33/F33-1 -> -0.21307601 | H34: =+H33/G33-1 -> -0.087087087 | I34: =+I33/H33-1 -> 0.18037281 | J34: =+J33/I33-1 -> -0.0097538319 | K34: =+K33/J33-1 -> -0.02532833 | L34: =+L33/K33-1 -> 0.034648701 | M34: =+M33/L33-1 -> 0 | N34: =+N33/M33-1 -> 0 | ... P34: =+P33/O33-1 -> 0
B35: Volumen de venta | D35: Miles TMF | F35: 50.5 | G35: 41.8 | H35: 56.2 | I35: 56.9 | J35: 60.8 | K35: 55.3 | L35: =+L40+L41 -> 77.505318 | M35: =+M40+M41 -> 87.505318 | N35: =+N40+N41 -> 97.505318 | O35: =+O40+O41 -> 97.505318 | P35: =+P40+P41 -> 97.505318
B37: Reservas total de plomo | F37: 371 | G37: 299 | H37: 231 | I37: 279 | J37: 275 | K37: 620
B38: % de uso | F38: =+F35/AVERAGE(D37:F37) -> 0.1361186 | G38: =+G35/AVERAGE(F37:G37) -> 0.12477612 | H38: =+H35/AVERAGE(G37:H37) -> 0.21207547 | I38: =+I35/AVERAGE(H37:I37) -> 0.22313725 | J38: =+J35/AVERAGE(I37:J37) -> 0.21949458 | K38: =+K35/AVERAGE(J37:K37) -> 0.12357542
B40: Cantidad vendida por reservas existentes | C40: =+AVERAGE(F38:K38) -> 0.17319624 | L40: =+$C$40*AVERAGE($J$37:$K$37) -> 77.505318 | M40: =+$C$40*AVERAGE($J$37:$K$37) -> 77.505318 | N40: =+$C$40*AVERAGE($J$37:$K$37) -> 77.505318 | O40: =+$C$40*AVERAGE($J$37:$K$37) -> 77.505318 | P40: =+$C$40*AVERAGE($J$37:$K$37) -> 77.505318
B41: Producción por nuevas reservas | D41: Miles TMF | L41: 0 | M41: =20*50% -> 10 | N41: 20 | O41: 20 | P41: 20
B43: Cobre
B44: Ventas por Cobre | F44: =+F46*F48 -> 25894.6 | G44: =+G46*G48 -> 19436.8 | H44: =+H46*H48 -> 37206 | I44: =+I46*I48 -> 43013.4 | J44: =+J46*J48 -> 47196.8 | K44: =+K46*K48 -> 42630 | L44: =+L46*L48 -> 46292.412 | M44: =+M46*M48 -> 100049.85 | ... P44: =+P46*P48 -> 151749.85
B45: Variación anual(%) | D45: % | G45: =+G44/F44-1 -> -0.2493879 | H45: =+H44/G44-1 -> 0.91420398 | I45: =+I44/H44-1 -> 0.15608773 | J45: =+J44/I44-1 -> 0.097258064 | K45: =+K44/J44-1 -> -0.096760797 | L45: =+L44/K44-1 -> 0.085911617 | M45: =+M44/L44-1 -> 1.1612581 | N45: =+N44/M44-1 -> 0.51674239 | ... P45: =+P44/O44-1 -> 0
B46: Precio | D46: US$/TM | F46: 6022 | G46: 6074 | H46: 8268 | I46: 8434 | J46: 8428 | K46: 8700 | L46: 9000 | M46: 9400 | N46: 9400 | O46: 9400 | P46: 9400
B47: Variación anual(%) | D47: % | G47: =+G46/F46-1 -> 0.008635005 | H47: =+H46/G46-1 -> 0.36121172 | I47: =+I46/H46-1 -> 0.020077407 | J47: =+J46/I46-1 -> -0.00071140621 | K47: =+K46/J46-1 -> 0.032273374 | L47: =+L46/K46-1 -> 0.034482759 | M47: =+M46/L46-1 -> 0.044444444 | N47: =+N46/M46-1 -> 0 | ... P47: =+P46/O46-1 -> 0
B48: Volumen de venta | D48: Miles TMF | F48: 4.3 | G48: 3.2 | H48: 4.5 | I48: 5.1 | J48: 5.6 | K48: 4.9 | L48: =+L53+L54 -> 5.1436014 | M48: =+M53+M54 -> 10.643601 | N48: =+N53+N54 -> 16.143601 | O48: =+O53+O54 -> 16.143601 | P48: =+P53+P54 -> 16.143601
B50: Reservas total de cobre | D50: Miles TMF | F50: 65.4 | G50: 27.7 | H50: 23.5 | I50: 31.5 | J50: 29.7 | K50: 46.8
B51: % de uso | F51: =+F48/AVERAGE(D50:F50) -> 0.065749235 | G51: =+G48/AVERAGE(F50:G50) -> 0.068743287 | H51: =+H48/AVERAGE(G50:H50) -> 0.17578125 | I51: =+I48/AVERAGE(H50:I50) -> 0.18545455 | J51: =+J48/AVERAGE(I50:J50) -> 0.18300654 | K51: =+K48/AVERAGE(J50:K50) -> 0.12810458
B53: Cantidad vendida por reservas existentes | C53: =+AVERAGE(F51:K51) -> 0.13447324 | L53: =+$C$53*AVERAGE($J$50:$K$50) -> 5.1436014 | M53: =+$C$53*AVERAGE($J$50:$K$50) -> 5.1436014 | N53: =+$C$53*AVERAGE($J$50:$K$50) -> 5.1436014 | O53: =+$C$53*AVERAGE($J$50:$K$50) -> 5.1436014 | P53: =+$C$53*AVERAGE($J$50:$K$50) -> 5.1436014
B54: Producción por nuevas reservas | D54: Miles TMF | L54: 0 | M54: =11*50% -> 5.5 | N54: =11*100% -> 11 | O54: =11*100% -> 11 | P54: =11*100% -> 11
B56: Plata
B57: Ventas por Plata | F57: =+F59*F61 -> 251.16 | G57: =+G59*G61 -> 242 | H57: =+H59*H61 -> 300 | I57: =+I59*I61 -> 316.8 | J57: =+J59*J61 -> 354.96 | K57: =+K59*K61 -> 394.8 | L57: =+L59*L61 -> 452.0341 | M57: =+M59*M61 -> 411.40729 | ... P57: =+P59*P61 -> 423.51779
B58: Variación anual (%) | D58: % | G58: =+G57/F57-1 -> -0.036470776 | H58: =+H57/G57-1 -> 0.23966942 | I58: =+I57/H57-1 -> 0.056 | J58: =+J57/I57-1 -> 0.12045455 | K58: =+K57/J57-1 -> 0.112238 | L58: =+L57/K57-1 -> 0.14496986 | M58: =+M57/L57-1 -> -0.089875546 | N58: =+N57/M57-1 -> 0.029436766 | ... P58: =+P57/O57-1 -> 0
B59: Precio | D59: US$/OZ | F59: 16.1 | G59: 20 | H59: 20 | I59: 22 | J59: 23.2 | K59: 28.2 | L59: 30 | M59: 26.5 | N59: 26.5 | O59: 26.5 | P59: 26.5
B60: Variación anual (%) | D60: % | G60: =+G59/F59-1 -> 0.24223602 | H60: =+H59/G59-1 -> 0 | I60: =+I59/H59-1 -> 0.1 | J60: =+J59/I59-1 -> 0.054545455 | K60: =+K59/J59-1 -> 0.21551724 | L60: =+L59/K59-1 -> 0.063829787 | M60: =+M59/L59-1 -> -0.11666667 | N60: =+N59/M59-1 -> 0 | ... P60: =+P59/O59-1 -> 0
B61: Volumen de venta | D61: Millones OZ | F61: 15.6 | G61: 12.1 | H61: 15 | I61: 14.4 | J61: 15.3 | K61: 14 | L61: =+L66+L67 -> 15.067803 | M61: =+M66+M67/1000 -> 15.524803 | N61: =+N66+N67/1000 -> 15.981803 | O61: =+O66+O67/1000 -> 15.981803 | P61: =+P66+P67/1000 -> 15.981803
B63: Reservas total de plata | F63: 99 | G63: 75 | H63: 61 | I63: 75 | J63: 64 | K63: 97
B64: % de uso | F64: =+F61/AVERAGE(D63:F63) -> 0.15757576 | G64: =+G61/AVERAGE(F63:G63) -> 0.13908046 | H64: =+H61/AVERAGE(G63:H63) -> 0.22058824 | I64: =+I61/AVERAGE(H63:I63) -> 0.21176471 | J64: =+J61/AVERAGE(I63:J63) -> 0.22014388 | K64: =+K61/AVERAGE(J63:K63) -> 0.17391304
B66: Cantidad vendida por reservas existentes | C66: =+AVERAGE(F64:K64) -> 0.18717768 | L66: =+$C$66*AVERAGE($J$63:$K$63) -> 15.067803 | M66: =+$C$66*AVERAGE($J$63:$K$63) -> 15.067803 | N66: =+$C$66*AVERAGE($J$63:$K$63) -> 15.067803 | O66: =+$C$66*AVERAGE($J$63:$K$63) -> 15.067803 | P66: =+$C$66*AVERAGE($J$63:$K$63) -> 15.067803
B67: Producción por nuevas reservas | D67: Mil OZ | L67: 0 | M67: =914*50% -> 457 | N67: =914*100% -> 914 | O67: =914*100% -> 914 | P67: =914*100% -> 914
A70: x | B70: B) Costos de ventas
B72: Costos sin D&A | D72: USD mm | F72: =+F77-F74-F75-F76 -> 445.219 | G72: =+G77-G74-G75-G76 -> 373.69 | H72: =+H77-H74-H75-H76 -> 473.27 | I72: =+I77-I74-I75-I76 -> 550.612 | J72: =+J77-J74-J75-J76 -> 531.438 | K72: =+K77-K74-K75-K76 -> 522.649 | L72: =L14*L73 -> 501.83818 | M72: =M14*M73 -> 579.83632 | N72: =N14*N73 -> 643.61503 | O72: =O14*O73 -> 643.61503 | P72: =P14*P73 -> 664.56407
B73: % de ventas | D73: % | F73: =F72/F14 -> 0.59875225 | G73: =G72/G14 -> 0.6978742 | H73: =H72/H14 -> 0.50487573 | I73: =I72/I14 -> 0.57882022 | J73: =J72/J14 -> 0.60179643 | K73: =K72/K14 -> 0.54413074 | L73: =K73 -> 0.54413074 | M73: =L73 -> 0.54413074 | N73: =M73 -> 0.54413074 | O73: =N73 -> 0.54413074 | P73: =O73 -> 0.54413074
B74: Depreciación | D74: USD mm | F74: =(108232-18302)/1000 -> 89.93 | G74: =(97189-15350)/1000 -> 81.839 | H74: =(92025-4058)/1000 -> 87.967 | I74: =(107864-5952)/1000 -> 101.912 | J74: =(105240-4568)/1000 -> 100.672 | K74: =(108424-6700)/1000 -> 101.724 | L74: =L122 -> 0.7115039 | M74: =M122 -> 2.2450971 | N74: =N122 -> 3.1576116 | O74: =O122 -> 4.070126 | P74: =P122 -> 5.0110036
B75: Depreciación por derecho de uso | D75: USD mm | F75: =18302/1000 -> 18.302 | G75: =15350/1000 -> 15.35 | H75: =4058/1000 -> 4.058 | I75: =5952/1000 -> 5.952 | J75: =4568/1000 -> 4.568 | K75: =6700/1000 -> 6.7 | L75: =L135 -> -8.1727595 | M75: =M135 -> -11.132089 | N75: =N135 -> -8.0181824 | O75: =O135 -> -11.201216 | P75: =P135 -> -14.780234
B76: Amortización | D76: USD mm | F76: =66534/1000 -> 66.534 | G76: =42387/1000 -> 42.387 | H76: =90736/1000 -> 90.736 | I76: =104267/1000 -> 104.267 | J76: =88829/1000 -> 88.829 | K76: =68515/1000 -> 68.515 | L76: =L149 -> 77.402997 | M76: =M149 -> 81.366742 | N76: =N149 -> 85.850023 | O76: =O149 -> 90.567018 | P76: =P149 -> 95.360779
B77: Total costos de venta | D77: USD mm | F77: =-Buildup!E7 -> 619.985 | G77: =-Buildup!F7 -> 513.266 | H77: =-Buildup!G7 -> 656.031 | I77: =-Buildup!H7 -> 762.743 | J77: =-Buildup!I7 -> 725.507 | K77: =-Buildup!J7 -> 699.588 | L77: =SUM(L72,L74:L76) -> 571.77992 | M77: =SUM(M72,M74:M76) -> 652.31607 | N77: =SUM(N72,N74:N76) -> 724.60449 | O77: =SUM(O72,O74:O76) -> 727.05096 | P77: =SUM(P72,P74:P76) -> 750.15562
A79: x | B79: C) Gastos operativos
B81: 1. Gastos de ventas
B82: Gastos de ventas sin D&A | D82: USD mm | F82: =+F87-F84-F85-F86 -> 23.155 | G82: =+G87-G84-G85-G86 -> 15.355 | H82: =+H87-H84-H85-H86 -> 21.034 | I82: =+I87-I84-I85-I86 -> 24.756 | J82: =+J87-J84-J85-J86 -> 30.52 | K82: =+K87-K84-K85-K86 -> 29.015 | L82: =L83*L14 -> 27.91187 | M82: =M83*M14 -> 33.756103 | N82: =N83*N14 -> 36.332313 | O82: =O83*O14 -> 36.53293 | P82: =P83*P14 -> 37.9752
B83: % de ventas | D83: % | F83: =F82/F14 -> 0.031139975 | G83: =G82/G14 -> 0.028675796 | H83: =H82/H14 -> 0.022438684 | I83: =I82/I14 -> 0.026024267 | J83: =J82/J14 -> 0.03456062 | K83: =K82/K14 -> 0.030207564 | L83: =AVERAGE(I83:K83) -> 0.03026415 | M83: =AVERAGE(J83:L83) -> 0.031677445 | N83: =AVERAGE(K83:M83) -> 0.030716387 | O83: =AVERAGE(L83:N83) -> 0.030885994 | P83: =AVERAGE(M83:O83) -> 0.031093275
B84: Depreciación | D84: USD mm | F84: =44/1000 -> 0.044 | G84: =80/1000 -> 0.08 | H84: =91/1000 -> 0.091 | I84: =96/1000 -> 0.096 | J84: =43/1000 -> 0.043 | K84: =66/1000 -> 0.066 | L84: =L123 -> 0.00047898738 | M84: =M123 -> 0.0015114087 | N84: =N123 -> 0.0021257172 | O84: =O123 -> 0.0027400258 | P84: =P123 -> 0.0033734284
B85: Depreciación - activos por derecho de uso | D85: USD mm | F85: 0 | G85: 0 | H85: 0 | I85: 0 | J85: 0 | K85: 0 | L85: =L136 -> 0 | M85: =M136 -> 0 | N85: =N136 -> 0 | O85: =O136 -> 0 | P85: =P136 -> 0
B86: Amortización | D86: USD mm | F86: 0 | G86: 0 | H86: 0 | I86: 0 | J86: 0 | K86: 0 | L86: =L150 -> 0 | M86: =M150 -> 0 | N86: =N150 -> 0 | O86: =O150 -> 0 | P86: =P150 -> 0
B87: Total gastos de ventas | D87: USD mm | F87: =+-Buildup!E11 -> 23.199 | G87: =+-Buildup!F11 -> 15.435 | H87: =+-Buildup!G11 -> 21.125 | I87: =+-Buildup!H11 -> 24.852 | J87: =+-Buildup!I11 -> 30.563 | K87: =+-Buildup!J11 -> 29.081 | L87: =SUM(L82,L84:L86) -> 27.912349 | M87: =SUM(M82,M84:M86) -> 33.757614 | N87: =SUM(N82,N84:N86) -> 36.334439 | O87: =SUM(O82,O84:O86) -> 36.53567 | P87: =SUM(P82,P84:P86) -> 37.978573
B89: 2. Gastos administrativos
B90: Gastos de administración sin D&A | D90: USD mm | F90: =+F96-F93-F94-F95 -> 21.384 | G90: =+G96-G93-G94-G95 -> 13.35 | H90: =+H96-H93-H94-H95 -> 19.192 | I90: =+I96-I93-I94-I95 -> 24.214 | J90: =+J96-J93-J94-J95 -> 26.476 | K90: =+K96-K93-K94-K95 -> 26.298 | L90: =L91*L14 -> 25.459284 | M90: =M91*M14 -> 30.180116 | N90: =N91*N14 -> 32.84543 | O90: =O91*O14 -> 32.999034 | P90: =P91*P14 -> 34.192593
B91: % de ventas | D91: % | F91: =F90/F14 -> 0.028758247 | G91: =G90/G14 -> 0.024931415 | H91: =H90/H14 -> 0.020473672 | I91: =I90/I14 -> 0.0254545 | J91: =J90/J14 -> 0.029981225 | K91: =K90/K14 -> 0.027378891 | L91: =AVERAGE(I91:K91) -> 0.027604872 | M91: =AVERAGE(J91:L91) -> 0.028321663 | N91: =AVERAGE(K91:M91) -> 0.027768475 | O91: =AVERAGE(L91:N91) -> 0.027898337 | P91: =AVERAGE(M91:O91) -> 0.027996158
B92: Variación anual | D92: USD mm | G92: =IFERROR((G90/F90-1),"") -> -0.37570146 | H92: =IFERROR((H90/G90-1),"") -> 0.437603 | I92: =IFERROR((I90/H90-1),"") -> 0.26167153 | J92: =IFERROR((J90/I90-1),"") -> 0.093417031 | K92: =IFERROR((K90/J90-1),"") -> -0.0067230699 | L92: =IFERROR((L90/K90-1),"") -> -0.031892784 | M92: =IFERROR((M90/L90-1),"") -> 0.18542675 | N92: =IFERROR((N90/M90-1),"") -> 0.088313587 | ... P92: =IFERROR((P90/O90-1),"") -> 0.036169499
B93: Depreciación | D93: USD mm | F93: =(1193-522)/1000 -> 0.671 | G93: =(860-868)/1000 -> -0.008 | H93: =(810-768)/1000 -> 0.042 | I93: =(229-1134)/1000 -> -0.905 | J93: =(1528-870)/1000 -> 0.658 | K93: =(720-744)/1000 -> -0.024 | L93: =L124 -> -0.00062385972 | M93: =M124 -> -0.0019685425 | N93: =N124 -> -0.002768652 | O93: =O124 -> -0.0035687615 | P93: =P124 -> -0.0043937402
B94: Depreciación - activos por derecho de uso | D94: USD mm | F94: 0.522 | G94: 0.868 | H94: 0.768 | I94: 1.134 | J94: 0.87 | K94: 0.744 | L94: =L137 -> -1.0107265 | M94: =M137 -> -1.3767072 | N94: =N137 -> -0.99160987 | O94: =O137 -> -1.3852561 | P94: =P137 -> -1.8278739
B95: Amortización | D95: USD mm | F95: =622/1000 -> 0.622 | G95: =1225/1000 -> 1.225 | H95: =1123/1000 -> 1.123 | I95: =409/1000 -> 0.409 | J95: =2559/1000 -> 2.559 | K95: =2063/1000 -> 2.063 | L95: =L151 -> 1.4558029 | M95: =M151 -> 1.5303535 | N95: =N151 -> 1.6146754 | O95: =O151 -> 1.7033931 | P95: =P151 -> 0
B96: Total gastos de administración | D96: USD mm | F96: =-+Buildup!E11 -> 23.199 | G96: =-+Buildup!F11 -> 15.435 | H96: =-+Buildup!G11 -> 21.125 | I96: =-+Buildup!H11 -> 24.852 | J96: =-+Buildup!I11 -> 30.563 | K96: =-+Buildup!J11 -> 29.081 | L96: =SUM(L90,L93:L95) -> 25.903736 | M96: =SUM(M90,M93:M95) -> 30.331794 | N96: =SUM(N90,N93:N95) -> 33.465727 | O96: =SUM(O90,O93:O95) -> 33.313603 | P96: =SUM(P90,P93:P95) -> 32.360325
A99: x | B99: D) Otros ingresos y gastos operativos
B101: 1. Otros ingresos operativos
B102: Otros ingresos operativos | D102: USD mm | F102: =+Buildup!E13 -> 66.84 | G102: =+Buildup!F13 -> 46.907 | H102: =+Buildup!G13 -> 42.505 | I102: =+Buildup!H13 -> 60.068 | J102: =+Buildup!I13 -> 63.429 | K102: =+Buildup!J13 -> 145.115 | L102: =L103*L14 -> 87.939327 | M102: =M103*M14 -> 101.60729 | N102: =N103*N14 -> 112.78351 | O102: =O103*O14 -> 112.78351 | P102: =P103*P14 -> 116.4545
B103: % de ventas | D103: % | F103: =F102/F14 -> 0.089889696 | G103: =G102/G14 -> 0.087599842 | H103: =H102/H14 -> 0.045343552 | I103: =I102/I14 -> 0.063145324 | J103: =J102/J14 -> 0.071826527 | K103: =K102/K14 -> 0.15107947 | L103: =AVERAGE(I103:K103) -> 0.095350439 | M103: =+L103 -> 0.095350439 | N103: =+M103 -> 0.095350439 | O103: =+N103 -> 0.095350439 | P103: =+O103 -> 0.095350439
B105: 2. Otros gastos operativos
B106: Otros gastos operativos sin D&A | D106: USD mm | F106: =+F112-F109-F111 -> 91.87 | G106: =+G112-G109-G111 -> 92.531 | H106: =+H112-H109-H111 -> 75.54 | I106: =+I112-I109-I111 -> 83.398 | J106: =+J112-J109-J111 -> 75.902 | K106: =+K112-K109-K111 -> 112.253 | L106: =L107*L14 -> 89.303329 | M106: =M107*M14 -> 103.18329 | N106: =N107*N14 -> 114.53287 | O106: =O107*O14 -> 114.53287 | P106: =P107*P14 -> 118.2608
B107: % de ventas | D107: % | F107: =F106/F14 -> 0.12355126 | G107: =G106/G14 -> 0.17280365 | H107: =H106/H14 -> 0.080584682 | I107: =I106/I14 -> 0.087670536 | J107: =J106/J14 -> 0.085950859 | K107: =K106/K14 -> 0.11686678 | L107: =AVERAGE(I107:K107) -> 0.096829393 | M107: =+L107 -> 0.096829393 | N107: =+M107 -> 0.096829393 | O107: =+N107 -> 0.096829393 | P107: =+O107 -> 0.096829393
B108: Var. Anual | D108: % | G108: =IFERROR((G106/F106-1),"") -> 0.0071949494 | H108: =IFERROR((H106/G106-1),"") -> -0.18362495 | I108: =IFERROR((I106/H106-1),"") -> 0.10402436 | J108: =IFERROR((J106/I106-1),"") -> -0.089882251 | K108: =IFERROR((K106/J106-1),"") -> 0.47892019 | L108: =IFERROR((L106/K106-1),"") -> -0.20444594 | M108: =IFERROR((M106/L106-1),"") -> 0.15542488 | N108: =IFERROR((N106/M106-1),"") -> 0.10999434 | ... P108: =IFERROR((P106/O106-1),"") -> 0.032549012
B109: Depreciación | D109: USD mm | F109: =3987/1000 -> 3.987 | G109: =4554/1000 -> 4.554 | H109: =3741/1000 -> 3.741 | I109: =3264/1000 -> 3.264 | J109: =2411/1000 -> 2.411 | K109: =2625/1000 -> 2.625 | L109: =L138 -> 0 | M109: =M138 -> 0 | N109: =N138 -> 0 | O109: =O138 -> 0 | P109: =P138 -> 0
B110: Depreciación - activos por derecho de uso | D110: USD mm | F110: 0 | G110: 0 | H110: 0 | I110: 0 | J110: 0 | K110: 0 | L110: =L138 -> 0 | M110: =M138 -> 0 | N110: =N138 -> 0 | O110: =O138 -> 0 | P110: =P138 -> 0
B111: Amortización | D111: USD mm | F111: =484/1000 -> 0.484 | G111: =262/1000 -> 0.262 | H111: =191/1000 -> 0.191 | I111: =803/1000 -> 0.803 | J111: =194/1000 -> 0.194 | K111: =404/1000 -> 0.404 | L111: =L152 -> 0.40457251 | M111: =M152 -> 0.42529035 | N111: =N152 -> 0.44872371 | O111: =O152 -> 0.47337865 | P111: =P152 -> 0.95360926
B112: Total otros gastos operativos | D112: USD mm | F112: =+-Buildup!E14 -> 96.341 | G112: =+-Buildup!F14 -> 97.347 | H112: =+-Buildup!G14 -> 79.472 | I112: =+-Buildup!H14 -> 87.465 | J112: =+-Buildup!I14 -> 78.507 | K112: =+-Buildup!J14 -> 115.282 | L112: =SUM(L106,L109:L111) -> 89.707902 | M112: =SUM(M106,M109:M111) -> 103.60858 | N112: =SUM(N106,N109:N111) -> 114.98159 | O112: =SUM(O106,O109:O111) -> 115.00624 | P112: =SUM(P106,P109:P111) -> 119.21441
A114: x | B114: E) D&A
B116: Depreciación | D116: USD mm | F116: =+F126 -> 94.632 | G116: =+G126 -> 86.465 | H116: =+H126 -> 91.841 | I116: =+I126 -> 104.367 | J116: =+J126 -> 103.784 | K116: =+K126 -> 104.391 | L116: =L126 -> 0.73076098 | M116: =M126 -> 2.3058614 | N116: =N126 -> 3.2430734 | O116: =O126 -> 4.1802853 | P116: =P126 -> 5.146628
B117: Depreciación - activos por derecho de uso | D117: USD mm | F117: =+F139 -> 18.824 | G117: =+G139 -> 16.218 | H117: =+H139 -> 4.826 | I117: =+I139 -> 7.086 | J117: =+J139 -> 5.438 | K117: =+K139 -> 7.444 | L117: =L139 -> -9.183486 | M117: =M139 -> -12.508796 | N117: =N139 -> -9.0097923 | O117: =O139 -> -12.586472 | P117: =P139 -> -16.608108
B118: Amortización | D118: USD mm | F118: =+F153 -> 67.64 | G118: =+G153 -> 43.874 | H118: =+H153 -> 92.05 | I118: =+I153 -> 105.479 | J118: =+J153 -> 91.582 | K118: =+K153 -> 70.982 | L118: =L153 -> 79.263372 | M118: =M153 -> 83.322386 | N118: =N153 -> 87.913422 | O118: =O153 -> 92.74379 | P118: =P153 -> 97.652769
B119: Total D&A | D119: USD mm | F119: =+SUM(F116:F118) -> 181.096 | G119: =+SUM(G116:G118) -> 146.557 | H119: =+SUM(H116:H118) -> 188.717 | I119: =+SUM(I116:I118) -> 216.932 | J119: =+SUM(J116:J118) -> 200.804 | K119: =+SUM(K116:K118) -> 182.817 | L119: =SUM(L116:L118) -> 70.810647 | M119: =SUM(M116:M118) -> 73.119451 | N119: =SUM(N116:N118) -> 82.146703 | O119: =SUM(O116:O118) -> 84.337603 | P119: =SUM(P116:P118) -> 86.191289
B121: 1. Depreciación, por costo/gasto
B122: Costo de ventas | D122: USD mm | F122: =+F74 -> 89.93 | G122: =+G74 -> 81.839 | H122: =+H74 -> 87.967 | I122: =+I74 -> 101.912 | J122: =+J74 -> 100.672 | K122: =+K74 -> 101.724 | L122: =L129*$L$126 -> 0.7115039 | M122: =M129*$M$126 -> 2.2450971 | N122: =N129*$N$126 -> 3.1576116 | O122: =O129*$O$126 -> 4.070126 | P122: =P129*$P$126 -> 5.0110036
B123: Gastos de ventas | D123: USD mm | F123: =+F84 -> 0.044 | G123: =+G84 -> 0.08 | H123: =+H84 -> 0.091 | I123: =+I84 -> 0.096 | J123: =+J84 -> 0.043 | K123: =+K84 -> 0.066 | L123: =L130*$L$126 -> 0.00047898738 | M123: =M130*$M$126 -> 0.0015114087 | N123: =N130*$N$126 -> 0.0021257172 | O123: =O130*$O$126 -> 0.0027400258 | P123: =P130*$P$126 -> 0.0033734284
B124: Gastos administrativos | D124: USD mm | F124: =+F93 -> 0.671 | G124: =+G93 -> -0.008 | H124: =+H93 -> 0.042 | I124: =+I93 -> -0.905 | J124: =+J93 -> 0.658 | K124: =+K93 -> -0.024 | L124: =L131*$L$126 -> -0.00062385972 | M124: =M131*$M$126 -> -0.0019685425 | N124: =N131*$N$126 -> -0.002768652 | O124: =O131*$O$126 -> -0.0035687615 | P124: =P131*$P$126 -> -0.0043937402
B125: Otros gastos operativos | D125: USD mm | F125: =+F109 -> 3.987 | G125: =+G109 -> 4.554 | H125: =+H109 -> 3.741 | I125: =+I109 -> 3.264 | J125: =+J109 -> 2.411 | K125: =+K109 -> 2.625 | L125: =L132*$L$126 -> 0.019401958 | M125: =M132*$M$126 -> 0.061221419 | N125: =N132*$N$126 -> 0.086104722 | O125: =O132*$O$126 -> 0.11098803 | P125: =P132*$P$126 -> 0.13664476
B126: Total depreciación | D126: USD mm | F126: =+SUM(F122:F125) -> 94.632 | G126: =+SUM(G122:G125) -> 86.465 | H126: =+SUM(H122:H125) -> 91.841 | I126: =+SUM(I122:I125) -> 104.367 | J126: =+SUM(J122:J125) -> 103.784 | K126: =+SUM(K122:K125) -> 104.391 | L126: =Capex!P31 -> 0.73076098 | M126: =Capex!Q31 -> 2.3058614 | N126: =Capex!R31 -> 3.2430734 | O126: =Capex!S31 -> 4.1802853 | P126: =Capex!T31 -> 5.146628
B128: Desglose de la depreciación en %
B129: Costos de ventas | D129: % | F129: =+F122/$F$126 -> 0.95031279 | G129: =+G122/$G$126 -> 0.94649858 | H129: =+H122/$H$126 -> 0.9578184 | I129: =+I122/$I$126 -> 0.97647724 | J129: =+J122/$J$126 -> 0.97001465 | K129: =+K122/$K$126 -> 0.97445182 | L129: =+AVERAGE(I129:K129) -> 0.9736479 | M129: =+L129 -> 0.9736479 | N129: =+M129 -> 0.9736479 | O129: =+N129 -> 0.9736479 | P129: =+O129 -> 0.9736479
B130: Gastos de ventas | D130: % | F130: =+F123/$F$126 -> 0.000464959 | G130: =+G123/$G$126 -> 0.00092522986 | H130: =+H123/$H$126 -> 0.00099084287 | I130: =+I123/$I$126 -> 0.00091983098 | J130: =+J123/$J$126 -> 0.00041432205 | K130: =+K123/$K$126 -> 0.00063223841 | L130: =+AVERAGE(I130:K130) -> 0.00065546382 | M130: =+L130 -> 0.00065546382 | N130: =+M130 -> 0.00065546382 | O130: =+N130 -> 0.00065546382 | P130: =+O130 -> 0.00065546382
B131: Gastos administrativos | D131: % | F131: =+F124/$F$126 -> 0.0070906247 | G131: =+G124/$G$126 -> -9.2522986e-05 | H131: =+H124/$H$126 -> 0.00045731209 | I131: =+I124/$I$126 -> -0.0086713233 | J131: =+J124/$J$126 -> 0.006340091 | K131: =+K124/$K$126 -> -0.00022990488 | L131: =+AVERAGE(I131:K131) -> -0.00085371241 | M131: =+L131 -> -0.00085371241 | N131: =+M131 -> -0.00085371241 | O131: =+N131 -> -0.00085371241 | P131: =+O131 -> -0.00085371241
...

Sheet Capex
C2: Volcan Minera | H2: Año | J2: 2019 | K2: 2020 | L2: 2021 | M2: 2022 | N2: 2023 | O2: 2024 | P2: 2025 | Q2: 2026 | R2: 2027 | S2: 2028 | T2: 2029
C3: Capex | H3: Mes | J3: 43830 | K3: 44196 | L3: 44561 | M3: 44926 | N3: 45291 | O3: 45657 | P3: 46022 | Q3: 46387 | R3: 46752 | S3: 47118 | T3: 47483
J4: Histórico | K4: Histórico | L4: Histórico | M4: Histórico | N4: Histórico | O4: Histórico | P4: Proyección | Q4: Proyección | R4: Proyección | S4: Proyección | T4: Proyección
A5: x | B5: Resumen
C7: A) Propiedad, planta y equipo (PPE),neto
C8: PPE,bruto | H8: USD mm | J8: =J50 -> 1388.181 | K8: =K50 -> 1859.667 | L8: =L50 -> 1929.62 | M8: =M50 -> 1816.027 | N8: =N50 -> 1945.957 | O8: =O50 -> 1935.681 | P8: =P50 -> 2026.3564 | Q8: =Q50 -> 2131.125 | ... T8: =T50 -> 2483.788
C9: Depreciación acumulada | H9: USD mm | J9: =-J77 -> -711.391 | K9: =-K77 -> -1087.604 | L9: =-L77 -> -1173.101 | M9: =-M77 -> -1003.115 | N9: =-N77 -> -1174.179 | O9: =-O77 -> -1252.56 | P9: =-P77 -> -1253.2908 | Q9: =-Q77 -> -1255.5966 | ... T9: =-T77 -> -1268.1666
C10: Deterioro acumulado | H10: USD mm | J10: =J101 -> -19.613 | K10: =K101 -> -10.408 | L10: =L101 -> -11.386 | M10: =M101 -> 43.921 | N10: =N101 -> 8.576 | O10: =O101 -> 0 | P10: =P101 -> 0 | Q10: =Q101 -> 0 | ... T10: =T101 -> 0
C11: PPE,neto | H11: USD mm | J11: =J8+J9+J10 -> 657.177 | K11: =K8+K9+K10 -> 761.655 | L11: =L8+L9+L10 -> 745.133 | M11: =M8+M9+M10 -> 856.833 | N11: =N8+N9+N10 -> 780.354 | O11: =O8+O9+O10 -> 683.121 | P11: =SUM(P8:P10) -> 773.06565 | Q11: =SUM(Q8:Q10) -> 875.52842 | R11: =SUM(R8:R10) -> 988.57793 | S11: =SUM(S8:S10) -> 1100.6902 | T11: =SUM(T8:T10) -> 1215.6214
C13: B) Derecho de uso, neto | H13: USD mm
C14: Derecho de uso, bruto | H14: USD mm | J14: =J379 | K14: =K379 -> 39.327 | L14: =L379 -> 44.253 | M14: =M379 -> 20.828 | N14: =N379 -> 24.646 | O14: =O379 -> 25.984 | P14: =P379 -> 36.477028 | Q14: =Q379 -> 48.600935 | ... T14: =T379 -> 89.411363
C15: Depreciación acumulada | H15: USD mm | J15: =J383 | K15: =K383 -> -35.042 | L15: =L383 -> -39.868 | M15: =M383 -> -9.443 | N15: =N383 -> -6.721 | O15: =O383 -> -10.322 | P15: =P383 -> -19.505486 | Q15: =Q383 -> -32.014282 | ... T15: =T383 -> -70.218655
C16: Derecho de uso neto | H16: USD mm | J16: =SUM(J14:J15) -> 0 | K16: =SUM(K14:K15) -> 4.285 | L16: =SUM(L14:L15) -> 4.385 | M16: =SUM(M14:M15) -> 11.385 | N16: =SUM(N14:N15) -> 17.925 | O16: =SUM(O14:O15) -> 15.662 | P16: =SUM(P14:P15) -> 16.971542 | Q16: =SUM(Q14:Q15) -> 16.586652 | ... T16: =SUM(T14:T15) -> 19.192708
C18: C) Intangible, neto
C19: Intangible, bruto | H19: USD mm | J19: =J410 -> 1376.45 | K19: =K410 -> 1572.165 | L19: =L410 -> 1676.34 | M19: =M410 -> 1672.381 | N19: =N410 -> 1751.595 | O19: =O410 -> 1831.858 | P19: =P410 -> 1921.02 | Q19: =Q410 -> 2024.0399 | ... T19: =T410 -> 2370.8166
C20: Amortización acumulada | H20: USD mm | J20: =J414 -> -596.328 | K20: =K414 -> -781.612 | L20: =L414 -> -874.357 | M20: =M414 -> -972.443 | N20: =N414 -> -1100.945 | O20: =O414 -> -1175.63 | P20: =P414 -> -1254.8934 | Q20: =Q414 -> -1338.2158 | ... T20: =T414 -> -1616.5257
C21: Intangible neto | H21: USD mm | J21: =SUM(J19:J20) -> 780.122 | K21: =SUM(K19:K20) -> 790.553 | L21: =SUM(L19:L20) -> 801.983 | M21: =SUM(M19:M20) -> 699.938 | N21: =SUM(N19:N20) -> 650.65 | O21: =SUM(O19:O20) -> 656.228 | P21: =SUM(P19:P20) -> 666.12658 | Q21: =SUM(Q19:Q20) -> 685.82414 | ... T21: =SUM(T19:T20) -> 754.29085
C23: D) Capex, por activo
C24: PPE | H24: USD mm | J24: =J62 -> 77.858 | K24: =K62 -> 61.572 | L24: =L62 -> 102.994 | M24: =M62 -> 129.494 | N24: =N62 -> 68.772 | O24: =O62 -> 70.752 | P24: =P62 -> 90.675413 | Q24: =Q62 -> 104.76863 | ... T24: =T62 -> 120.07779
C25: Derecho de uso | H25: USD mm | J25: =J377 | K25: =K377 -> 1.642 | L25: =L377 -> 4.325 | M25: =M377 -> 14.886 | N25: =N377 -> 12.248 | O25: =O377 -> 5.329 | P25: =P377 -> 10.493028 | Q25: =Q377 -> 12.123906 | ... T25: =T377 -> 13.895494
C26: Intangibles | H26: USD mm | J26: =J408 -> 110.115 | K26: =K408 -> 50.685 | L26: =L408 -> 83.762 | M26: =M408 -> 109.336 | N26: =N408 -> 89.385 | O26: =O408 -> 77.987 | P26: =P408 -> 89.161956 | Q26: =Q408 -> 103.01994 | ... T26: =T408 -> 118.07358
C27: Total capex | H27: USD mm | J27: =SUM(J24:J26) -> 187.973 | K27: =SUM(K24:K26) -> 113.899 | L27: =SUM(L24:L26) -> 191.081 | M27: =SUM(M24:M26) -> 253.716 | N27: =SUM(N24:N26) -> 170.405 | O27: =SUM(O24:O26) -> 154.068 | P27: =SUM(P24:P26) -> 190.3304 | Q27: =SUM(Q24:Q26) -> 219.91248 | ... T27: =SUM(T24:T26) -> 252.04687
C28: Total capex / ventas | H28: % | J28: =IFERROR(J27/'Supuestos '!F14,"-") -> 0.25279527 | K28: =IFERROR(K27/'Supuestos '!G14,"-") -> 0.21270886 | L28: =IFERROR(L27/'Supuestos '!H14,"-") -> 0.20384169 | M28: =IFERROR(M27/'Supuestos '!I14,"-") -> 0.26671404 | N28: =IFERROR(N27/'Supuestos '!J14,"-") -> 0.19296535 | O28: =IFERROR(O27/'Supuestos '!K14,"-") -> 0.16040045 | P28: =IFERROR(P27/'Supuestos '!L14,"-") -> 0.20637055 | Q28: =IFERROR(Q27/'Supuestos '!M14,"-") -> 0.20637055 | ... T28: =IFERROR(T27/'Supuestos '!P14,"-") -> 0.20637055
C30: E) D&aA, por activo
C31: Depreciación de PPE | H31: USD mm | J31: =J89 -> 113.456 | K31: =K89 -> 85.441 | L31: =L89 -> 96.667 | M31: =M89 -> 111.453 | N31: =N89 -> 109.222 | O31: =O89 -> 111.835 | P31: =P89 -> 0.73076098 | Q31: =Q89 -> 2.3058614 | ... T31: =T89 -> 5.146628
C32: Depreciación de Derecho de Uso | H32: USD mm | J32: =J381 | K32: =-K381 -> 16.218 | L32: =-L381 -> 4.826 | M32: =-M381 -> 7.086 | N32: =-N381 -> 5.438 | O32: =-O381 -> 7.444 | P32: =P381 -> -9.183486 | Q32: =Q381 -> -12.508796 | R32: =R381 -> -9.0097923 | S32: =S381 -> -12.586472 | T32: =T381 -> -16.608108
C33: Amortización de intangibles | H33: USD mm | J33: =-J412 -> 69.06 | K33: =-K412 -> 46.351 | L33: =-L412 -> 92.745 | M33: =-M412 -> 106.255 | N33: =-N412 -> 92.455 | O33: =-O412 -> 75.685 | P33: =-P412 -> 79.263372 | Q33: =-Q412 -> 83.322386 | ... T33: =-T412 -> 97.652769
C34: Total D&A | H34: USD mm | J34: =SUM(J31:J33) -> 182.516 | K34: =SUM(K31:K33) -> 148.01 | L34: =SUM(L31:L33) -> 194.238 | M34: =SUM(M31:M33) -> 224.794 | N34: =SUM(N31:N33) -> 207.115 | O34: =SUM(O31:O33) -> 194.964 | P34: =SUM(P31:P33) -> 70.810647 | Q34: =SUM(Q31:Q33) -> 73.119451 | ... T34: =SUM(T31:T33) -> 86.191289
C35: Total D&A / ventas | H35: % | J35: =IFERROR(J34/'Supuestos '!F14,"-") -> 0.24545643 | K35: =IFERROR(K34/'Supuestos '!G14,"-") -> 0.27641189 | L35: =IFERROR(L34/'Supuestos '!H14,"-") -> 0.20720952 | M35: =IFERROR(M34/'Supuestos '!I14,"-") -> 0.23631035 | N35: =IFERROR(N34/'Supuestos '!J14,"-") -> 0.23453548 | O35: =IFERROR(O34/'Supuestos '!K14,"-") -> 0.20297734 | P35: =IFERROR(P34/'Supuestos '!L14,"-") -> 0.076778234 | Q35: =IFERROR(Q34/'Supuestos '!M14,"-") -> 0.068616848 | ... T35: =IFERROR(T34/'Supuestos '!P14,"-") -> 0.07057157
A38: x | B38: A) Desglose de PPE por activo
C40: PPE bruto (costo)
B41: 1 | C41: Terreno | H41: USD mm | J41: =31353/1000 -> 31.353 | K41: =31498/1000 -> 31.498 | L41: =23537/1000 -> 23.537 | M41: =23919/1000 -> 23.919 | N41: =23573/1000 -> 23.573 | O41: =23106/1000 -> 23.106 | P41: =O41+P53 -> 23.310311 | Q41: =P41+Q53 -> 23.546377 | R41: =Q41+R53 -> 23.808408 | S41: =+R41+S53 -> 24.07044 | T41: =+S41+T53 -> 24.341001
B42: 2 | C42: Edificios y otras construcciones | H42: USD mm | J42: =747170/1000 -> 747.17 | K42: =940701/1000 -> 940.701 | L42: =976667/1000 -> 976.667 | M42: =1078997/1000 -> 1078.997 | N42: =1200955/1000 -> 1200.955 | O42: =1175308/1000 -> 1175.308 | P42: =O42+P54 -> 1178.8825 | Q42: =P42+Q54 -> 1183.0126 | R42: =Q42+R54 -> 1187.597 | S42: =+R42+S54 -> 1192.1814 | T42: =+S42+T54 -> 1196.915
B43: 3 | C43: Infraestructura de programa de manejo ambiental | H43: USD mm | J43: =11773/1000 -> 11.773 | K43: =22281/1000 -> 22.281 | L43: =22281/1000 -> 22.281 | M43: =259/1000 -> 0.259 | N43: =680/1000 -> 0.68 | O43: =680/1000 -> 0.68 | P43: =O43+P55 -> 0.68 | Q43: =P43+Q55 -> 0.68 | R43: =Q43+R55 -> 0.68 | S43: =+R43+S55 -> 0.68 | T43: =+S43+T55 -> 0.68
B44: 4 | C44: Maquinaria y equipo | H44: USD mm | J44: =167681/1000 -> 167.681 | K44: =285931/1000 -> 285.931 | L44: =300338/1000 -> 300.338 | M44: =193491/1000 -> 193.491 | N44: =187986/1000 -> 187.986 | O44: =178080/1000 -> 178.08 | P44: =O44+P56 -> 184.07752 | Q44: =P44+Q56 -> 191.0072 | R44: =Q44+R56 -> 198.69911 | S44: =+R44+S56 -> 206.39101 | T44: =+S44+T56 -> 214.33328
B45: 5 | C45: Unidades de transporte | H45: USD mm | J45: =4223/1000 -> 4.223 | K45: =11172/1000 -> 11.172 | L45: =11561/1000 -> 11.561 | M45: =3500/1000 -> 3.5 | N45: =3320/1000 -> 3.32 | O45: =2916/1000 -> 2.916 | P45: =O45+P57 -> 2.9668216 | Q45: =P45+Q57 -> 3.0255421 | R45: =Q45+R57 -> 3.0907215 | S45: =+R45+S57 -> 3.155901 | T45: =+S45+T57 -> 3.2232019
B46: 6 | C46: Muebles y enseres | H46: USD mm | J46: =12780/1000 -> 12.78 | K46: =15265/1000 -> 15.265 | L46: =16030/1000 -> 16.03 | M46: =10485/1000 -> 10.485 | N46: =8937/1000 -> 8.937 | O46: =8927/1000 -> 8.927 | P46: =O46+P58 -> 9.1068783 | Q46: =P46+Q58 -> 9.3147141 | R46: =Q46+R58 -> 9.5454107 | S46: =+R46+S58 -> 9.7761073 | T46: =+S46+T58 -> 10.014313
B47: 7 | C47: Equipos diversos | H47: USD mm | J47: =355816/1000 -> 355.816 | K47: =479759/1000 -> 479.759 | L47: =497908/1000 -> 497.908 | M47: =399352/1000 -> 399.352 | N47: =430633/1000 -> 430.633 | O47: =444796/1000 -> 444.796 | P47: =O47+P59 -> 460.8316 | Q47: =P47+Q59 -> 479.35953 | R47: =Q47+R59 -> 499.92542 | S47: =+R47+S59 -> 520.49132 | T47: =+S47+T59 -> 541.72661
B48: 8 | C48: Unidades por recibir | H48: USD mm | J48: =3724/1000 -> 3.724 | K48: =9326/1000 -> 9.326 | L48: =1602/1000 -> 1.602 | M48: =1620/1000 -> 1.62 | N48: =3244/1000 -> 3.244 | O48: =565/1000 -> 0.565 | P48: =O48+P60 -> 1.7840883 | Q48: =P48+Q60 -> 3.1926532 | R48: =Q48+R60 -> 4.7561523 | S48: =+R48+S60 -> 6.3196514 | T48: =+S48+T60 -> 7.9340409
B49: 9 | C49: Obras en curso | H49: USD mm | J49: =53661/1000 -> 53.661 | K49: =63734/1000 -> 63.734 | L49: =79696/1000 -> 79.696 | M49: =104404/1000 -> 104.404 | N49: =86629/1000 -> 86.629 | O49: =101303/1000 -> 101.303 | P49: =O49+P61 -> 164.71668 | Q49: =P49+Q61 -> 237.98642 | R49: =Q49+R61 -> 319.31541 | S49: =+R49+S61 -> 400.64441 | T49: =+S49+T61 -> 484.62059
C50: Total PPE bruto | H50: USD mm | J50: =+SUM(J41:J49) -> 1388.181 | K50: =+SUM(K41:K49) -> 1859.667 | L50: =+SUM(L41:L49) -> 1929.62 | M50: =+SUM(M41:M49) -> 1816.027 | N50: =+SUM(N41:N49) -> 1945.957 | O50: =+SUM(O41:O49) -> 1935.681 | P50: =SUM(P41:P49) -> 2026.3564 | Q50: =SUM(Q41:Q49) -> 2131.125 | R50: =SUM(R41:R49) -> 2247.4176 | S50: =SUM(S41:S49) -> 2363.7102 | T50: =SUM(T41:T49) -> 2483.788
C52: Capex del PPE (inversiones)
B53: 1 | C53: Terreno | H53: USD mm | J53: =2163/1000 -> 2.163 | K53: =145/1000 -> 0.145 | L53: 0 | M53: =382/1000 -> 0.382 | N53: =262/1000 -> 0.262 | O53: 0 | P53: =$P$62*P104 -> 0.20431086 | Q53: =$Q$62*Q104 -> 0.23606585 | R53: =$R$62*R104 -> 0.26203175 | S53: =$S$62*S104 -> 0.26203175 | T53: =$T$62*T104 -> 0.27056063
B54: 2 | C54: Edificios y otras construcciones | H54: USD mm | J54: =7794/1000 -> 7.794 | K54: =227/1000 -> 0.227 | L54: =2290/1000 -> 2.29 | M54: =7500/1000 -> 7.5 | N54: =3597/1000 -> 3.597 | O54: =569/1000 -> 0.569 | P54: =$P$62*P105 -> 3.5745209 | Q54: =$Q$62*Q105 -> 4.1300904 | R54: =$R$62*R105 -> 4.5843769 | S54: =$S$62*S105 -> 4.5843769 | T54: =$T$62*T105 -> 4.7335939
B55: 3 | C55: Infraestructura de programa de manejo ambiental | H55: USD mm | J55: 0 | K55: 0 | L55: 0 | M55: 0 | N55: 0 | O55: 0 | P55: =$P$62*P106 -> 0 | Q55: =$Q$62*Q106 -> 0 | R55: =$R$62*R106 -> 0 | S55: =$S$62*S106 -> 0 | T55: =$T$62*T106 -> 0
B56: 4 | C56: Maquinaria y equipo | H56: USD mm | J56: =7593/1000 -> 7.593 | K56: =10596/1000 -> 10.596 | L56: =19312/1000 -> 19.312 | M56: =16323/1000 -> 16.323 | N56: =1832/1000 -> 1.832 | O56: =3236/1000 -> 3.236 | P56: =$P$62*P107 -> 5.997518 | Q56: =$Q$62*Q107 -> 6.9296815 | R56: =$R$62*R107 -> 7.6919072 | S56: =$S$62*S107 -> 7.6919072 | T56: =$T$62*T107 -> 7.9422712
B57: 5 | C57: Unidades de transporte | H57: USD mm | J57: =189/1000 -> 0.189 | K57: =46/1000 -> 0.046 | L57: =389/1000 -> 0.389 | M57: =310/1000 -> 0.31 | N57: =+-49/1000 -> -0.049 | O57: 0 | P57: =$P$62*P108 -> 0.050821575 | Q57: =$Q$62*Q108 -> 0.058720512 | R57: =$R$62*R108 -> 0.065179436 | S57: =$S$62*S108 -> 0.065179436 | T57: =$T$62*T108 -> 0.067300963
B58: 6 | C58: Muebles y enseres | H58: USD mm | J58: =434/1000 -> 0.434 | K58: =510/1000 -> 0.51 | L58: =696/1000 -> 0.696 | M58: =592/1000 -> 0.592 | N58: =56/1000 -> 0.056 | O58: =40/1000 -> 0.04 | P58: =$P$62*P109 -> 0.17987827 | Q58: =$Q$62*Q109 -> 0.20783582 | R58: =$R$62*R109 -> 0.23069659 | S58: =$S$62*S109 -> 0.23069659 | T58: =$T$62*T109 -> 0.23820553
B59: 7 | C59: Equipos diversos | H59: USD mm | J59: =16964/1000 -> 16.964 | K59: =13830/1000 -> 13.83 | L59: =23487/1000 -> 23.487 | M59: =28071/1000 -> 28.071 | N59: =11581/1000 -> 11.581 | O59: =10285/1000 -> 10.285 | P59: =$P$62*P110 -> 16.035598 | Q59: =$Q$62*Q110 -> 18.527929 | R59: =$R$62*R110 -> 20.565896 | S59: =$S$62*S110 -> 20.565896 | T59: =$T$62*T110 -> 21.235296
B60: 8 | C60: Unidades por recibir | H60: USD mm | J60: =4000/1000 -> 4 | K60: =6066/1000 -> 6.066 | L60: 0 | M60: =1288/1000 -> 1.288 | N60: =1874/1000 -> 1.874 | O60: =222/1000 -> 0.222 | P60: =$P$62*P111 -> 1.2190883 | Q60: =$Q$62*Q111 -> 1.4085649 | R60: =$R$62*R111 -> 1.5634991 | S60: =$S$62*S111 -> 1.5634991 | T60: =$T$62*T111 -> 1.6143895
B61: 9 | C61: Obras en curso | H61: USD mm | J61: =38721/1000 -> 38.721 | K61: =30152/1000 -> 30.152 | L61: =56820/1000 -> 56.82 | M61: =75028/1000 -> 75.028 | N61: =49619/1000 -> 49.619 | O61: =56400/1000 -> 56.4 | P61: =$P$62*P112 -> 63.413677 | Q61: =$Q$62*Q112 -> 73.26974 | R61: =$R$62*R112 -> 81.328997 | S61: =$S$62*S112 -> 81.328997 | T61: =$T$62*T112 -> 83.976175
C62: Total Capex | H62: USD mm | J62: =+SUM(J53:J61) -> 77.858 | K62: =+SUM(K53:K61) -> 61.572 | L62: =+SUM(L53:L61) -> 102.994 | M62: =+SUM(M53:M61) -> 129.494 | N62: =+SUM(N53:N61) -> 68.772 | O62: =+SUM(O53:O61) -> 70.752 | P62: =P64*'Supuestos '!L14 -> 90.675413 | Q62: =Q64*'Supuestos '!M14 -> 104.76863 | R62: =R64*'Supuestos '!N14 -> 116.29258 | S62: =S64*'Supuestos '!O14 -> 116.29258 | T62: =T64*'Supuestos '!P14 -> 120.07779
C64: Capex PPE / ventas | H64: % | J64: =J62/'Supuestos '!G14 -> 0.14540151 | K64: =K62/'Supuestos '!H14 -> 0.065683876 | L64: =L62/'Supuestos '!I14 -> 0.10827045 | M64: =M62/'Supuestos '!J14 -> 0.14663804 | N64: =N62/'Supuestos '!K14 -> 0.071598643 | O64: =O62/'Supuestos '!L14 -> 0.076714645 | P64: =AVERAGE(M64:O64) -> 0.098317109 | Q64: =+P64 -> 0.098317109 | R64: =+Q64 -> 0.098317109 | S64: =+R64 -> 0.098317109 | T64: =+S64 -> 0.098317109
C65: Depreciación PPE / ventas | H65: % | J65: =J89/'Supuestos '!G14 -> 0.21188155 | K65: =K89/'Supuestos '!H14 -> 0.091146886 | L65: =L89/'Supuestos '!I14 -> 0.10161932 | M65: =M89/'Supuestos '!J14 -> 0.12620855 | N65: =N89/'Supuestos '!K14 -> 0.1137112 | O65: =O89/'Supuestos '!L14 -> 0.12125993 | P65: =AVERAGE(M65:O65) -> 0.12039323 | Q65: =+P65 -> 0.12039323 | R65: =+Q65 -> 0.12039323 | S65: =+R65 -> 0.12039323 | T65: =+S65 -> 0.12039323
C67: Depreciación acumulada
B68: 1 | C68: Terreno | H68: USD mm | J68: 0 | K68: 0 | L68: 0 | M68: 0 | N68: 0 | O68: 0 | P68: =O68+P80 -> 0 | Q68: =P68+Q80 -> 0 | R68: =Q68+R80 -> 0 | S68: =R68+S80 -> 0 | T68: =S68+T80 -> 0
B69: 2 | C69: Edificios y otras construcciones | H69: USD mm | J69: =289689/1000 -> 289.689 | K69: =428880/1000 -> 428.88 | L69: =491692/1000 -> 491.692 | M69: =564168/1000 -> 564.168 | N69: =686093/1000 -> 686.093 | O69: =741372/1000 -> 741.372 | P69: =O69+P81 -> 741.48717 | Q69: =P69+Q81 -> 741.85059 | R69: =Q69+R81 -> 742.36172 | S69: =R69+S81 -> 743.02056 | T69: =S69+T81 -> 743.83191
B70: 3 | C70: Infraestructura de programa de manejo ambiental | H70: USD mm | J70: =11773/1000 -> 11.773 | K70: =22281/1000 -> 22.281 | L70: =22281/1000 -> 22.281 | M70: =259/1000 -> 0.259 | N70: =680/1000 -> 0.68 | O70: =680/1000 -> 0.68 | P70: =O70+P82 -> 0.68 | Q70: =P70+Q82 -> 0.68 | R70: =Q70+R82 -> 0.68 | S70: =R70+S82 -> 0.68 | T70: =S70+T82 -> 0.68
B71: 4 | C71: Maquinaria y equipo | H71: USD mm | J71: =137415/1000 -> 137.415 | K71: =249647/1000 -> 249.647 | L71: =248315/1000 -> 248.315 | M71: =140060/1000 -> 140.06 | N71: =147157/1000 -> 147.157 | O71: =149201/1000 -> 149.201 | P71: =O71+P83 -> 149.41677 | Q71: =P71+Q83 -> 150.09763 | R71: =Q71+R83 -> 151.05522 | S71: =R71+S83 -> 152.28954 | T71: =S71+T83 -> 153.8096
B72: 5 | C72: Unidades de transporte | H72: USD mm | J72: =3587/1000 -> 3.587 | K72: =10724/1000 -> 10.724 | L72: =10920/1000 -> 10.92 | M72: =2801/1000 -> 2.801 | N72: =2811/1000 -> 2.811 | O72: =2586/1000 -> 2.586 | P72: =O72+P84 -> 2.5872388 | Q72: =P72+Q84 -> 2.5911476 | R72: =Q72+R84 -> 2.5966451 | S72: =R72+S84 -> 2.6037313 | T72: =S72+T84 -> 2.612458
B73: 6 | C73: Muebles y enseres | H73: USD mm | J73: =9086/1000 -> 9.086 | K73: =11864/1000 -> 11.864 | L73: =12913/1000 -> 12.913 | M73: =7807/1000 -> 7.807 | N73: =7108/1000 -> 7.108 | O73: =7478/1000 -> 7.478 | P73: =O73+P85 -> 7.4822392 | Q73: =P73+Q85 -> 7.4956156 | R73: =Q73+R85 -> 7.5144288 | S73: =R73+S85 -> 7.5386789 | T73: =S73+T85 -> 7.5671681
B74: 7 | C74: Equipos diversos | H74: USD mm | J74: =259841/1000 -> 259.841 | K74: =364208/1000 -> 364.208 | L74: =386980/1000 -> 386.98 | M74: =288020/1000 -> 288.02 | N74: =330330/1000 -> 330.33 | O74: =351243/1000 -> 351.243 | P74: =O74+P86 -> 351.63734 | Q74: =P74+Q86 -> 352.88164 | R74: =Q74+R86 -> 354.63168 | S74: =R74+S86 -> 356.88747 | T74: =S74+T86 -> 359.66547
B75: 8 | C75: Unidades por recibir | H75: USD mm | J75: 0 | K75: 0 | L75: 0 | M75: 0 | N75: 0 | O75: 0 | P75: =O75+P87 -> 0 | Q75: =P75+Q87 -> 0 | R75: =Q75+R87 -> 0 | S75: =R75+S87 -> 0 | T75: =S75+T87 -> 0
B76: 9 | C76: Obras en curso | H76: USD mm | J76: 0 | K76: 0 | L76: 0 | M76: 0 | N76: 0 | O76: 0 | P76: =O76+P88 -> 0 | Q76: =P76+Q88 -> 0 | R76: =Q76+R88 -> 0 | S76: =R76+S88 -> 0 | T76: =S76+T88 -> 0
C77: Total depreciación acumulada | H77: USD mm | J77: =+SUM(J68:J76) -> 711.391 | K77: =+SUM(K68:K76) -> 1087.604 | L77: =+SUM(L68:L76) -> 1173.101 | M77: =+SUM(M68:M76) -> 1003.115 | N77: =+SUM(N68:N76) -> 1174.179 | O77: =+SUM(O68:O76) -> 1252.56 | P77: =+SUM(P68:P76) -> 1253.2908 | Q77: =+SUM(Q68:Q76) -> 1255.5966 | ... T77: =+SUM(T68:T76) -> 1268.1666
C79: Depreciación del periodo
B80: 1 | C80: Terreno | H80: USD mm | J80: 0 | K80: 0 | L80: 0 | M80: 0 | N80: 0 | O80: 0 | P80: =P122 -> 0 | Q80: =Q122 -> 0 | R80: =R122 -> 0 | S80: =S122 -> 0 | T80: =T122 -> 0
B81: 2 | C81: Edificios y otras construcciones | H81: USD mm | J81: =80764/1000 -> 80.764 | K81: =58701/1000 -> 58.701 | L81: =62812/1000 -> 62.812 | M81: =72476/1000 -> 72.476 | N81: =70582/1000 -> 70.582 | O81: =76564/1000 -> 76.564 | P81: =P150 -> 0.11517228 | Q81: =Q150 -> 0.36341746 | R81: =R150 -> 0.51112764 | S81: =S150 -> 0.65883782 | T81: =T150 -> 0.81135582
B82: 3 | C82: Infraestructura de programa de manejo ambiental | H82: USD mm | J82: =4/1000 -> 0.004 | K82: 0 | L82: 0 | M82: 0 | N82: 0 | O82: 0 | P82: =P178 -> 0 | Q82: =Q178 -> 0 | R82: =R178 -> 0 | S82: =S178 -> 0 | T82: =T178 -> 0
B83: 4 | C83: Maquinaria y equipo | H83: USD mm | J83: =8130/1000 -> 8.13 | K83: =7469/1000 -> 7.469 | L83: =9641/1000 -> 9.641 | M83: =13414/1000 -> 13.414 | N83: =13730/1000 -> 13.73 | O83: =13170/1000 -> 13.17 | P83: =P206 -> 0.21577342 | Q83: =Q206 -> 0.68085681 | R83: =R206 -> 0.95758947 | S83: =S206 -> 1.2343221 | T83: =T206 -> 1.5200622
B84: 5 | C84: Unidades de transporte | H84: USD mm | J84: =254/1000 -> 0.254 | K84: =215/1000 -> 0.215 | L84: =196/1000 -> 0.196 | M84: =211/1000 -> 0.211 | N84: =188/1000 -> 0.188 | O84: =152/1000 -> 0.152 | P84: =P235 -> 0.0012387555 | Q84: =Q235 -> 0.0039088 | R84: =R235 -> 0.0054975226 | S84: =S235 -> 0.0070862453 | T84: =T235 -> 0.0087266792
B85: 6 | C85: Muebles y enseres | H85: USD mm | J85: =951/1000 -> 0.951 | K85: =953/1000 -> 0.953 | L85: =1052/1000 -> 1.052 | M85: =1031/1000 -> 1.031 | N85: =532/1000 -> 0.532 | O85: =421/1000 -> 0.421 | P85: =P264 -> 0.0042391822 | Q85: =Q264 -> 0.013376421 | R85: =R264 -> 0.018813236 | S85: =S264 -> 0.024250051 | T85: =T264 -> 0.028489233
B86: 7 | C86: Equipos diversos | H86: USD mm | J86: =23353/1000 -> 23.353 | K86: =18103/1000 -> 18.103 | L86: =22966/1000 -> 22.966 | M86: =24321/1000 -> 24.321 | N86: =24190/1000 -> 24.19 | O86: =21528/1000 -> 21.528 | P86: =P293 -> 0.39433735 | Q86: =Q293 -> 1.2443019 | R86: =R293 -> 1.7500455 | S86: =S293 -> 2.2557891 | T86: =T293 -> 2.7779941
B87: 8 | C87: Unidades por recibir | H87: USD mm | J87: 0 | K87: 0 | L87: 0 | M87: 0 | N87: 0 | O87: 0 | P87: =P322 -> 0 | Q87: =Q322 -> 0 | R87: =R322 -> 0 | S87: =S322 -> 0 | T87: =T322 -> 0
B88: 9 | C88: Obras en curso | H88: USD mm | J88: 0 | K88: 0 | L88: 0 | M88: 0 | N88: 0 | O88: 0 | P88: =P351 -> 0 | Q88: =Q351 -> 0 | R88: =R351 -> 0 | S88: =S351 -> 0 | T88: =T351 -> 0
C89: Total depreciación del periodo | H89: USD mm | J89: =+SUM(J80:J88) -> 113.456 | K89: =+SUM(K80:K88) -> 85.441 | L89: =+SUM(L80:L88) -> 96.667 | M89: =+SUM(M80:M88) -> 111.453 | N89: =+SUM(N80:N88) -> 109.222 | O89: =+SUM(O80:O88) -> 111.835 | P89: =+SUM(P80:P88) -> 0.73076098 | Q89: =+SUM(Q80:Q88) -> 2.3058614 | ... T89: =+SUM(T80:T88) -> 5.146628
C91: Deterioro acumulado
B92: 1 | C92: Terreno | H92: USD mm | J92: 0 | K92: 0 | L92: 0 | M92: 0 | N92: 0 | O92: 0 | P92: =+O92 -> 0 | Q92: =+P92 -> 0 | R92: =+Q92 -> 0 | S92: =+R92 -> 0 | T92: =+S92 -> 0
B93: 2 | C93: Edificios y otras construcciones | H93: USD mm | J93: =+-19613/1000 -> -19.613 | K93: =+-8020/1000 -> -8.02 | L93: 0 | M93: =58455/1000 -> 58.455 | N93: =(-25058+33634)/1000 -> 8.576 | O93: 0 | P93: =+O93 -> 0 | Q93: =+P93 -> 0 | R93: =+Q93 -> 0 | S93: =+R93 -> 0 | T93: =+S93 -> 0
B94: 3 | C94: Infraestructura de programa de manejo ambiental | H94: USD mm | J94: 0 | K94: 0 | L94: 0 | M94: 0 | N94: 0 | O94: 0 | P94: =+O94 -> 0 | Q94: =+P94 -> 0 | R94: =+Q94 -> 0 | S94: =+R94 -> 0 | T94: =+S94 -> 0
B95: 4 | C95: Maquinaria y equipo | H95: USD mm | J95: 0 | K95: 0 | L95: 0 | M95: =-143/1000 -> -0.143 | N95: 0 | O95: 0 | P95: =+O95 -> 0 | Q95: =+P95 -> 0 | R95: =+Q95 -> 0 | S95: =+R95 -> 0 | T95: =+S95 -> 0
B96: 5 | C96: Unidades de transporte | H96: USD mm | J96: 0 | K96: 0 | L96: 0 | M96: 0 | N96: 0 | O96: 0 | P96: =+O96 -> 0 | Q96: =+P96 -> 0 | R96: =+Q96 -> 0 | S96: =+R96 -> 0 | T96: =+S96 -> 0
B97: 6 | C97: Muebles y enseres | H97: USD mm | J97: 0 | K97: =+-20/1000 -> -0.02 | L97: =+-59/1000 -> -0.059 | M97: 0 | N97: 0 | O97: 0 | P97: =+O97 -> 0 | Q97: =+P97 -> 0 | R97: =+Q97 -> 0 | S97: =+R97 -> 0 | T97: =+S97 -> 0
B98: 7 | C98: Equipos diversos | H98: USD mm | J98: 0 | K98: =+-698/1000 -> -0.698 | L98: =+-4587/1000 -> -4.587 | M98: =-1747/1000 -> -1.747 | N98: 0 | O98: 0 | P98: =+O98 -> 0 | Q98: =+P98 -> 0 | R98: =+Q98 -> 0 | S98: =+R98 -> 0 | T98: =+S98 -> 0
B99: 8 | C99: Unidades por recibir | H99: USD mm | J99: 0 | K99: =-5/1000 -> -0.005 | L99: 0 | M99: =-81/1000 -> -0.081 | N99: 0 | O99: 0 | P99: =+O99 -> 0 | Q99: =+P99 -> 0 | R99: =+Q99 -> 0 | S99: =+R99 -> 0 | T99: =+S99 -> 0
B100: 9 | C100: Obras en curso | H100: USD mm | J100: 0 | K100: =-1665/1000 -> -1.665 | L100: =+-6740/1000 -> -6.74 | M100: =-12563/1000 -> -12.563 | N100: 0 | O100: 0 | P100: =+O100 -> 0 | Q100: =+P100 -> 0 | R100: =+Q100 -> 0 | S100: =+R100 -> 0 | T100: =+S100 -> 0
C101: Deterioro acumulado | H101: USD mm | J101: =+SUM(J92:J100) -> -19.613 | K101: =+SUM(K92:K100) -> -10.408 | L101: =+SUM(L92:L100) -> -11.386 | M101: =+SUM(M92:M100) -> 43.921 | N101: =+SUM(N92:N100) -> 8.576 | O101: =+SUM(O92:O100) -> 0 | P101: =SUM(P92:P100) -> 0 | Q101: =SUM(Q92:Q100) -> 0 | R101: =SUM(R92:R100) -> 0 | S101: =SUM(S92:S100) -> 0 | T101: =SUM(T92:T100) -> 0
C103: Desglose del capex, por activo fijo (en %)
B104: 1 | C104: Terreno | H104: % | J104: =+IFERROR(J53/$J$62,"") -> 0.027781346 | K104: =+IFERROR(K53/$K$62,"") -> 0.0023549665 | L104: =+IFERROR(L53/$L$62,"") -> 0 | M104: =+IFERROR(M53/$M$62,"") -> 0.0029499436 | N104: =+IFERROR(N53/$N$62,"") -> 0.00380969 | O104: =+IFERROR(O53/$O$62,"") -> 0 | P104: =AVERAGE(M104:O104) -> 0.0022532112 | Q104: =P104 -> 0.0022532112 | R104: =Q104 -> 0.0022532112 | S104: =R104 -> 0.0022532112 | T104: =S104 -> 0.0022532112
B105: 2 | C105: Edificios y otras construcciones | H105: % | J105: =+IFERROR(J54/$J$62,"") -> 0.10010532 | K105: =+IFERROR(K54/$K$62,"") -> 0.0036867407 | L105: =+IFERROR(L54/$L$62,"") -> 0.022234305 | M105: =+IFERROR(M54/$M$62,"") -> 0.057917741 | N105: =+IFERROR(N54/$N$62,"") -> 0.052303263 | O105: =+IFERROR(O54/$O$62,"") -> 0.0080421755 | P105: =AVERAGE(M105:O105) -> 0.03942106 | Q105: =P105 -> 0.03942106 | R105: =Q105 -> 0.03942106 | S105: =R105 -> 0.03942106 | T105: =S105 -> 0.03942106
B106: 3 | C106: Infraestructura de programa de manejo ambiental | H106: % | J106: =+IFERROR(J55/$J$62,"") -> 0 | K106: =+IFERROR(K55/$K$62,"") -> 0 | L106: =+IFERROR(L55/$L$62,"") -> 0 | M106: =+IFERROR(M55/$M$62,"") -> 0 | N106: =+IFERROR(N55/$N$62,"") -> 0 | O106: =+IFERROR(O55/$O$62,"") -> 0 | P106: =AVERAGE(M106:O106) -> 0 | Q106: =P106 -> 0 | R106: =Q106 -> 0 | S106: =R106 -> 0 | T106: =S106 -> 0
B107: 4 | C107: Maquinaria y equipo | H107: % | J107: =+IFERROR(J56/$J$62,"") -> 0.097523697 | K107: =+IFERROR(K56/$K$62,"") -> 0.17209121 | L107: =+IFERROR(L56/$L$62,"") -> 0.18750607 | M107: =+IFERROR(M56/$M$62,"") -> 0.12605217 | N107: =+IFERROR(N56/$N$62,"") -> 0.026638748 | O107: =+IFERROR(O56/$O$62,"") -> 0.045737223 | P107: =AVERAGE(M107:O107) -> 0.066142715 | Q107: =P107 -> 0.066142715 | R107: =Q107 -> 0.066142715 | S107: =R107 -> 0.066142715 | T107: =S107 -> 0.066142715
B108: 5 | C108: Unidades de transporte | H108: % | J108: =+IFERROR(J57/$J$62,"") -> 0.0024274962 | K108: =+IFERROR(K57/$K$62,"") -> 0.00074709283 | L108: =+IFERROR(L57/$L$62,"") -> 0.003776919 | M108: =+IFERROR(M57/$M$62,"") -> 0.0023939333 | N108: =+IFERROR(N57/$N$62,"") -> -0.00071249927 | O108: =+IFERROR(O57/$O$62,"") -> 0 | P108: =AVERAGE(M108:O108) -> 0.00056047801 | Q108: =P108 -> 0.00056047801 | R108: =Q108 -> 0.00056047801 | S108: =R108 -> 0.00056047801 | T108: =S108 -> 0.00056047801
B109: 6 | C109: Muebles y enseres | H109: % | J109: =+IFERROR(J58/$J$62,"") -> 0.0055742506 | K109: =+IFERROR(K58/$K$62,"") -> 0.0082829858 | L109: =+IFERROR(L58/$L$62,"") -> 0.0067576752 | M109: =+IFERROR(M58/$M$62,"") -> 0.0045716404 | N109: =+IFERROR(N58/$N$62,"") -> 0.00081428488 | O109: =+IFERROR(O58/$O$62,"") -> 0.00056535504 | P109: =AVERAGE(M109:O109) -> 0.0019837601 | Q109: =P109 -> 0.0019837601 | R109: =Q109 -> 0.0019837601 | S109: =R109 -> 0.0019837601 | T109: =S109 -> 0.0019837601
B110: 7 | C110: Equipos diversos | H110: % | J110: =+IFERROR(J59/$J$62,"") -> 0.21788384 | K110: =+IFERROR(K59/$K$62,"") -> 0.22461508 | L110: =+IFERROR(L59/$L$62,"") -> 0.22804241 | M110: =+IFERROR(M59/$M$62,"") -> 0.21677452 | N110: =+IFERROR(N59/$N$62,"") -> 0.16839702 | O110: =+IFERROR(O59/$O$62,"") -> 0.14536692 | P110: =AVERAGE(M110:O110) -> 0.17684615 | Q110: =P110 -> 0.17684615 | R110: =Q110 -> 0.17684615 | S110: =R110 -> 0.17684615 | T110: =S110 -> 0.17684615
B111: 8 | C111: Unidades por recibir | H111: % | J111: =+IFERROR(J60/$J$62,"") -> 0.051375581 | K111: =+IFERROR(K60/$K$62,"") -> 0.098518807 | L111: =+IFERROR(L60/$L$62,"") -> 0 | M111: =+IFERROR(M60/$M$62,"") -> 0.0099464068 | N111: =+IFERROR(N60/$N$62,"") -> 0.027249462 | O111: =+IFERROR(O60/$O$62,"") -> 0.0031377205 | P111: =AVERAGE(M111:O111) -> 0.01344453 | Q111: =P111 -> 0.01344453 | R111: =Q111 -> 0.01344453 | S111: =R111 -> 0.01344453 | T111: =S111 -> 0.01344453
B112: 9 | C112: Obras en curso | H112: % | J112: =+IFERROR(J61/$J$62,"") -> 0.49732847 | K112: =+IFERROR(K61/$K$62,"") -> 0.48970311 | L112: =+IFERROR(L61/$L$62,"") -> 0.55168262 | M112: =+IFERROR(M61/$M$62,"") -> 0.57939364 | N112: =+IFERROR(N61/$N$62,"") -> 0.72150003 | O112: =+IFERROR(O61/$O$62,"") -> 0.79715061 | P112: =AVERAGE(M112:O112) -> 0.69934809 | Q112: =P112 -> 0.69934809 | R112: =Q112 -> 0.69934809 | S112: =R112 -> 0.69934809 | T112: =S112 -> 0.69934809
A114: x | B114: Proyección de PPE
C116: 1) Terreno
C117: Saldo inicial del activo bruto | H117: USD mm | J117: =+$E$41 | K117: =+$J$41 -> 31.353 | L117: =+$K$41 -> 31.498 | M117: =+$L$41 -> 23.537 | N117: =+$M$41 -> 23.919 | O117: =+$N$41 -> 23.573 | P117: =+O120 -> 23.106 | Q117: =+P120 -> 23.310311 | R117: =+Q120 -> 23.546377 | S117: =+R120 -> 23.808408 | T117: =+S120 -> 24.07044
...

Sheet Wacc
B2: VOLCAN COMPAÑÍA MINERA
B3: Análisis WACC
B4: (US$ millones)
B6: Cálculo de la WACC | G6: Empresas comparables beta desapalancado
B7: Estructura de capital del Target | G7: Empresas | H7: Ticket | I7: País | J7: Beta apalancado | K7: Total deuda (Millones) | L7: Market Equity(Millones) | M7: Debt/ Equity | N7: Tax Rate | O7: Beta desapalancado
G8: Coeur Mining Inc DRC | H8: CDE | I8: Estados Unidos | J8: 1.98 | K8: 528.5 | L8: 2150 | M8: =K8/L8 -> 0.24581395 | N8: 0 | O8: =IFERROR(J8/((1+M8)*(1-N8)),"-") -> 1.5893224
B9: Deuda / (Deuda + Patrimonio) | E9: =(Buildup!E57+Buildup!E67)/(Buildup!E57+Buildup!E67+Buildup!E83) -> 0.5838733 | G9: Endeavour Silver Corp | H9: EDR | I9: Canadá | J9: 1.35 | K9: 5.8 | L9: 1020 | M9: =K9/L9 -> 0.0056862745 | N9: 0.6 | O9: =IFERROR(J9/((1+M9)*(1-N9)),"-") -> 3.3559173
B10: Patrimonio / (Deuda + Patrimonio) | E10: =1-E9 -> 0.4161267 | G10: Eldorado Gold Corp | H10: ELD | I10: Canadá | J10: 0.85 | K10: 592.5 | L10: 2800 | M10: =K10/L10 -> 0.21160714 | N10: 0.35 | O10: =IFERROR(J10/((1+M10)*(1-N10)),"-") -> 1.0793039
G11: Fortuna Mining CorpFortuna Mining Corp | H11: FVI | I11: Canadá | J11: 1.1 | K11: 165 | L11: 1350 | M11: =K11/L11 -> 0.12222222 | N11: 0.5 | O11: =IFERROR(J11/((1+M11)*(1-N11)),"-") -> 1.960396
B12: Costo de deuda (Kd) | G12: Buenaventura S.A.A | H12: BUENAVC1 | I12: Perú | J12: 1.3 | K12: 598 | L12: 3100 | M12: =K12/L12 -> 0.19290323 | N12: 0.39 | O12: =IFERROR(J12/((1+M12)*(1-N12)),"-") -> 1.7865217
B13: Costo de deuda ( US$ ) | E13: ='Supuestos '!K170 -> 0.1019625 | G13: Industrias Penoles SAB de CV | H13: IPOA.F | I13: México | J13: 0.75 | K13: 1950 | L13: 6500 | M13: =K13/L13 -> 0.3 | N13: 0.3 | O13: =IFERROR(J13/((1+M13)*(1-N13)),"-") -> 0.82417582
B14: Tasa de impuestos | E14: 0.295
B15: Costo de deuda después de impuesto ( US$ ) | E15: =E13*(1-E14) -> 0.071883563 | G15: Promedio | J15: =AVERAGE(J8:J13) -> 1.2216667 | K15: =AVERAGE(K8:K13) -> 639.96667 | L15: =AVERAGE(L8:L13) -> 2820 | M15: =AVERAGE(M8:M13) -> 0.17970547 | N15: =AVERAGE(N8:N13) -> 0.35666667 | O15: =AVERAGE(O8:O13) -> 1.7659395
G16: Mediana | J16: =MEDIAN(J8:J13) -> 1.2 | K16: =MEDIAN(K8:K13) -> 560.5 | L16: =MEDIAN(L8:L13) -> 2475 | M16: =MEDIAN(M8:M13) -> 0.20225518 | N16: =MEDIAN(N8:N13) -> 0.37 | O16: =MEDIAN(O8:O13) -> 1.6879221
B17: Costo de equity (Ke)
B18: Tasa libe de riesgo (1) | E18: 0.0458 | G18: Beta desapalancado del sector según Damodaran | I18: 0.91
B19: Rendimiento esperado del mercado (Rm) (2) | E19: 0.1355
B20: Rendimiento esperado del bono del tesoro (Rf) | E20: 0.0652 | G20: Beta apalancado del Target
B21: Prima de Riesgo de Mercado (ERP) | E21: =E19-E20 -> 0.0703 | K21: Promedio de | L21: Deuda/ | M21: Tasa de | N21: Beta
B22: Beta apalacando | E22: =N25 -> 1.6264277 | K22: beta | L22: Patrimonio del | M22: impuestos del | N22: apalancado
B23: Riesgo país (Rp) (5) | E23: 0.0126 | K23: desapalancado | L23: Target | M23: Target
B24: Costo de equity (Ke) (US$) | E24: =E18+E22*E21+E23 -> 0.17273787 | G24: Beta apalancado, según comparables | K24: =O15 -> 1.7659395 | L24: =E9/E10 -> 1.4031143 | M24: =N15 -> 0.35666667 | N24: =K24*(1+L24)*(1-M24) -> 2.7301487
B25: Riesgo de divisa | E25: =E52 -> 0.01541 | G25: Beta apalancado, según Damodaran | K25: 0.96 | L25: =L24 -> 1.4031143 | M25: =E14 -> 0.295 | N25: =K25*(1+L25)*(1-M25) -> 1.6264277
B26: Costo de equity (Ke) ( PEN) | E26: =E24+E25 -> 0.18814787
G27: Análisis de sensibilidad de la WACC
B28: WACC (US$) | E28: =E15*E9+E24*E10 -> 0.11385173
K29: Costo de deuda antes de impuestos
I30: D/(D+E) | J30: =E28 -> 0.11385173 | K30: =L30-0.5% -> 0.092 | L30: =M30-0.5% -> 0.097 | M30: 0.102 | N30: =M30+0.5% -> 0.107 | O30: =N30+0.5% -> 0.112
J31: =J32-10% -> 0.384 | K31: 0.10845968 | L31: 0.10981328 | M31: 0.11116688 | N31: 0.11252048 | O31: 0.11387408
J32: =J33-10% -> 0.484 | K32: 0.10910568 | L32: 0.11081178 | M32: 0.11251788 | N32: 0.11422398 | O32: 0.11593008
J33: 0.584 | K33: 0.10975168 | L33: 0.11181028 | M33: 0.11386888 | N33: 0.11592748 | O33: 0.11798608
J34: =J33+10% -> 0.684 | K34: 0.11039768 | L34: 0.11280878 | M34: 0.11521988 | N34: 0.11763098 | O34: 0.12004208
J35: =J34+10% -> 0.784 | K35: 0.11104368 | L35: 0.11380728 | M35: 0.11657088 | N35: 0.11933448 | O35: 0.12209808
B38: (1) Rendimiento del bono del Tesoro USA a 20 años, obtenido en Treasury.gov.
B39: (2) Fuente: Damodaran
B40: (3) Fuente: Damodaran
B41: (4) Fuente: Damodaran
B42: (5) Resultado del EMBIG Perú al 18/09/2025, obtenido del BCRP
B44: Riesgo país (Rp)
B45: Bono emitido por Estados Unidos en US$ | E45: =E18 -> 0.0458
B46: Bono emitido por Perú en US$ | E46: 0.05683
B47: Tasa riesgo país | E47: =E46-E45 -> 0.01103
B49: Riesgo divisa
B50: Bono emitido por Perú en US$ | E50: =E46 -> 0.05683
B51: Bono emitido por Perú en PEN | E51: 0.07224
B52: Riesgo divisa | E52: =E51-E50 -> 0.01541

Sheet Comparables
B2: Empresas | C2: País | D2: Nombre | E2: Ticket | F2: EV/EBITDA | G2: EV/Ventas | H2: PER | I2: Market Cap (Millones)
B3: Empresa 1 | C3: Perú | D3: Compania de Minas Buenaventura SAA | E3: BUENAVC1 | F3: 8.2 | G3: 3,0 | H3: 12.3 | I3: =18121 -> 18121
B4: Empresa 2 | C4: Estados Unidos | D4: Coeur Mining Inc DRC | E4: CDE | F4: 12.8 | G4: 5,3 | H4: 21.7 | I4: 29925
B5: Empresa 3 | C5: Canadá | D5: Endeavour Silver Corp | E5: EDR | F5: 56.8 | G5: 9,3 | H5: - | I5: 7330
B6: Empresa 4 | C6: =C7 -> Canadá | D6: Eldorado Gold Corp | E6: ELD | F6: 5.6 | G6: 3,1 | H6: 13.3 | I6: 16862
B7: Empresa 5 | C7: Canadá | D7: Fortuna Mining Corp | E7: FVI | F7: 4.1 | G7: 1,9 | H7: 14.1 | I7: 8106
B8: Empresa 6 | C8: México | D8: Industrias Penoles SAB de CV | E8: IPOA.F | F8: 6.4 | G8: 2,2 | H8: 16.7 | I8: 51770
B9: Fuente: Investing.com
E11: Mediana | F11: =MEDIAN(F3:F8) -> 7.3 | H11: =MEDIAN(H3:H8) -> 14.1
E12: Promedio | F12: =AVERAGE(F3:F8) -> 15.65 | H12: =AVERAGE(H3:H8) -> 15.62

Sheet Valoración
B2: VOLCAN COMPAÑÍA MINERA
B3: Análisis de flujos de caja descontados (DCF)
B4: (USD millones)
E6: Periodo histórico | I6: CAGR | K6: Periodo de proyección | P6: CAGR
E7: 2020 | F7: 2021 | G7: 2022 | H7: 2023 | I7: ('20 - '23) | J7: 2024 | K7: 2025 | L7: 2026 | M7: 2027 | N7: 2028 | O7: 2029 | P7: ('24 - '29)
B8: Ventas | E8: =Buildup!F6 -> 535.469 | F8: =Buildup!G6 -> 937.399 | G8: =Buildup!H6 -> 951.266 | H8: =Buildup!I6 -> 883.086 | I8: =(H8/E8)^(1/(H$7-E$7))-1 -> 0.18147052 | J8: =Buildup!J6 -> 960.521 | K8: =Buildup!K6 -> 922.27501 | L8: =Buildup!L6 -> 1065.6195 | M8: =Buildup!M6 -> 1182.8316 | N8: =Buildup!N6 -> 1182.8316 | O8: =Buildup!O6 -> 1221.3316 | P8: =(O8/J8)^(1/(O$7-J$7))-1 -> 0.049217067
B9: Variación anual % | E9: ='Supuestos '!G15 -> -0.27987514 | F9: ='Supuestos '!H15 -> 0.75061301 | G9: ='Supuestos '!I15 -> 0.01479306 | H9: ='Supuestos '!J15 -> -0.071672907 | J9: ='Supuestos '!K15 -> 0.087686816 | K9: ='Supuestos '!L15 -> -0.039817962 | L9: ='Supuestos '!M15 -> 0.15542488 | M9: ='Supuestos '!N15 -> 0.10999434 | N9: ='Supuestos '!O15 -> 0 | O9: ='Supuestos '!P15 -> 0.032549012
B10: EBITDA | E10: =Buildup!F21 -> 70.413 | F10: =Buildup!G21 -> 376.993 | G10: =Buildup!H21 -> 134.797 | H10: =Buildup!I21 -> 227.696 | I10: =(H10/E10)^(1/(H$7-E$7))-1 -> 0.47877075 | J10: =Buildup!J21 -> 485.474 | K10: =Buildup!K21 -> 365.72108 | L10: =Buildup!L21 -> 420.33217 | M10: =Buildup!M21 -> 468.37558 | N10: =Buildup!N21 -> 468.04624 | O10: =Buildup!O21 -> 484.26848 | P10: =(O10/J10)^(1/(O$7-J$7))-1 -> -0.00049713134
B11: Margen EBITDA % | E11: =E10/E8 -> 0.13149781 | F11: =F10/F8 -> 0.40216919 | G11: =G10/G8 -> 0.14170274 | H11: =H10/H8 -> 0.25784125 | J11: =J10/J8 -> 0.50542778 | K11: =K10/K8 -> 0.39654232 | L11: =L10/L8 -> 0.39444865 | M11: =M10/M8 -> 0.39597824 | N11: =N10/N8 -> 0.39569981 | O11: =O10/O8 -> 0.39650859
B12: Depreciación y Amortización (D&A) | E12: =Buildup!F20 -> 165.496 | F12: =Buildup!G20 -> 224.794 | G12: =Buildup!H20 -> 194.238 | H12: =Buildup!I20 -> 207.115 | J12: =Buildup!J20 -> 194.964 | K12: =Buildup!K20 -> 70.810647 | L12: =Buildup!L20 -> 73.119451 | M12: =Buildup!M20 -> 82.146703 | N12: =Buildup!N20 -> 84.337603 | O12: =Buildup!O20 -> 86.191289
B13: EBIT | E13: =E10+E12 -> 235.909 | F13: =F10+F12 -> 601.787 | G13: =G10+G12 -> 329.035 | H13: =H10+H12 -> 434.811 | I13: =(H13/E13)^(1/(H$7-E$7))-1 -> 0.22607961 | J13: =J10+J12 -> 680.438 | K13: =K10+K12 -> 436.53172 | L13: =L10+L12 -> 493.45162 | M13: =M10+M12 -> 550.52228 | N13: =N10+N12 -> 552.38384 | O13: =O10+O12 -> 570.45977 | P13: =(O13/J13)^(1/(O$7-J$7))-1 -> -0.034644463
B14: Margen EBIT % | E14: =E13/E8 -> 0.44056519 | F14: =F13/F8 -> 0.6419753 | G14: =G13/G8 -> 0.34589169 | H14: =H13/H8 -> 0.49237673 | J14: =J13/J8 -> 0.70840513 | K14: =K13/K8 -> 0.47332056 | L14: =L13/L8 -> 0.4630655 | M14: =M13/M8 -> 0.46542744 | N14: =N13/N8 -> 0.46700126 | O14: =O13/O8 -> 0.46708016
B15: (-) impuestos | D15: 0.295 | E15: =E13*$D$15 -> 69.593155 | F15: =F13*$D$15 -> 177.52716 | G15: =G13*$D$15 -> 97.065325 | H15: =H13*$D$15 -> 128.26925 | J15: =J13*$D$15 -> 200.72921 | K15: =K13*$D$15 -> 128.77686 | L15: =L13*$D$15 -> 145.56823 | M15: =M13*$D$15 -> 162.40407 | N15: =N13*$D$15 -> 162.95323 | O15: =O13*$D$15 -> 168.28563
B16: (+) D&A | E16: =E12 -> 165.496 | F16: =F12 -> 224.794 | G16: =G12 -> 194.238 | H16: =H12 -> 207.115 | J16: =J12 -> 194.964 | K16: =K12 -> 70.810647 | L16: =L12 -> 73.119451 | M16: =M12 -> 82.146703 | N16: =N12 -> 84.337603 | O16: =O12 -> 86.191289
B17: (+/-) Variación de WK operativo | E17: =Buildup!F93 -> 27.591 | F17: =Buildup!G93 -> -6.835 | G17: =Buildup!H93 -> 39.497 | H17: =Buildup!I93 -> 8.032 | J17: =Buildup!J93 -> -55.428 | K17: =Buildup!K93 -> 20.646399 | L17: =Buildup!L93 -> 21.574589 | M17: =Buildup!M93 -> 17.641441 | N17: =Buildup!N93 -> 229.1741 | O17: =Buildup!O93 -> -223.37952
B18: (-) Capex | E18: =-Capex!K27 -> -113.899 | F18: =-Capex!L27 -> -191.081 | G18: =-Capex!M27 -> -253.716 | H18: =-Capex!N27 -> -170.405 | J18: =-Capex!O27 -> -154.068 | K18: =-Capex!P27 -> -190.3304 | L18: =-Capex!Q27 -> -219.91248 | M18: =-Capex!R27 -> -244.1016 | N18: =-Capex!S27 -> -244.1016 | O18: =-Capex!T27 -> -252.04687
B19: Flujos de caja libe (FCF) | E19: =E13+E15+E16+E17+E18 -> 384.69016 | F19: =F13+F15+F16+F17+F18 -> 806.19217 | G19: =G13+G15+G16+G17+G18 -> 406.11933 | H19: =H13+H15+H16+H17+H18 -> 607.82224 | J19: =J13+J15+J16+J17+J18 -> 866.63521 | K19: =K13+K15+K16+K17+K18 -> 466.43523 | L19: =L13+L15+L16+L17+L18 -> 513.80142 | M19: =M13+M15+M16+M17+M18 -> 568.6129 | N19: =N13+N15+N16+N17+N18 -> 784.74718 | O19: =O13+O15+O16+O17+O18 -> 349.5103
B21: WACC | D21: =Wacc!E28 -> 0.11385173
B22: Periodo de descuento | K22: 0.5 | L22: =K22+1 -> 1.5 | M22: =L22+1 -> 2.5 | N22: =M22+1 -> 3.5 | O22: =N22+1 -> 4.5
B23: Factor descuento | K23: =1/(1+$D$21)^(K22) -> 0.94751547 | L23: =1/(1+$D$21)^(L22) -> 0.8506657 | M23: =1/(1+$D$21)^(M22) -> 0.76371538 | N23: =1/(1+$D$21)^(N22) -> 0.68565264 | O23: =1/(1+$D$21)^(O22) -> 0.61556904
B24: Valor actual de FCF | K24: =K23*K19 -> 441.95459 | L24: =L23*L19 -> 437.07325 | M24: =M23*M19 -> 434.25842 | N24: =N23*N19 -> 538.06398 | O24: =O23*O19 -> 215.14772
B27: Enterprise Value (EV) | G27: Valor implicito de las acciones y precio | L27: Tasa de crecimiento perpetuo implícito
B28: Valor actual acumulado de FCF | E28: =SUM(K19:O19) -> 2683.107 | G28: Enterprise Value | J28: =E38 -> 3530.472 | L28: FCF ( 2029P) | O28: =O19 -> 349.5103
G29: (-) Total deuda | J29: =-(Buildup!J57+Buildup!J67) -> -749.761 | L29: WACC | O29: =D21 -> 0.11385173
B30: Valor terminal | G30: (+) Efectivo y equivalente de efectivo | J30: =Buildup!J36 -> 155.834 | L30: Valor terminal | O30: =E33 -> 1452.8054
B31: EBITDA (2029P) | E31: =O10 -> 484.26848 | G31: Equity value implícito | J31: =SUM(J28:J30) -> 2936.545
B32: Múltiplo de salida (EV/EBITDA) | E32: 3 | G32: N° de acciones (millones) | J32: =3881340000/1000000 -> 3881.34 | L32: Tasa de crecimiento perpetuo implicito | O32: 0.03
B33: Valor terminal | E33: =E31*E32 -> 1452.8054 | G33: Precio objetivo | J33: =J31/J32 -> 0.75658021
B34: Factor descuento | E34: =1/(1+$D$21)^(5) -> 0.58326119 | L34: EV/ EBITDA implicito
B35: Valor presente de Valor Terminal | E35: =E33*E34 -> 847.36502 | G35: Precio actual (04/11/2025) | J35: 0.47 | L35: Enterprise Value | O35: =E38 -> 3530.472
B36: % de Enterprise Value | G36: Potencial de crecimiento (upside) | J36: =J33/J35-1 -> 0.60974513 | L36: EBITDA 2024 | O36: =J10 -> 485.474
B38: Enterprise Value | E38: =E35+E28 -> 3530.472 | L38: EV/ EBITDA implícito | O38: =O35/O36 -> 7.2722165
C40: Enterprise Value | J40: Equity Value
C41: Múltiplo de Salida | J41: Múltiplo de Salida
B42: WACC | C42: =E38 -> 3530.472 | D42: =E42-0.5 -> 2 | E42: =F42-0.5 -> 2.5 | F42: 3 | G42: =F42+0.5 -> 3.5 | H42: =G42+0.5 -> 4 | I42: WACC | J42: 2936.545 | K42: =L42-0.5 -> 2 | L42: =M42-0.5 -> 2.5 | M42: 3 | N42: =M42+0.5 -> 3.5 | O42: =N42+0.5 -> 4
C43: =C44-0.5% -> 0.10385173 | D43: 3274.073 | E43: 3421.8145 | F43: 3569.556 | G43: 3717.2975 | H43: 3865.039 | J43: =J44-0.5% -> 0.10385173 | K43: 2936.545 | L43: 2936.545 | M43: 2936.545 | N43: 2936.545 | O43: 2936.545
C44: =C45-0.5% -> 0.10885173 | D44: 3260.8688 | E44: 3405.3092 | F44: 3549.7497 | G44: 3694.1901 | H44: 3838.6306 | J44: =J45-0.5% -> 0.10885173 | K44: 2936.545 | L44: 2936.545 | M44: 2936.545 | N44: 2936.545 | O44: 2936.545
C45: 0.11385173 | D45: 3248.017 | E45: 3389.2445 | F45: 3530.472 | G45: 3671.6995 | H45: 3812.9271 | J45: 0.11385173 | K45: 2936.545 | L45: 2936.545 | M45: 2936.545 | N45: 2936.545 | O45: 2936.545
C46: =C45+0.5% -> 0.11885173 | D46: 3235.5068 | E46: 3373.6068 | F46: 3511.7067 | G46: 3649.8067 | H46: 3787.9066 | J46: =J45+0.5% -> 0.11885173 | K46: 2936.545 | L46: 2936.545 | M46: 2936.545 | N46: 2936.545 | O46: 2936.545
C47: =C46+0.5% -> 0.12385173 | D47: 3223.3276 | E47: 3358.3827 | F47: 3493.4378 | G47: 3628.493 | H47: 3763.5481 | J47: =J46+0.5% -> 0.12385173 | K47: 2936.545 | L47: 2936.545 | M47: 2936.545 | N47: 2936.545 | O47: 2936.545
C49: DCF | F49: Acotado
C50: Rango mínimo | F50: =PERCENTILE(D43:H47,0.25) -> 3373.6068
C51: Promedio | F51: =PERCENTILE(D43:H47,0.5) -> 3530.472
C52: Rango máximo | F52: =PERCENTILE(D43:H47,0.75) -> 3694.1901
E55: Mínimo | G55: Máximo
C56: DCF | E56: =F50 -> 3373.6068 | F56: =G56-E56 -> 320.58336 | G56: =F52 -> 3694.1901
C57: Ultimas 52 semanas | E57: =Hoja3!G6 -> 675.4609 | F57: =G57-E57 -> 492.48644 | G57: =Hoja3!G5 -> 1167.9473
C58: EV/EBITDA comps | E58: =Comparables!F11*J10+J29+J30 -> 2950.0332 | F58: =G58-E58 -> 4053.7079 | G58: =Comparables!F12*J10+J29+J30 -> 7003.7411
C59: P/E comps | E59: =Comparables!H11*Buildup!J29 -> 1933.5753 | F59: =G59-E59 -> 208.44216 | G59: =Comparables!H12*Buildup!J29 -> 2142.0175

Sheet Hoja3
B2: Promedio
B4: 0.30091343 | E4: Precio | F4: N acciones(mm) | G4: Valor Equity
B5: 0.28809104 | D5: MAX | E5: =MAX(B4:B251) -> 0.30091343 | F5: 3881.34 | G5: =E5*F5 -> 1167.9473
B6: 0.28274699 | D6: MIN | E6: =MIN(B4:B251) -> 0.17402776 | F6: 3881.34 | G6: =E6*F6 -> 675.4609
B7: 0.28179056
B8: 0.29137711
B9: 0.2858383
B10: 0.27086884
B11: 0.26895454
B12: 0.26520361
B13: 0.25994513
B14: 0.25695751
B15: 0.2504802
B16: 0.25689628
B17: 0.26480943
B18: 0.26397871
... B251: 0.18145144

Sheet Gráficos
C3: 2020 | D3: 2021 | E3: 2022 | F3: 2023 | G3: 2024
B4: Zinc | C4: 234.7 | D4: 454.8 | E4: 551.9 | F4: 427.2 | G4: 479.3
B5: Plomo | C5: 59.1 | D5: 104.4 | E5: 98.9 | F5: 113.9 | G5: 105
B6: Cobre | C6: 12.1 | D6: 26.6 | E6: 26.7 | F6: 29.1 | G6: 30.6
B7: Plata | C7: 212.2 | D7: 312.4 | E7: 257.7 | F7: 290.1 | G7: 324.1
B8: Oro | C8: 13.6 | D8: 36.4 | E8: 34.7 | F8: 30.1 | G8: 24.6
B9: Escorias | C9: 0 | D9: 0 | E9: 0 | F9: 0 | G9: 1.5
B10: Ventas antes de ajustes | C10: =+SUM(C4:C9) -> 531.7 | D10: =+SUM(D4:D9) -> 934.6 | E10: =+SUM(E4:E9) -> 969.9 | F10: =+SUM(F4:F9) -> 890.4 | G10: =+SUM(G4:G9) -> 965.1
B11: Ajustes | C11: 3.7 | D11: 2.6 | E11: -17.8 | F11: -7.4 | G11: -4.5
B12: Ventas Netas | C12: =+SUM(C10+C11) -> 535.4 | D12: =+SUM(D10+D11) -> 937.2 | E12: =+SUM(E10+E11) -> 952.1 | F12: =+SUM(F10+F11) -> 883 | G12: =+SUM(G10+G11) -> 960.6
B13: Variación Anual | C13: -0.28 | D13: =+(D12-C12)/C12 -> 0.75046694 | E13: =+(E12-D12)/D12 -> 0.015898421 | F13: =+(F12-E12)/E12 -> -0.07257641 | G13: =+(G12-F12)/F12 -> 0.08788222
